Workbook

Sheet Occupancy
B1: PROJECT PEGASUS - HISTORICAL OCCUPANCY
E3: Quarter Ending
B4: Property Name | C4: Submarket | D4: Square Footage | E4: 44476 | F4: 44561 | G4: 44651 | H4: 44742 | I4: 44834 | J4: 44926 | K4: 45016 | L4: 45107 | M4: 45199 | N4: 45291 | O4: 45382 | P4: 45473 | Q4: 45565 | R4: 45657 | S4: 45747 | T4: 45838 | U4: 45930 | V4: Current
B5: Reliance Broadway | C5: Airport | D5: 200813 | E5: 0.9891 | F5: 0.955 | G5: 0.96520146 | H5: 0.96520146 | I5: 0.98312858 | J5: 0.93333101 | K5: 0.94528243 | L5: 0.97117716 | M5: 0.96520146 | N5: 0.96520146 | O5: 0.97715287 | P5: 0.93333101 | Q5: 0.90544437 | R5: 0.8596306 | S5: 0.78314153 | T5: 0.79987351 | U5: 0.81471319
B6: Reliance Broadway - Building A | C6: Airport | D6: 77045 | E6: 1 | F6: 1 | G6: 1 | H6: 1 | I6: 1 | J6: 1 | K6: 1 | L6: 1 | M6: 1 | N6: 1 | O6: 1 | P6: 1 | Q6: 1 | R6: 1 | S6: 1 | T6: 1 | U6: 1
B7: Reliance Broadway - Building B | C7: Airport | D7: 107490 | E7: 1 | F7: 1 | G7: 1 | H7: 1 | I7: 1 | J7: 1 | K7: 1 | L7: 1 | M7: 1 | N7: 1 | O7: 1 | P7: 1 | Q7: 1 | R7: 1 | S7: 1 | T7: 1 | U7: 1
B8: Reliance Broadway - Building C-D-E | C8: Airport | D8: 115354 | E8: 1 | F8: 1 | G8: 1 | H8: 1 | I8: 1 | J8: 1 | K8: 1 | L8: 1 | M8: 1 | N8: 1 | O8: 0.96001006 | P8: 0.96867902 | Q8: 0.96867902 | R8: 0.96399778 | S8: 1 | T8: 1 | U8: 0.96867902
B9: Reliance Broadway - Building F | C9: Airport | D9: 103094 | E9: 1 | F9: 1 | G9: 1 | H9: 1 | I9: 1 | J9: 1 | K9: 1 | L9: 1 | M9: 1 | N9: 1 | O9: 1 | P9: 1 | Q9: 1 | R9: 1 | S9: 1 | T9: 1 | U9: 1
B10: Reliance Broadway | D10: =+D9+D8+D7+D6+D5 -> 603796 | E10: =+SUMPRODUCT(E5:E9,$D$5:$D$9)/$D$10 -> 0.99637483 | F10: =+SUMPRODUCT(F5:F9,$D$5:$D$9)/$D$10 -> 0.98503371 | G10: =+SUMPRODUCT(G5:G9,$D$5:$D$9)/$D$10 -> 0.98842655 | H10: =+SUMPRODUCT(H5:H9,$D$5:$D$9)/$D$10 -> 0.98842655 | I10: =+SUMPRODUCT(I5:I9,$D$5:$D$9)/$D$10 -> 0.99438883 | J10: =+SUMPRODUCT(J5:J9,$D$5:$D$9)/$D$10 -> 0.97782695 | K10: =+SUMPRODUCT(K5:K9,$D$5:$D$9)/$D$10 -> 0.9818018 | L10: =+SUMPRODUCT(L5:L9,$D$5:$D$9)/$D$10 -> 0.99041398 | ... U10: =+SUMPRODUCT(U5:U9,$D$5:$D$9)/$D$10 -> 0.93239273 | V10: =(Occupancy!D10-SUM('Occupancy Summary Schedule'!F4:F8))/Occupancy!D10 -> 0.92367124
A11: 880904 | B11: South 40 | C11: Airport | D11: 84412 | E11: 1 | F11: 1 | G11: 1 | H11: 1 | I11: 1 | J11: 1 | K11: 1 | L11: 1 | M11: 0.92607686 | N11: 0.96777709 | O11: 0.96777709 | P11: 1 | Q11: 0.88139127 | R11: 0.88139127 | S11: 0.9631569 | T11: 0.89918495 | U11: 0.8745439 | V11: ='Occupancy Summary Schedule'!E10 -> 0.8745439
B12: AIRPORT SUB-TOTAL | D12: =+D10+D11 -> 688208 | E12: =+SUMPRODUCT(E10:E11,$D$10:$D$11)/$D$12 -> 0.99681948 | F12: =+SUMPRODUCT(F10:F11,$D$10:$D$11)/$D$12 -> 0.9868694 | G12: =+SUMPRODUCT(G10:G11,$D$10:$D$11)/$D$12 -> 0.98984609 | H12: =+SUMPRODUCT(H10:H11,$D$10:$D$11)/$D$12 -> 0.98984609 | I12: =+SUMPRODUCT(I10:I11,$D$10:$D$11)/$D$12 -> 0.99507707 | J12: =+SUMPRODUCT(J10:J11,$D$10:$D$11)/$D$12 -> 0.98054658 | K12: =+SUMPRODUCT(K10:K11,$D$10:$D$11)/$D$12 -> 0.9840339 | L12: =+SUMPRODUCT(L10:L11,$D$10:$D$11)/$D$12 -> 0.99158975 | ... U12: =+SUMPRODUCT(U10:U11,$D$10:$D$11)/$D$12 -> 0.92529729 | V12: ='Occupancy Summary Schedule'!E11 -> 0.91764554
B14: Golden Key Plaza | C14: Chandler Gilbert | D14: 63714 | E14: 0.919 | F14: 0.90777537 | G14: 0.97377342 | H14: 1 | I14: 0.98130709 | J14: 0.98130709 | K14: 1 | L14: 1 | M14: 1 | N14: 0.98130709 | O14: 0.96073077 | P14: 0.92957592 | Q14: 0.96073077 | R14: 0.89711837 | S14: 0.90827762 | T14: 0.91893461 | U14: 0.94516119 | V14: ='Occupancy Summary Schedule'!E13 -> 0.94261858
B15: Chandler Technology Center | C15: Chandler Gilbert | D15: 113000 | E15: 0.965 | F15: 1 | G15: 0.93654867 | H15: 0.9359292 | I15: 0.9359292 | J15: 0.9359292 | K15: 0.9359292 | L15: 0.9359292 | M15: 0.9359292 | N15: 0.9359292 | O15: 0.94942478 | P15: 0.90888496 | Q15: 0.94219469 | R15: 0.94219469 | S15: 1 | T15: 1 | U15: 0.92911504 | V15: ='Occupancy Summary Schedule'!E14 -> 0.88383186
B16: Chicago Street Business Park | C16: Chandler Gilbert | D16: 54382 | E16: 1 | F16: 1 | G16: 1 | H16: 0.95426796 | I16: 0.90853591 | J16: 1 | K16: 1 | L16: 1 | M16: 1 | N16: 1 | O16: 1 | P16: 1 | Q16: 1 | R16: 1 | S16: 0.9451289 | T16: 0.60795852 | U16: 0.9421132 | V16: ='Occupancy Summary Schedule'!E15 -> 0.90853591
B17: Fiesta Center | C17: Chandler Gilbert | D17: 122693 | E17: 1 | F17: 0.938 | G17: 0.98384586 | H17: 0.98061829 | I17: 1 | J17: 0.96656696 | K17: 0.98425338 | L17: 1 | M17: 0.9818327 | N17: 1 | O17: 1 | P17: 1 | Q17: 1 | R17: 0.92834147 | S17: 0.92389134 | T17: 0.94327305 | U17: 0.73978141 | V17: ='Occupancy Summary Schedule'!E16 -> 0.75552803
B18: Fiesta Ranch Business Center | C18: Chandler Gilbert | D18: 56520 | E18: 1 | F18: 1 | G18: 1 | H18: 1 | I18: 1 | J18: 1 | K18: 1 | L18: 1 | M18: 0.84962845 | N18: 0.94803609 | O18: 1 | P18: 1 | Q18: 1 | R18: 1 | S18: 1 | T18: 1 | U18: 1 | V18: ='Occupancy Summary Schedule'!E17 -> 1
B19: Frye Road Business Center | C19: Chandler Gilbert | D19: 73291 | E19: 1 | F19: 0.981 | G19: 0.96425209 | H19: 1 | I19: 1 | J19: 1 | K19: 1 | L19: 0.98188045 | M19: 0.98188045 | N19: 0.9388738 | O19: 0.86110164 | P19: 0.90094282 | Q19: 0.78302929 | R19: 0.84360972 | S19: 0.90473592 | T19: 0.90066993 | U19: 0.84036239 | V19: ='Occupancy Summary Schedule'!E18 -> 0.84036239
B20: Oakland Business Park | C20: Chandler Gilbert | D20: 38501 | E20: 1 | F20: 1 | G20: 1 | H20: 1 | I20: 0.96093608 | J20: 1 | K20: 1 | L20: 0.95844264 | M20: 1 | N20: 1 | O20: 0.9657931 | P20: 0.9657931 | Q20: 1 | R20: 1 | S20: 1 | T20: 1 | U20: 1 | V20: ='Occupancy Summary Schedule'!E19 -> 1
B21: CHANDLER-GILBERT SUB-TOTAL | D21: =+SUM(D14:D20) -> 522101 | E21: =+SUMPRODUCT(E14:E20,$D$14:$D$20)/$D$21 -> 0.98254009 | F21: =+SUMPRODUCT(F14:F20,$D$14:$D$20)/$D$21 -> 0.9715084 | G21: =+SUMPRODUCT(G14:G20,$D$14:$D$20)/$D$21 -> 0.97425211 | H21: =+SUMPRODUCT(H14:H20,$D$14:$D$20)/$D$21 -> 0.97681483 | I21: =+SUMPRODUCT(I14:I20,$D$14:$D$20)/$D$21 -> 0.97144422 | J21: =+SUMPRODUCT(J14:J20,$D$14:$D$20)/$D$21 -> 0.97599507 | K21: =+SUMPRODUCT(K14:K20,$D$14:$D$20)/$D$21 -> 0.98243252 | L21: =+SUMPRODUCT(L14:L20,$D$14:$D$20)/$D$21 -> 0.98052484 | ... U21: =+SUMPRODUCT(U14:U20,$D$14:$D$20)/$D$21 -> 0.888376 | V21: ='Occupancy Summary Schedule'!E20 -> 0.87846796
B23: Central Deer Valley | C23: Deer Valley | D23: 52560 | E23: 1 | F23: 1 | G23: 1 | H23: 1 | I23: 1 | J23: 0.9766933 | K23: 0.93007991 | L23: 1 | M23: 1 | N23: 1 | O23: 1 | P23: 0.92161339 | Q23: 0.92161339 | R23: 0.88242009 | S23: 0.81992009 | T23: 0.81992009 | U23: 0.88242009 | V23: ='Occupancy Summary Schedule'!E22 -> 0.92161339
B24: Deer Valley Commerce Center | C24: Deer Valley | D24: 214400 | E24: 1 | F24: 1 | G24: 0.9591 | H24: 1 | I24: 0.98635728 | J24: 0.91512127 | K24: 1 | L24: 1 | M24: 0.98635728 | N24: 0.94240672 | O24: 0.94316231 | P24: 0.98560168 | Q24: 0.98635728 | R24: 0.94391791 | S24: 0.89010261 | T24: 0.86281716 | U24: 0.84776586 | V24: ='Occupancy Summary Schedule'!E23 -> 0.87645989
B25: Desert Ridge Industrial Park | C25: Deer Valley | D25: 52715 | E25: 1 | F25: 1 | G25: 1 | H25: 1 | I25: 1 | J25: 1 | K25: 1 | L25: 1 | M25: 1 | N25: 1 | O25: 1 | P25: 1 | Q25: 1 | R25: 1 | S25: 1 | T25: 1 | U25: 0.53343451 | V25: ='Occupancy Summary Schedule'!E24 -> 0.87597458
B26: Laser Drive Industrial | C26: Deer Valley | D26: 35597 | E26: 1 | F26: 1 | G26: 0.96451948 | H26: 0.93926454 | I26: 0.93926454 | J26: 0.93926454 | K26: 1 | L26: 1 | M26: 0.97022221 | N26: 1 | O26: 0.93926454 | P26: 0.93926454 | Q26: 1 | R26: 1 | S26: 1 | T26: 0.94505155 | U26: 0.88032699 | V26: ='Occupancy Summary Schedule'!E25 -> 0.84307666
B27: Perimeter Center | C27: Deer Valley | D27: 84028 | E27: 1 | F27: 0.9768 | G27: 0.97680535 | H27: 0.95599086 | I27: 0.95599086 | J27: 1 | K27: 1 | L27: 0.95288475 | M27: 0.95288475 | N27: 0.89091731 | O27: 0.81901271 | P27: 0.77500357 | Q27: 0.74975008 | R27: 0.84690817 | S27: 1 | T27: 1 | U27: 1 | V27: ='Occupancy Summary Schedule'!E26 -> 1
B28: Rose Garden Business Center | C28: Deer Valley | D28: 71016 | E28: 1 | F28: 0.9376 | G28: 0.96522954 | H28: 1 | I28: 1 | J28: 1 | K28: 1 | L28: 1 | M28: 1 | N28: 0.9718655 | O28: 1 | P28: 1 | Q28: 1 | R28: 0.95950208 | S28: 0.98593275 | T28: 0.96993635 | U28: 0.9732173 | V28: ='Occupancy Summary Schedule'!E27 -> 0.97040104
B29: DEER VALLEY SUB-TOTAL | D29: =+SUM(D23:D28) -> 510316 | E29: =+SUMPRODUCT(E23:E28,$D$23:$D$28)/$D$29 -> 1 | F29: =+SUMPRODUCT(F23:F28,$D$23:$D$28)/$D$29 -> 0.98749628 | G29: =+SUMPRODUCT(G23:G28,$D$23:$D$28)/$D$29 -> 0.97168378 | H29: =+SUMPRODUCT(H23:H28,$D$23:$D$28)/$D$29 -> 0.98851692 | I29: =+SUMPRODUCT(I23:I28,$D$23:$D$28)/$D$29 -> 0.98278518 | J29: =+SUMPRODUCT(J23:J28,$D$23:$D$28)/$D$29 -> 0.95770268 | K29: =+SUMPRODUCT(K23:K28,$D$23:$D$28)/$D$29 -> 0.99279858 | L29: =+SUMPRODUCT(L23:L28,$D$23:$D$28)/$D$29 -> 0.99224206 | ... U29: =+SUMPRODUCT(U23:U28,$D$23:$D$28)/$D$29 -> 0.86366095 | V29: ='Occupancy Summary Schedule'!E28 -> 0.91214659
B31: Falcon Field Industrial | C31: Mesa | D31: 40860 | E31: 1 | F31: 1 | G31: 1 | H31: 1 | I31: 1 | J31: 0.94517866 | K31: 1 | L31: 0.94517866 | M31: 1 | N31: 1 | O31: 1 | P31: 1 | Q31: 1 | R31: 1 | S31: 1 | T31: 1 | U31: 0.94517866 | V31: ='Occupancy Summary Schedule'!E30 -> 1
B32: Horne Commerce Center | C32: Mesa | D32: 59408 | E32: 0.9659 | F32: 1 | G32: 1 | H32: 1 | I32: 0.96323727 | J32: 1 | K32: 1 | L32: 1 | M32: 0.96323727 | N32: 1 | O32: 0.96323727 | P32: 0.96586318 | Q32: 0.96586318 | R32: 0.96586318 | S32: 1 | T32: 1 | U32: 0.8345004 | V32: ='Occupancy Summary Schedule'!E31 -> 0.87126313
B33: Mesa Business Park | C33: Mesa | D33: 64619 | E33: 0.9609 | F33: 1 | G33: 1 | H33: 0.96092481 | I33: 1 | J33: 1 | K33: 1 | L33: 0.88526594 | M33: 1 | N33: 0.96092481 | O33: 0.96227116 | P33: 0.92299478 | Q33: 0.84349804 | R33: 0.88257324 | S33: 0.72896517 | T33: 0.72896517 | U33: 0.68988997 | V33: ='Occupancy Summary Schedule'!E32 -> 0.80597038
B34: Southpoint Commerce Center | C34: Mesa | D34: 59194 | E34: 0.9673 | F34: 0.947 | G34: 0.96731088 | H34: 0.97712606 | I34: 0.97021658 | J34: 0.9191641 | K34: 0.9191641 | L34: 0.9191641 | M34: 0.95126195 | N34: 0.96942258 | O34: 0.94541677 | P34: 0.94541677 | Q34: 0.94594047 | R34: 0.91894449 | S34: 0.91894449 | T34: 0.96731088 | U34: 0.94443694 | V34: ='Occupancy Summary Schedule'!E33 -> 1
B35: Aero I | C35: Mesa | D35: 58816 | E35: 1 | F35: 1 | G35: 1 | H35: 1 | I35: 1 | J35: 1 | K35: 1 | L35: 1 | M35: 1 | N35: 1 | O35: 1 | P35: 1 | Q35: 0.84820457 | R35: 0.9171994 | S35: 1 | T35: 1 | U35: 1 | V35: ='Occupancy Summary Schedule'!E34 -> 0.68238234
B36: MESA SUB-TOTAL | D36: =+SUM(D31:D35) -> 282897 | E36: =+SUMPRODUCT(E31:E35,$D$31:$D$35)/$D$36 -> 0.97706565 | F36: =+SUMPRODUCT(F31:F35,$D$31:$D$35)/$D$36 -> 0.98891016 | G36: =+SUMPRODUCT(G31:G35,$D$31:$D$35)/$D$36 -> 0.99316005 | H36: =+SUMPRODUCT(H31:H35,$D$31:$D$35)/$D$36 -> 0.9862883 | I36: =+SUMPRODUCT(I31:I35,$D$31:$D$35)/$D$36 -> 0.98604793 | J36: =+SUMPRODUCT(J31:J35,$D$31:$D$35)/$D$36 -> 0.97516764 | K36: =+SUMPRODUCT(K31:K35,$D$31:$D$35)/$D$36 -> 0.98308572 | L36: =+SUMPRODUCT(L31:L35,$D$31:$D$35)/$D$36 -> 0.94896022 | ... U36: =+SUMPRODUCT(U31:U35,$D$31:$D$35)/$D$36 -> 0.87486612 | V36: ='Occupancy Summary Schedule'!E35 -> 0.86261077
B38: Broadway Industrial | C38: Tempe | D38: 43963 | E38: 0.98337238 | F38: 0.983 | G38: 0.92648363 | H38: 1 | I38: 1 | J38: 0.98337238 | K38: 1 | L38: 1 | M38: 1 | N38: 0.943134 | O38: 1 | P38: 1 | Q38: 1 | R38: 1 | S38: 0.829402 | T38: 0.772536 | U38: 0.65880399 | V38: ='Occupancy Summary Schedule'!E37 -> 0.71567
B39: Hayden Park | C39: Tempe | D39: 100134 | E39: 1 | F39: 1 | G39: 0.9857491 | H39: 1 | I39: 1 | J39: 1 | K39: 1 | L39: 0.96944095 | M39: 1 | N39: 1 | O39: 0.97009008 | P39: 0.97009008 | Q39: 0.92132542 | R39: 0.92132542 | S39: 0.93557633 | T39: 0.90606587 | U39: 0.90606587 | V39: ='Occupancy Summary Schedule'!E38 -> 0.85781053
B40: Hardy Center | C40: Tempe | D40: 49277 | E40: 1 | F40: 0.94407127 | G40: 1 | H40: 1 | I40: 1 | J40: 1 | K40: 1 | L40: 1 | M40: 0.95438034 | N40: 0.97236033 | O40: 0.97236033 | P40: 1 | Q40: 0.88221686 | R40: 0.95438034 | S40: 0.95438034 | T40: 0.95438034 | U40: 0.95438034 | V40: ='Occupancy Summary Schedule'!E39 -> 0.76516428
B41: Park Lane | C41: Tempe | D41: 51040 | E41: 0.96598746 | F41: 0.96598746 | G41: 0.94604232 | H41: 1 | I41: 1 | J41: 1 | K41: 1 | L41: 1 | M41: 0.97452978 | N41: 0.97452978 | O41: 1 | P41: 1 | Q41: 1 | R41: 0.93030956 | S41: 0.96598746 | T41: 0.96598746 | U41: 0.96598746 | V41: ='Occupancy Summary Schedule'!E40 -> 0.96598746
A42: 975543 | B42: University Business Center | C42: Tempe | D42: 34473 | E42: 1 | F42: 1 | G42: 1 | H42: 1 | I42: 1 | J42: 1 | K42: 1 | L42: 1 | M42: 1 | N42: 1 | O42: 1 | P42: 0.95660372 | Q42: 0.95660372 | R42: 1 | S42: 1 | T42: 1 | U42: 1 | V42: ='Occupancy Summary Schedule'!E41 -> 0.59991878
B43: TEMPE SUB-TOTAL | D43: =+SUM(D38:D42) -> 278887 | E43: =+SUMPRODUCT(E38:E42,$D$38:$D$42)/$D$43 -> 0.99115412 | F43: =+SUMPRODUCT(F38:F42,$D$38:$D$42)/$D$43 -> 0.98121328 | G43: =+SUMPRODUCT(G38:G42,$D$38:$D$42)/$D$43 -> 0.97341934 | H43: =+SUMPRODUCT(H38:H42,$D$38:$D$42)/$D$43 -> 1 | I43: =+SUMPRODUCT(I38:I42,$D$38:$D$42)/$D$43 -> 1 | J43: =+SUMPRODUCT(J38:J42,$D$38:$D$42)/$D$43 -> 0.99737887 | K43: =+SUMPRODUCT(K38:K42,$D$38:$D$42)/$D$43 -> 1 | L43: =+SUMPRODUCT(L38:L42,$D$38:$D$42)/$D$43 -> 0.98902781 | ... U43: =+SUMPRODUCT(U38:U42,$D$38:$D$42)/$D$43 -> 0.8982025 | V43: ='Occupancy Summary Schedule'!E42 -> 0.80695407
B47: SUMMARY
B48: Sub-Market | D48: Sq. Ft. | E48: Occupancy at Acquisition | F48: 44561 | G48: 44651 | H48: 44742 | I48: 44834 | J48: 44926 | K48: 45016 | L48: 45107 | M48: 45199 | N48: 45291 | O48: 45382 | P48: 45473 | Q48: =Q4 -> 45565 | R48: =R4 -> 45657 | S48: =S4 -> 45747 | T48: =T4 -> 45838 | U48: =U4 -> 45930 | V48: Current
B49: Airport | D49: =+D12 -> 688208 | E49: =+E12 -> 0.99681948 | F49: =+F12 -> 0.9868694 | G49: =+G12 -> 0.98984609 | H49: =+IF(H12=0%, "", H12) -> 0.98984609 | I49: =+IF(I12=0%, "", I12) -> 0.99507707 | J49: =+IF(J12=0%, "", J12) -> 0.98054658 | K49: =+IF(K12=0%, "", K12) -> 0.9840339 | L49: =+IF(L12=0%, "", L12) -> 0.99158975 | M49: =+IF(M12=0%, "", M12) -> 0.98077907 | N49: =+IF(N12=0%, "", N12) -> 0.9858938 | O49: =+IF(O12=0%, "", O12) -> 0.9826782 | ... V49: =+IF(V12=0%, "", V12) -> 0.91764554
B50: Chandler-Gilbert | D50: =+D21 -> 522101 | E50: =+E21 -> 0.98254009 | F50: =+F21 -> 0.9715084 | G50: =+G21 -> 0.97425211 | H50: =+IF(H21=0%, "", H21) -> 0.97681483 | I50: =+IF(I21=0%, "", I21) -> 0.97144422 | J50: =+IF(J21=0%, "", J21) -> 0.97599507 | K50: =+IF(K21=0%, "", K21) -> 0.98243252 | L50: =+IF(L21=0%, "", L21) -> 0.98052484 | M50: =+IF(M21=0%, "", M21) -> 0.96304163 | N50: =+IF(N21=0%, "", N21) -> 0.96964572 | O50: =+IF(O21=0%, "", O21) -> 0.96224102 | ... V50: =+IF(V21=0%, "", V21) -> 0.87846796
B51: Deer Valley | D51: =+D29 -> 510316 | E51: =+E29 -> 1 | F51: =+F29 -> 0.98749628 | G51: =+G29 -> 0.97168378 | H51: =+IF(H29=0%, "", H29) -> 0.98851692 | I51: =+IF(I29=0%, "", I29) -> 0.98278518 | J51: =+IF(J29=0%, "", J29) -> 0.95770268 | K51: =+IF(K29=0%, "", K29) -> 0.99279858 | L51: =+IF(L29=0%, "", L29) -> 0.99224206 | M51: =+IF(M29=0%, "", M29) -> 0.98443317 | N51: =+IF(N29=0%, "", N29) -> 0.95392659 | O51: =+IF(O29=0%, "", O29) -> 0.94208294 | ... V51: =+IF(V29=0%, "", V29) -> 0.91214659
B52: Mesa | D52: =+D36 -> 282897 | E52: =+E36 -> 0.97706565 | F52: =+F36 -> 0.98891016 | G52: =+G36 -> 0.99316005 | H52: =+IF(H36=0%, "", H36) -> 0.9862883 | I52: =+IF(I36=0%, "", I36) -> 0.98604793 | J52: =+IF(J36=0%, "", J36) -> 0.97516764 | K52: =+IF(K36=0%, "", K36) -> 0.98308572 | L52: =+IF(L36=0%, "", L36) -> 0.94896022 | M52: =+IF(M36=0%, "", M36) -> 0.98208182 | N52: =+IF(N36=0%, "", N36) -> 0.9846764 | O52: =+IF(O36=0%, "", O36) -> 0.97224078 | ... V52: =+IF(V36=0%, "", V36) -> 0.86261077
B53: Tempe | D53: =+D43 -> 278887 | E53: =+E43 -> 0.99115412 | F53: =+F43 -> 0.98121328 | G53: =+G43 -> 0.97341934 | H53: =+IF(H43=0%, "", H43) -> 1 | I53: =+IF(I43=0%, "", I43) -> 1 | J53: =+IF(J43=0%, "", J43) -> 0.99737887 | K53: =+IF(K43=0%, "", K43) -> 1 | L53: =+IF(L43=0%, "", L43) -> 0.98902781 | M53: =+IF(M43=0%, "", M43) -> 0.987278 | N53: =+IF(N43=0%, "", N43) -> 0.98149071 | O53: =+IF(O43=0%, "", O43) -> 0.98437719 | ... V53: =+IF(V43=0%, "", V43) -> 0.80695407
B54: Totals/Weighted Average | D54: =+SUM(D49:D53) -> 2282409 | E54: =+SUMPRODUCT(E49:E53,$D$49:$D$53)/$D$54 -> 0.99112352 | F54: =+SUMPRODUCT(F49:F53,$D$49:$D$53)/$D$54 -> 0.98305756 | G54: =+SUMPRODUCT(G49:G53,$D$49:$D$53)/$D$54 -> 0.98062169 | H54: =+SUMPRODUCT(H49:H53,$D$49:$D$53)/$D$54 -> 0.98736773 | I54: =+SUMPRODUCT(I49:I53,$D$49:$D$53)/$D$54 -> 0.98640515 | J54: =+SUMPRODUCT(J49:J53,$D$49:$D$53)/$D$54 -> 0.97578786 | K54: =+SUMPRODUCT(K49:K53,$D$49:$D$53)/$D$54 -> 0.98746062 | L54: =+SUMPRODUCT(L49:L53,$D$49:$D$53)/$D$54 -> 0.98360767 | ... U54: =+SUMPRODUCT(U49:U53,$D$49:$D$53)/$D$54 -> 0.89350901 | V54: ='Occupancy Summary Schedule'!F53 -> 0.88710744
B56: Increase/(Decrease) to Acquisition | F56: =+F54-$E$54 -> -0.0080659627 | G56: =+IF(G54=0%, "", G54-$E$54) -> -0.010501827 | H56: =+IF(H54=0%, "", H54-$E$54) -> -0.0037557882 | I56: =+IF(I54=0%, "", I54-$E$54) -> -0.0047183677 | J56: =+IF(J54=0%, "", J54-$E$54) -> -0.015335658 | K56: =+IF(K54=0%, "", K54-$E$54) -> -0.0036629039 | L56: =+IF(L54=0%, "", L54-$E$54) -> -0.0075158505 | M56: =+IF(M54=0%, "", M54-$E$54) -> -0.012629307 | N56: =+IF(N54=0%, "", N54-$E$54) -> -0.016782814 | ... U56: =+IF(U54=0%, "", U54-$E$54) -> -0.097614514
B57: Quarter over Quarter Increase/Decrease | F57: =+F54-E54 -> -0.0080659627 | G57: =+IF(G54=0%, "", G54-F54) -> -0.0024358639 | H57: =+IF(H54=0%, "", H54-G54) -> 0.0067460384 | I57: =+IF(I54=0%, "", I54-H54) -> -0.00096257945 | J57: =+IF(J54=0%, "", J54-I54) -> -0.010617291 | K57: =+IF(K54=0%, "", K54-J54) -> 0.011672755 | L57: =+IF(L54=0%, "", L54-K54) -> -0.0038529466 | M57: =+IF(M54=0%, "", M54-L54) -> -0.0051134569 | N57: =+IF(N54=0%, "", N54-M54) -> -0.0041535062 | ... U57: =+IF(U54=0%, "", U54-T54) -> -0.029716847

Sheet Sheet1
A1: [
A2: {"Submarket": "Airport", "Total SF": 688208, "Vacant SF": 56677, "Occupancy": 0.9176, "SF Expiring in Next 6 Months": null, "% Expiring in Next 6 Months": null, "Pending Deals": 15240, "Vacant Space": 25247, "Relative Occupancy": 0.9633},
A3: {"Submarket": "Chandler-Gilbert", "Total SF": 522101, "Vacant SF": 63452, "Occupancy": 0.8785, "SF Expiring in Next 6 Months": null, "% Expiring in Next 6 Months": null, "Pending Deals": 17886, "Vacant Space": 41125, "Relative Occupancy": 0.9212},
A4: {"Submarket": "Deer Valley", "Total SF": 510316, "Vacant SF": 44833, "Occupancy": 0.9121, "SF Expiring in Next 6 Months": null, "% Expiring in Next 6 Months": null, "Pending Deals": 8775, "Vacant Space": 31073, "Relative Occupancy": 0.9391},
A5: {"Submarket": "Mesa", "Total SF": 282897, "Vacant SF": 38867, "Occupancy": 0.8626, "SF Expiring in Next 6 Months": null, "% Expiring in Next 6 Months": null, "Pending Deals": 0, "Vacant Space": 20186, "Relative Occupancy": 0.9286},
A6: {"Submarket": "Tempe", "Total SF": 278887, "Vacant SF": 53838, "Occupancy": 0.8070, "SF Expiring in Next 6 Months": null, "% Expiring in Next 6 Months": null, "Pending Deals": 10000, "Vacant Space": 43838, "Relative Occupancy": 0.8428},
A7: {"Submarket": "Totals/Weighted Average", "Total SF": 2282409, "Vacant SF": 257667, "Occupancy": 0.8871, "SF Expiring in Next 6 Months": null, "% Expiring in Next 6 Months": null, "Pending Deals": 51901, "Vacant Space": 161469, "Relative Occupancy": 0.9293}
A8: ]

Sheet Occupancy Summary Schedule
B1: Summary Schedule
B3: Property Name | C3: Submarket | D3: Square Footage | E3: Occupancy | F3: Vacant SF | G3: SF Expiring in Next 6 Months | H3: % Expiring in Next 6 Months | I3: Pending Deals | J3: Vacant
B4: Reliance Broadway | C4: Airport | D4: 200813 | E4: =IF(D4=0,"",(D4-F4)/D4) -> 0.78848979 | F4: ='551_Reliance Broadway'!E56 -> 42474 | G4: ='551_Reliance Broadway'!E30 -> 28840 | H4: =IF(D4=0,"",G4/D4) -> 0.1436162 | I4: ='551_Reliance Broadway'!C56 -> 15240 | J4: ='551_Reliance Broadway'!H56 -> 21634 | K4: =(D4-J4)/D4 -> 0.89226793
B5: Reliance Broadway - Building A | C5: Airport | D5: 77045 | E5: =IF(D5=0,"",(D5-F5)/D5) -> 1 | F5: ='551A_Reliance Broadway A'!E46 -> 0 | G5: ='551A_Reliance Broadway A'!E24 -> 9456 | H5: =IF(D5=0,"",G5/D5) -> 0.12273347 | I5: ='551A_Reliance Broadway A'!C46 -> 0 | J5: ='551A_Reliance Broadway A'!H46 -> 0 | K5: =(D5-J5)/D5 -> 1
B6: Reliance Broadway - Building B | C6: Airport | D6: 107490 | E6: =IF(D6=0,"",(D6-F6)/D6) -> 1 | F6: ='551B_Reliance Broadway B'!E46 -> 0 | G6: ='551B_Reliance Broadway B'!E24 -> 20924 | H6: =IF(D6=0,"",G6/D6) -> 0.19465997 | I6: ='551B_Reliance Broadway B'!C46 -> 0 | J6: ='551B_Reliance Broadway B'!H46 -> 0 | K6: =(D6-J6)/D6 -> 1
B7: Reliance Broadway - Building C-D-E | C7: Airport | D7: 115354 | E7: =IF(D7=0,"",(D7-F7)/D7) -> 0.96867902 | F7: ='551E_Reliance Broadway C,D,E'!E46 -> 3613 | G7: ='551E_Reliance Broadway C,D,E'!E24 -> 14587 | H7: =IF(D7=0,"",G7/D7) -> 0.12645422 | I7: ='551E_Reliance Broadway C,D,E'!C46 -> 0 | J7: ='551E_Reliance Broadway C,D,E'!H46 -> 3613 | K7: =(D7-J7)/D7 -> 0.96867902
B8: Reliance Broadway - Building F | C8: Airport | D8: 103094 | E8: =IF(D8=0,"",(D8-F8)/D8) -> 1 | F8: ='551F_Reliance Broadway F'!E46 -> 0 | H8: =IF(D8=0,"",G9/D8) -> 0 | I8: ='551F_Reliance Broadway F'!C46 -> 0 | J8: ='551F_Reliance Broadway F'!H46 -> 0 | K8: =(D8-J8)/D8 -> 1
B9: Reliance Broadway | D9: =+D8+D7+D6+D5+D4 -> 603796 | E9: =IF(D9=0,"",(D9-F9)/D9) -> 0.92367124 | F9: =SUM(F4:F8) -> 46087 | G9: ='551F_Reliance Broadway F'!E24 -> 0 | H9: =IF(D9=0,"",G10/D9) -> 0.0034448721 | I9: =SUM(I4:I8) -> 15240 | J9: =SUM(J4:J8) -> 25247 | K9: =(D9-J9)/D9 -> 0.95818621
B10: South 40 | C10: Airport | D10: 84412 | E10: =IF(D10=0,"",(D10-F10)/D10) -> 0.8745439 | F10: ='730_South 40'!E32 -> 10590 | G10: ='730_South 40'!E24 -> 2080 | H10: =IF(D10=0,"",G10/D10) -> 0.024641046 | I10: ='730_South 40'!C32 -> 0 | J10: ='730_South 40'!H32 -> 0 | K10: =(D10-J10)/D10 -> 1
B11: AIRPORT SUB-TOTAL | D11: =+D9+D10 -> 688208 | E11: =IF(D11=0,"",(D11-F11)/D11) -> 0.91764554 | F11: =SUM(F9:F10) -> 56677 | G11: =SUM(G4:G10) -> 75887 | H11: =+G11/D11 -> 0.11026754 | I11: =SUM(I9:I10) -> 15240 | J11: =SUM(J9:J10) -> 25247 | K11: =(D11-J11)/D11 -> 0.96331487
B13: Golden Key Plaza | C13: Chandler Gilbert | D13: 63714 | E13: =IF(D13=0,"",(D13-F13)/D13) -> 0.94261858 | F13: ='120_Golden Key Plaza'!E47 -> 3656 | G13: ='120_Golden Key Plaza'!E25 -> 7746 | H13: =IF(D13=0,"",G13/D13) -> 0.12157454 | I13: ='120_Golden Key Plaza'!C47 -> 0 | J13: ='120_Golden Key Plaza'!H47 -> 1985 | K13: =(D13-J13)/D13 -> 0.96884515
B14: Chandler Technology Center | C14: Chandler Gilbert | D14: 113000 | E14: =IF(D14=0,"",(D14-F14)/D14) -> 0.88383186 | F14: ='341_Chandler Tech'!E38 -> 13127 | G14: ='341_Chandler Tech'!E17 -> 10393 | H14: =IF(D14=0,"",G14/D14) -> 0.091973451 | I14: ='341_Chandler Tech'!C38 -> 0 | J14: ='341_Chandler Tech'!H38 -> 10357 | K14: =(D14-J14)/D14 -> 0.90834513
B15: Chicago Street Business Park | C15: Chandler Gilbert | D15: 54382 | E15: =IF(D15=0,"",(D15-F15)/D15) -> 0.90853591 | F15: ='350 Chicago'!E39 -> 4974 | G15: ='350 Chicago'!E17 -> 7461 | H15: =IF(D15=0,"",G15/D15) -> 0.13719613 | I15: ='350 Chicago'!C39 -> 0 | J15: ='350 Chicago'!H39 -> 4974 | K15: =(D15-J15)/D15 -> 0.90853591
B16: Fiesta Center | C16: Chandler Gilbert | D16: 122693 | E16: =IF(D16=0,"",(D16-F16)/D16) -> 0.75552803 | F16: ='503_Fiesta Center'!E43 -> 29995 | G16: ='503_Fiesta Center'!E21 -> 19751 | H16: =IF(D16=0,"",G16/D16) -> 0.16097903 | I16: ='503_Fiesta Center'!C43 -> 17886 | J16: ='503_Fiesta Center'!H43 -> 12109 | K16: =(D16-J16)/D16 -> 0.90130651
B17: Fiesta Ranch Business Center | C17: Chandler Gilbert | D17: 56520 | E17: =IF(D17=0,"",(D17-F17)/D17) -> 1 | F17: ='511_Fiesta Ranch'!E31 -> 0 | G17: ='511_Fiesta Ranch'!E24 -> 2937 | H17: =IF(D17=0,"",G17/D17) -> 0.051963907 | I17: ='511_Fiesta Ranch'!C31 -> 0 | J17: ='511_Fiesta Ranch'!H31 -> 0 | K17: =(D17-J17)/D17 -> 1
B18: Frye Road Business Center | C18: Chandler Gilbert | D18: 73291 | E18: =IF(D18=0,"",(D18-F18)/D18) -> 0.84036239 | F18: ='525_Frye Road'!E45 -> 11700 | G18: ='525_Frye Road'!E24 -> 4140 | H18: =IF(D18=0,"",G18/D18) -> 0.056487154 | I18: ='525_Frye Road'!C45 -> 0 | J18: ='525_Frye Road'!H45 -> 11700 | K18: =(D18-J18)/D18 -> 0.84036239
B19: Oakland Business Park | C19: Chandler Gilbert | D19: 38501 | E19: =IF(D19=0,"",(D19-F19)/D19) -> 1 | F19: ='605_Oakland'!E31 -> 0 | G19: ='605_Oakland'!E24 -> 4608 | H19: =IF(D19=0,"",G19/D19) -> 0.1196852 | I19: ='605_Oakland'!C31 -> 0 | J19: ='605_Oakland'!H31 -> 0 | K19: =(D19-J19)/D19 -> 1
B20: CHANDLER-GILBERT SUB-TOTAL | D20: =+SUM(D13:D19) -> 522101 | E20: =IF(D20=0,"",(D20-F20)/D20) -> 0.87846796 | F20: =SUM(F13:F19) -> 63452 | G20: =SUM(G13:G19) -> 57036 | H20: =+G20/D20 -> 0.10924323 | I20: =SUM(I13:I19) -> 17886 | J20: =SUM(J13:J19) -> 41125 | K20: =(D20-J20)/D20 -> 0.92123172
B22: Central Deer Valley | C22: Deer Valley | D22: 52560 | E22: =IF(D22=0,"",(D22-F22)/D22) -> 0.92161339 | F22: ='336_Central Deer Valley'!E38 -> 4120 | G22: ='336_Central Deer Valley'!E20 -> 3675 | H22: =IF(D22=0,"",G22/D22) -> 0.069920091 | I22: ='336_Central Deer Valley'!C38 -> 0 | J22: ='336_Central Deer Valley'!H38 -> 2060 | K22: =(D22-J22)/D22 -> 0.9608067
B23: Deer Valley Commerce Center | C23: Deer Valley | D23: 214400 | E23: =IF(D23=0,"",(D23-F23)/D23) -> 0.87645989 | F23: ='370 Deer Valley Commerce'!E39 -> 26487 | G23: ='370 Deer Valley Commerce'!E17 -> 15435 | H23: =IF(D23=0,"",G23/D23) -> 0.071991604 | I23: ='370 Deer Valley Commerce'!C39 -> 8775 | J23: ='370 Deer Valley Commerce'!H39 -> 14787 | K23: =(D23-J23)/D23 -> 0.93103078
B24: Desert Ridge Industrial Park | C24: Deer Valley | D24: 52715 | E24: =IF(D24=0,"",(D24-F24)/D24) -> 0.87597458 | F24: ='375_Desert Ridge'!E38 -> 6538 | G24: ='375_Desert Ridge'!E17 -> 4509 | H24: =IF(D24=0,"",G24/D24) -> 0.085535426 | I24: ='375_Desert Ridge'!C38 -> 0 | J24: ='375_Desert Ridge'!H38 -> 6538 | K24: =(D24-J24)/D24 -> 0.87597458
B25: Laser Drive Industrial | C25: Deer Valley | D25: 35597 | E25: =IF(D25=0,"",(D25-F25)/D25) -> 0.84307666 | F25: ='548_Laser Drive'!E46 -> 5586 | G25: ='548_Laser Drive'!E24 -> 3865 | H25: =IF(D25=0,"",G25/D25) -> 0.10857657 | I25: ='548_Laser Drive'!C46 -> 0 | J25: ='548_Laser Drive'!H46 -> 5586 | K25: =(D25-J25)/D25 -> 0.84307666
B26: Perimeter Center | C26: Deer Valley | D26: 84028 | E26: =IF(D26=0,"",(D26-F26)/D26) -> 1 | F26: ='640_Perimeter Center'!E46 -> 0 | G26: ='640_Perimeter Center'!E24 -> 27824 | H26: =IF(D26=0,"",G26/D26) -> 0.33112772 | I26: ='640_Perimeter Center'!C46 -> 0 | J26: ='640_Perimeter Center'!H46 -> 0 | K26: =(D26-J26)/D26 -> 1
B27: Rose Garden Business Center | C27: Deer Valley | D27: 71016 | E27: =IF(D27=0,"",(D27-F27)/D27) -> 0.97040104 | F27: ='668_Rose Garden'!E46 -> 2102 | G27: ='668_Rose Garden'!E24 -> 8707 | H27: =IF(D27=0,"",G27/D27) -> 0.12260617 | I27: ='668_Rose Garden'!C46 -> 0 | J27: ='668_Rose Garden'!H46 -> 2102 | K27: =(D27-J27)/D27 -> 0.97040104
B28: DEER VALLEY SUB-TOTAL | D28: =+SUM(D22:D27) -> 510316 | E28: =IF(D28=0,"",(D28-F28)/D28) -> 0.91214659 | F28: =SUM(F22:F27) -> 44833 | G28: =SUM(G21:G27) -> 64015 | H28: =+G28/D28 -> 0.12544188 | I28: =SUM(I22:I27) -> 8775 | J28: =SUM(J22:J27) -> 31073 | K28: =(D28-J28)/D28 -> 0.93911028
B30: Falcon Field Industrial | C30: Mesa | D30: 40860 | E30: =IF(D30=0,"",(D30-F30)/D30) -> 1 | F30: ='508_Falcon Industrial'!E46 -> 0 | G30: ='508_Falcon Industrial'!E24 -> 8480 | H30: =IF(D30=0,"",G30/D30) -> 0.20753793 | I30: ='508_Falcon Industrial'!C46 -> 0 | J30: ='508_Falcon Industrial'!H46 -> 0 | K30: =(D30-J30)/D30 -> 1
B31: Horne Commerce Center | C31: Mesa | D31: 59408 | E31: =IF(D31=0,"",(D31-F31)/D31) -> 0.87126313 | F31: ='538_Horne'!E46 -> 7648 | G31: ='538_Horne'!E24 -> 8536 | H31: =IF(D31=0,"",G31/D31) -> 0.14368435 | I31: ='538_Horne'!C46 -> 0 | J31: ='538_Horne'!H46 -> 7648 | K31: =(D31-J31)/D31 -> 0.87126313
B32: Mesa Business Park | C32: Mesa | D32: 64619 | E32: =IF(D32=0,"",(D32-F32)/D32) -> 0.80597038 | F32: ='585_Mesa Business Park'!E46 -> 12538 | G32: ='585_Mesa Business Park'!E24 -> 7488 | H32: =IF(D32=0,"",G32/D32) -> 0.11587923 | I32: ='585_Mesa Business Park'!C46 -> 0 | J32: ='585_Mesa Business Park'!H46 -> 12538 | K32: =(D32-J32)/D32 -> 0.80597038
B33: Southpoint Commerce Center | C33: Mesa | D33: 59194 | E33: =IF(D33=0,"",(D33-F33)/D33) -> 1 | F33: ='735_Southpoint'!E46 -> 0 | G33: ='735_Southpoint'!E24 -> 9757 | H33: =IF(D33=0,"",G33/D33) -> 0.1648309 | I33: ='735_Southpoint'!C46 -> 0 | J33: ='735_Southpoint'!H46 -> 0 | K33: =(D33-J33)/D33 -> 1
B34: Aero I | C34: Mesa | D34: 58816 | E34: =IF(D34=0,"",(D34-F34)/D34) -> 0.68238234 | F34: ='805_Aero'!E29 -> 18681 | G34: ='805_Aero'!E19 -> 11729 | H34: =IF(D34=0,"",G34/D34) -> 0.19941853 | I34: ='805_Aero'!C29 -> 0 | J34: ='805_Aero'!H29 -> 0 | K34: =(D34-J34)/D34 -> 1
B35: MESA SUB-TOTAL | D35: =+SUM(D30:D34) -> 282897 | E35: =IF(D35=0,"",(D35-F35)/D35) -> 0.86261077 | F35: =SUM(F30:F34) -> 38867 | G35: =SUM(G28:G34) -> 110005 | H35: =+G35/D35 -> 0.38885177 | I35: =SUM(I30:I34) -> 0 | J35: =SUM(J30:J34) -> 20186 | K35: =(D35-J35)/D35 -> 0.92864541
B37: Broadway Industrial | C37: Tempe | D37: 43963 | E37: =IF(D37=0,"",(D37-F37)/D37) -> 0.71567 | F37: ='167_Broadway'!E40 -> 12500 | G37: ='167_Broadway'!E21 -> 5000 | H37: =IF(D37=0,"",G37/D37) -> 0.113732 | I37: ='167_Broadway'!C40 -> 10000 | J37: ='167_Broadway'!H40 -> 2500 | K37: =(D37-J37)/D37 -> 0.943134
B38: Hayden Park | C38: Tempe | D38: 100134 | E38: =IF(D38=0,"",(D38-F38)/D38) -> 0.85781053 | F38: ='537_Hayden Park'!E46 -> 14238 | G38: ='537_Hayden Park'!E24 -> 29856 | H38: =IF(D38=0,"",G38/D38) -> 0.29816046 | I38: ='537_Hayden Park'!C46 -> 0 | J38: ='537_Hayden Park'!H46 -> 14238 | K38: =(D38-J38)/D38 -> 0.85781053
B39: Hardy Center | C39: Tempe | D39: 49277 | E39: =IF(D39=0,"",(D39-F39)/D39) -> 0.76516428 | F39: ='542_Hardy Center'!E46 -> 11572 | G39: ='542_Hardy Center'!E24 -> 5012 | H39: =IF(D39=0,"",G39/D39) -> 0.10171074 | I39: ='542_Hardy Center'!C46 -> 0 | J39: ='542_Hardy Center'!H46 -> 11572 | K39: =(D39-J39)/D39 -> 0.76516428
B40: Park Lane | C40: Tempe | D40: 51040 | E40: =IF(D40=0,"",(D40-F40)/D40) -> 0.96598746 | F40: ='629_Park Lane'!E46 -> 1736 | G40: ='629_Park Lane'!E24 -> 11333 | H40: =IF(D40=0,"",G40/D40) -> 0.22204154 | I40: ='629_Park Lane'!C46 -> 0 | J40: ='629_Park Lane'!H46 -> 1736 | K40: =(D40-J40)/D40 -> 0.96598746
B41: University Business Center | C41: Tempe | D41: 34473 | E41: =IF(D41=0,"",(D41-F41)/D41) -> 0.59991878 | F41: ='873_University Business'!E39 -> 13792 | G41: ='873_University Business'!E17 -> 7425 | H41: =IF(D41=0,"",G41/D41) -> 0.21538595 | I41: ='873_University Business'!C39 -> 0 | J41: ='873_University Business'!H39 -> 13792 | K41: =(D41-J41)/D41 -> 0.59991878
B42: TEMPE SUB-TOTAL | D42: =+SUM(D37:D41) -> 278887 | E42: =IF(D42=0,"",(D42-F42)/D42) -> 0.80695407 | F42: =SUM(F37:F41) -> 53838 | G42: =SUM(G35:G41) -> 168631 | H42: =+G42/D42 -> 0.60465708 | I42: =SUM(I37:I41) -> 10000 | J42: =SUM(J37:J41) -> 43838 | K42: =(D42-J42)/D42 -> 0.84281089
B46: SUMMARY
B47: Sub-Market | D47: Sq. Ft. | E47: Vacant Sq. Ft. | F47: Occupancy | I47: Pending Deals | J47: Vacant Space | K47: Relative Occupancy
B48: Airport | D48: =+D11 -> 688208 | E48: =F11 -> 56677 | F48: =E11 -> 0.91764554 | I48: =I11 -> 15240 | J48: =J11 -> 25247 | K48: =K11 -> 0.96331487
B49: Chandler-Gilbert | D49: =+D20 -> 522101 | E49: =F20 -> 63452 | F49: =E20 -> 0.87846796 | I49: =I20 -> 17886 | J49: =J20 -> 41125 | K49: =K20 -> 0.92123172
B50: Deer Valley | D50: =+D28 -> 510316 | E50: =F28 -> 44833 | F50: =E28 -> 0.91214659 | I50: =I28 -> 8775 | J50: =J28 -> 31073 | K50: =K28 -> 0.93911028
B51: Mesa | D51: =+D35 -> 282897 | E51: =F35 -> 38867 | F51: =E35 -> 0.86261077 | I51: =I35 -> 0 | J51: =J35 -> 20186 | K51: =K35 -> 0.92864541
B52: Tempe | D52: =+D42 -> 278887 | E52: =F42 -> 53838 | F52: =E42 -> 0.80695407 | I52: =I42 -> 10000 | J52: =J42 -> 43838 | K52: =K42 -> 0.84281089
B53: Totals/Weighted Average | D53: =+SUM(D48:D52) -> 2282409 | E53: =+SUM(E48:E52) -> 257667 | F53: =(D53-E53)/D53 -> 0.88710744 | I53: =+SUM(I48:I52) -> 51901 | J53: =+SUM(J48:J52) -> 161469 | K53: =(D53-J53)/D53 -> 0.92925501

Sheet Working - CPI
B1: Address | C1: Ste. | D1: S.F. Available | E1: Date Suite Available | F1: Days on Market | G1: Market Effective Rent | H1: On Lock Box | I1: Lease Ready | J1: Comments | Q1: Yes | R1: No
B2: LAURA LINK
B3: RELIANCE BROADWAY
B4: $1.15-$1.35/sq ft - MG
B5: 200813
A6: 551 | B6: 3620 E Broadway Rd | C6: 14 | D6: 1420 | E6: 45931 | F6: =IF(B6="","",NOW()-E6) -> 78.527668 | G6: 1.2 | H6: Yes | I6: Yes | J6: Suite is clean and ready to be leased.
A7: 551 | B7: 3620 E Broadway Rd | C7: 4 | D7: 1422 | E7: 45962 | F7: =IF(B7="","",NOW()-E7) -> 47.527668 | G7: 1.2 | H7: Yes | I7: Yes | J7: Lease ready
A8: 551 | B8: 3620 E Broadway Rd | C8: 11 | D8: 1977 | E8: 45992 | F8: =IF(B8="","",NOW()-E8) -> 17.527668 | G8: 1.2 | H8: Yes | I8: No | J8: HVAC Inspections Needed. Paint and suite clean
A9: 551 | B9: 3620 E Broadway Rd | C9: 12 | D9: 1835 | E9: 45992 | F9: =IF(B9="","",NOW()-E9) -> 17.527668 | G9: 1.2 | H9: Yes | I9: No | J9: HVAC Inspections Needed. Paint and suite clean
A10: 551 | B10: 3620 E Broadway Rd | C10: 15 | D10: 1420 | E10: 45992 | F10: =IF(B10="","",NOW()-E10) -> 17.527668 | G10: 1.2 | H10: Yes | I10: No | J10: HVAC Inspections Needed. Paint and suite clean
A11: 551 | B11: 4203 S. 37th Street | D11: 2400 | E11: 45627 | F11: =IF(B11="","",NOW()-E11) -> 382.52767 | G11: 1.15 | H11: Yes | I11: Yes | J11: Suite was professionally cleaned. Updating interior and exterior lighting for now.
A12: 551 | B12: 4209 S. 36th Place | D12: 3200 | E12: 45383 | F12: =IF(B12="","",NOW()-E12) -> 626.52767 | G12: 1.1 | H12: Yes | I12: Yes | J12: Lease Ready - Updating WH lighting - Allied Electric
A13: 551 | B13: 4216 S 37th Street | D13: 2400 | E13: 45839 | F13: =IF(B13="","",NOW()-E13) -> 170.52767 | G13: 1.15 | H13: Yes | I13: Yes | J13: Lease ready work completed. Ready for lease.
A14: 551 | B14: 4217 S. 36th Place | D14: 3200 | E14: 45809 | F14: =IF(B14="","",NOW()-E14) -> 200.52767 | G14: 1.1 | H14: Yes | I14: Yes | J14: Suite was professionally cleaned - Updating interior and exterior lighting for now. Will include in next group of lease ready work.
A15: 551 | B15: 4219 S 37th Street | D15: 1200 | E15: 45992 | F15: =IF(B15="","",NOW()-E15) -> 17.527668 | G15: 1.15 | H15: Yes | I15: No
A16: 551 | B16: 4221 S 36th Place | D16: 2400 | E16: 45839 | F16: =IF(B16="","",NOW()-E16) -> 170.52767 | G16: 1.15 | H16: Yes | I16: Yes | J16: Issue with lighting. Need additional time to complete.
A17: 551 | B17: 4222 S 37th Street | D17: 2400 | E17: 45717 | F17: =IF(B17="","",NOW()-E17) -> 292.52767 | G17: 1.15 | H17: Yes | I17: Yes | J17: Lease ready work completed. Ready for lease.
A18: 551 | B18: 4224, 4226, 4228 S 37th Street | D18: 5600 | E18: 45964 | F18: =IF(B18="","",NOW()-E18) -> 45.527668 | G18: 1.2 | H18: Yes | I18: Yes | J18: Tenant lease expires 03/2026. Vacated space early. Deal for suite 4224 and 4226. Demo and lease ready work to be completed on suite 4228. Close passthrough between 4226-4228
A19: 551 | B19: 4226 S 36th Place | D19: 1200 | E19: 45992 | F19: =IF(B19="","",NOW()-E19) -> 17.527668 | G19: 1.15 | H19: Yes | I19: Yes | J19: Tenant will be moved out by 12/01/2025 (SD Lighting moving to 4246 37th St)
A20: 551 | B20: 4227 S 36th Place | D20: 1200 | E20: 45992 | F20: =IF(B20="","",NOW()-E20) -> 17.527668 | G20: 1.15 | H20: Yes | I20: No | J20: Suite needs paint, flooring, lighting, HVAC inspection
A21: 551 | B21: 4241 S 36th Place | D21: 1200 | E21: 45915 | F21: =IF(B21="","",NOW()-E21) -> 94.527668 | G21: 1.15 | H21: Yes | I21: Yes | J21: Needs paint, flooring, lighting.
A22: 551 | B22: 4243 S 36th Place | D22: 2400 | E22: 45719 | F22: =IF(B22="","",NOW()-E22) -> 290.52767 | G22: 1.15 | H22: Yes | I22: Yes | J22: Updating interior and exterior lighting for now. Will include in next group of lease ready work
A23: 551 | B23: 4244 S 37th Street | D23: 2400 | E23: 46023 | F23: =IF(B23="","",NOW()-E23) -> -13.472332 | G23: 1.15 | H23: No | I23: No | J23: T. W. Garage Pros Vacating
A24: 551 | B24: 4246 S 36th Place | D24: 3200 | E24: 45839 | F24: =IF(B24="","",NOW()-E24) -> 170.52767 | G24: 1.1 | H24: Yes | I24: Yes | J24: Needs update on flooring and paint. LED has been upgraded throughout.
B25: TOTAL | D25: =+SUM(D6:D16) -> 22874 | E25: =+D25/B5 -> 0.11390697 | F25: =+IF(E25=0,"100% LEASED","")
B27: RELIANCE BROADWAY A
B28: $1.30/sq ft - NNN
B29: 77045
F32: =IF(B32="","",NOW()-E32)
F33: =IF(B33="","",NOW()-E33)
F34: =IF(B34="","",NOW()-E34)
F35: =IF(B35="","",NOW()-E35)
F36: =IF(B36="","",NOW()-E36)
F37: =IF(B37="","",NOW()-E37)
F38: =IF(B38="","",NOW()-E38)
F39: =IF(B39="","",NOW()-E39)
F40: =IF(B40="","",NOW()-E40)
F41: =IF(B41="","",NOW()-E41)
F42: =IF(B42="","",NOW()-E42)
F43: =IF(B43="","",NOW()-E43)
... F49: =IF(B49="","",NOW()-E49)
B50: TOTAL | D50: =+SUM(D30:D49) -> 0 | E50: =+D50/$B$29 -> 0 | F50: =+IF(E50=0,"100% LEASED","") -> 100% LEASED
B52: RELIANCE BROADWAY B
B53: $1.30/sq ft - NNN
B54: 107490
F55: =IF(B55="","",NOW()-E55)
F56: =IF(B56="","",NOW()-E56)
F57: =IF(B57="","",NOW()-E57)
F58: =IF(B58="","",NOW()-E58)
F59: =IF(B59="","",NOW()-E59)
F60: =IF(B60="","",NOW()-E60)
F61: =IF(B61="","",NOW()-E61)
F62: =IF(B62="","",NOW()-E62)
F63: =IF(B63="","",NOW()-E63)
F64: =IF(B64="","",NOW()-E64)
F65: =IF(B65="","",NOW()-E65)
F66: =IF(B66="","",NOW()-E66)
... F74: =IF(B74="","",NOW()-E74)
B75: TOTAL | D75: =+SUM(D55:D74) -> 0 | E75: =+D75/$B$54 -> 0 | F75: =+IF(E75=0,"100% LEASED","") -> 100% LEASED
B77: RELIANCE BROADWAY C
B78: $1.40/sq ft - NNN
B79: 49816
F80: =IF(B80="","",NOW()-E80)
F81: =IF(B81="","",NOW()-E81)
F82: =IF(B82="","",NOW()-E82)
F83: =IF(B83="","",NOW()-E83)
F84: =IF(B84="","",NOW()-E84)
F85: =IF(B85="","",NOW()-E85)
F86: =IF(B86="","",NOW()-E86)
F87: =IF(B87="","",NOW()-E87)
F88: =IF(B88="","",NOW()-E88)
F89: =IF(B89="","",NOW()-E89)
F90: =IF(B90="","",NOW()-E90)
F91: =IF(B91="","",NOW()-E91)
... F99: =IF(B99="","",NOW()-E99)
B100: TOTAL | D100: =+SUM(D80:D99) -> 0 | E100: =+D100/$B$79 -> 0 | F100: =+IF(E100=0,"100% LEASED","") -> 100% LEASED
B102: RELIANCE BROADWAY D
B103: $1.40/sq ft - NNN
B104: 31049
A105: 551E | B105: 4300 S 38th St | C105: D160 | D105: 3613 | E105: 45901 | F105: =IF(B105="","",NOW()-E105) -> 108.52767 | G105: 1.4 | H105: Yes | I105: Yes | J105: Suite is clean and ready to lease.
F106: =IF(B106="","",NOW()-E106)
F107: =IF(B107="","",NOW()-E107)
F108: =IF(B108="","",NOW()-E108)
F109: =IF(B109="","",NOW()-E109)
F110: =IF(B110="","",NOW()-E110)
F111: =IF(B111="","",NOW()-E111)
F112: =IF(B112="","",NOW()-E112)
F113: =IF(B113="","",NOW()-E113)
F114: =IF(B114="","",NOW()-E114)
F115: =IF(B115="","",NOW()-E115)
F116: =IF(B116="","",NOW()-E116)
F117: =IF(B117="","",NOW()-E117)
... F124: =IF(B124="","",NOW()-E124)
B125: TOTAL | D125: =+SUM(D105:D124) -> 3613 | E125: =+D125/$B$104 -> 0.11636446 | F125: =+IF(E125=0,"100% LEASED","")
B127: RELIANCE BROADWAY E
B128: $1.40/sq ft - NNN
B129: 34489
A130: 551E | B130: 4350 S 38th St | C130: E150 | D130: 4013 | E130: 45962 | F130: =IF(B130="","",NOW()-E130) -> 47.527668 | G130: 1.4 | H130: Yes | I130: Yes | J130: Suite is clean and on lockbox.
F131: =IF(B131="","",NOW()-E131)
F132: =IF(B132="","",NOW()-E132)
...

Sheet Lease Report 2025
A1: Type of Lease (New, Renewal,Expansion, Expansion and Renewal) ( R N X RX) | B1: Property | C1: Property Name | D1: Notice Address | E1: Units | F1: City, State, Zip | G1: Lease Area | H1: Tenant Entity | I1: Current Rent | J1: PSF Current | K1: First Year Rent | L1: PSF First Year | M1: Percentage increase | N1: Annual Increase | O1: CPI Notes | P1: Term | Q1: EXP | R1: Lease Commencment Date
A2: RX | B2: 120 | C2: Golden Key Plaza | D2: 751 N Monterey | E2: 113 | F2: Gilbert, AZ | G2: 1191 | H2: Scale X Pro LLC | I2: 1429.2 | J2: =I2/G2 -> 1.2 | K2: 3239.52 | L2: =K2/G2 -> 2.72 | M2: =(K2/I2)-1 -> 1.2666667 | N2: 0.07 | O2: Minor TI, No Free rent, No outside agent, Base Year Gross | P2: 3 | Q2: 45688 | R2: 45689
A3: New | B3: 120 | C3: Golden Key Plaza | D3: 425 W Guadalupe | E3: 114 | F3: Lease | G3: 2502 | H3: Luxe Cabinetry | K3: =G3*L3 -> 3127.5 | L3: 1.25 | N3: 0.06 | O3: 3 | P3: 3 | R3: 45748
A4: R | B4: 120 | C4: Golden Key Plaza | D4: 425 W Guadalupe | E4: 115, 116 | F4: Gilbert, AZ | G4: 3494 | H4: JRL Goods LLC | I4: 3852.14 | J4: =I4/G4 -> 1.1025014 | K4: 4751.84 | L4: =K4/G4 -> 1.36 | M4: =(K4/I4)-1 -> 0.23355849 | N4: 0.07 | O4: No TI, No Free rent, No outside agent, Base Year Gross | P4: 3 | Q4: 45777 | R4: 45778
A5: R | B5: 120 | C5: Golden Key Plaza | D5: 751 N Monterey | E5: 114 | F5: Gilbert, AZ | G5: 1191 | H5: Eagle One Appliance Repair | I5: 1310.1 | J5: =I5/G5 -> 1.1 | K5: 1679.31 | L5: =K5/G5 -> 1.41 | M5: =(K5/I5)-1 -> 0.28181818 | N5: 0.07 | O5: No TI, No Free rent, No outside agent, Base Year Gross | P5: 3 | Q5: 45838 | R5: 45839
A6: New | B6: 120 | C6: Golden Key Plaza | D6: 761 N Monterey | E6: 103 | F6: Lease | G6: 1671 | H6: Joshua Daniel Brown d/b/a Superstition Merch | K6: =G6*L6 -> 2088.75 | L6: 1.25 | N6: 0.05 | P6: 2 | R6: 45901
A7: R | B7: 120 | C7: Golden Key Plaza | D7: 761 N Monterey St | E7: 107 | F7: Gilbert, 85233 | G7: 1676 | H7: Lamp Service Products Arizona | I7: 1743.04 | J7: =I7/G7 -> 1.04 | K7: 2178.8 | L7: =K7/G7 -> 1.3 | M7: =(K7/I7)-1 -> 0.25 | N7: 0.06 | O7: HVAC Replacement, No Free rent, No outside agent, Base Year Gross | P7: 5 | Q7: =#REF! -> #REF! | R7: 45901
A8: New | B8: 120 | C8: Golden Key Plaza | D8: 425 W. Guadalupe Road, Suite 115 | E8: 115 | F8: Lease | G8: 1784 | H8: Batti-Performance, LLC | K8: =L8*G8 -> 2319.2 | L8: 1.3 | N8: 0.05 | O8: 1 Month free | P8: 3 | R8: 45962
A9: New | B9: 120 | C9: Golden Key Plaza | D9: 425 W Guadalupe Rd Suite 116 | E9: 116 | F9: Lease | G9: 1710 | H9: Madbrows LLC | K9: =G9*L9 -> 2137.5 | L9: 1.25 | N9: 0.05 | O9: 2 | P9: 5 | R9: 45992
A10: OFS | B10: 120 | C10: Golden Key Plaza | D10: 425 W Guadalupe | E10: 113 | F10: Gilbert, AZ 85233 | G10: 1421 | H10: Miller Chiropractic Center Inc | I10: 2358.86 | J10: =I10/G10 -> 1.66 | K10: 2358.86 | L10: =K10/G10 -> 1.66 | M10: =(K10/I10)-1 -> 0 | O10: No TI, No Free rent, No outside agent, Base Year Gross | P10: 1 | Q10: 46022 | R10: 46023
A11: New | B11: 120 | C11: Golden Key Plaza | D11: 761 N Monterey | E11: 104 | F11: Lease | G11: 1671 | H11: DRT Fabrication LLC | K11: =L11*G11 -> 2255.85 | L11: 1.35 | N11: 0.05 | O11: 1 Month free | P11: 3
A12: New | B12: 120 | C12: Golden Key Plaza | G12: 1191 | H12: Kachina Contracting Corp | K12: =G12*L12 -> 0
A13: R | B13: 167 | C13: Broadway Industrial | D13: 835 W 22nd | E13: 105-107 | F13: Tempe, AZ | G13: 7500 | H13: TRUE WORLD FOODS PHOENIX, LLC ( TW FOODS LLC ) | I13: 6075 | J13: =I13/G13 -> 0.81 | K13: 8625 | L13: =K13/G13 -> 1.15 | M13: =(K13/I13)-1 -> 0.41975309 | N13: 0.05 | O13: No TI, No Free rent, No outside agent, Base Year Gross | P13: 5 | Q13: 45900 | R13: 45901
A14: R | B14: 336 | C14: Central Deer Valley | D14: 21616 N Central Ave | F14: Phoenix, AZ 85024 | G14: 1225 | H14: Claude Bryant | I14: 1335.25 | J14: =I14/G14 -> 1.09 | K14: 1715 | L14: =K14/G14 -> 1.4 | M14: 0.28 | N14: 0.06 | O14: Tenant signed 3 year renewal | P14: 3 | Q14: 45688 | R14: 45689
A15: New | B15: 336 | C15: Central Deer Valley | D15: 21616 N Centerl | E15: 16 | F15: Lease | G15: 1225 | H15: James Cartwright a/b/a Vision Scape | K15: =G15*L15 -> 1800.75 | L15: 1.47 | N15: 0.05 | O15: 2 | P15: 5 | R15: 45748
A16: New | B16: 336 | C16: Central Deer Valley | D16: 21628 N Central | E16: 8 | F16: Lease | G16: 2060 | H16: Quiiriego Restaurant, LLC | K16: =G16*L16 -> 2925.2 | L16: 1.42 | N16: 0.085 | O16: 1 | P16: 3 | R16: 45748
A17: R | B17: 336 | C17: Central Deer Valley | D17: 21616 N Central Ave | E17: 15 | F17: Phoenix, AZ 85024 | G17: 1225 | H17: Pool Barrier of AZ | I17: 1335.25 | J17: =I17/$G17 -> 1.09 | K17: 1715 | L17: =K17/$G17 -> 1.4 | M17: =(K17/I17)-1 -> 0.28440367 | N17: 0.06 | O17: Tenant agreed to a 3 year MG renewal | P17: 3 | Q17: 45747 | R17: 45748
A18: R | B18: 336 | C18: Central Deer Valley | D18: 21616 N Central Ave | E18: 5, 11, 12, 13 | F18: Phoenix, AZ 85024 | G18: 4900 | H18: Rich Interiors | I18: 5488 | J18: =I18/G18 -> 1.12 | K18: 6615 | L18: =K18/G18 -> 1.35 | M18: =(K18/I18)-1 -> 0.20535714 | N18: 0.06 | O18: Tenant agreed to a 3 year renewal - MG lease | P18: 3 | Q18: 45747 | R18: 45748
A19: R | B19: 336 | C19: Central Deer Valley | D19: 21602 N Central Ave | E19: 7 | F19: Phoenix, AZ 85024 | G19: 4120 | H19: Scudo Divers, LLC | I19: 4738 | J19: =I19/G19 -> 1.15 | K19: 5562 | L19: =K19/G19 -> 1.35 | M19: =(K19/I19)-1 -> 0.17391304 | N19: 0.06 | O19: No TI, No Free rent, No outside agent, Base Year Gross | P19: 3 | Q19: 45777 | R19: 45778
A20: R | B20: 336 | C20: Central Deer Valley | D20: 21628 N Central Ave | E20: 3 | F20: Phoenix, AZ 85024 | G20: 2060 | H20: AZ Gun Works | I20: 2245.4 | J20: =I20/G20 -> 1.09 | K20: 2678 | L20: =K20/G20 -> 1.3 | M20: =(K20/I20)-1 -> 0.19266055 | N20: 0.05 | O20: Tenant has agreed to a 5 year MG Renewal | P20: 5 | Q20: 45838 | R20: 45839
A21: R | B21: 336 | C21: Central Deer Valley | D21: 21628 N Central Ave | E21: 4 & 5 | F21: Phoenix, AZ 85024 | G21: 4120 | H21: Bruno's Shooting Supply | I21: 4490.8 | J21: =I21/G21 -> 1.09 | K21: 5356 | L21: =K21/G21 -> 1.3 | M21: =(K21/I21)-1 -> 0.19266055 | N21: 0.05 | O21: Tenant has agreed to a 5 year MG Renewal | P21: 5 | Q21: 45838 | R21: 45839
A22: R | B22: 336 | C22: Central Deer Valley | D22: 21628 N Central Ave | E22: 1 & 2 | F22: Phoenix, AZ 85024 | G22: 4120 | H22: Moto Garage | I22: 4614.4 | J22: =I22/G22 -> 1.12 | K22: 5768 | L22: =K22/G22 -> 1.4 | M22: =(K22/I22)-1 -> 0.25 | N22: 0.06 | O22: Tenant has agreed to a 3 year MG Renewal | P22: 3 | Q22: 45838 | R22: 45839
A23: New | B23: 336 | C23: Central Deer Valley | D23: 21606 N Central | E23: 14 | F23: Lease | G23: 1225 | H23: Gecko Garage Doors Inc Doors | K23: =G23*L23 -> 1800.75 | L23: 1.47 | N23: 0.06 | O23: 1 | P23: 3 | R23: 45870
A24: R | B24: 336 | C24: Central Deer Valley | D24: 21602 N Central Ave | E24: 1 | F24: Phoenix, AZ 85024 | G24: 2060 | H24: Import Care Center/Benz | I24: 2472 | J24: =I24/G24 -> 1.2 | K24: 2884 | L24: =K24/G24 -> 1.4 | M24: 0.17 | N24: 0.06 | O24: Tenant signed a new 3 year MG renewal | P24: 3 | Q24: 45869 | R24: 45870
A25: New | B25: 336 | C25: Central Deer Valley | D25: 21602 N Central | E25: 5,6 | F25: Lease | G25: 4120 | H25: D&A Partners LLC | K25: =G25*L25 -> 5768 | L25: 1.4 | N25: 0.05 | O25: 0 | P25: 3 | R25: 45931
A26: RX | B26: 336 | C26: Central Deer Valley | D26: 21616 &21628 N Central Av3 | E26: 3, 4, 8 | F26: Phoneix. AZ 85024 | G26: 4510 | H26: Two Brother's Auto Restoration | I26: 4593.75 | J26: =I26/G26 -> 1.0185698 | K26: 6404.2 | L26: =K26/G26 -> 1.42 | M26: =(K26/I26)-1 -> 0.39411156 | N26: 0.06 | O26: Tenant is increasing 835 sf and signing a 3 year MG renewal | P26: 3 | Q26: 45991 | R26: 45992
A27: New | B27: 341 | C27: CHANDLER TECHNOLOGY CENTER | D27: 7402 W Detroit | E27: 100 | F27: Lease | G27: 1951 | H27: Arizona Fitness Distributors LLC | K27: =G27*L27 -> 2828.95 | L27: 1.45 | P27: 1 | R27: 45703
A28: RX | B28: 341 | C28: CHANDLER TECHNOLOGY CENTER | D28: 7408 W Detroit St | E28: 170 | F28: Chandler, AZ 85226 | G28: 4581 | H28: AutoJoy, Inc | K28: =G28*L28 -> 6413.4 | L28: 1.4 | N28: 0.1 | O28: No TI, No Free rent,Gold Trust Realty, Base Year Gross, Expansion | P28: 2 | Q28: 46022 | R28: 45717
A29: New | B29: 341 | C29: CHANDLER TECHNOLOGY CENTER | D29: 7408 W Detroit Street Suite 170 | E29: 170 | F29: Lease | G29: 4581 | H29: Autojoy Inc | K29: =G29*L29 -> 6413.4 | L29: 1.4 | N29: 0.1 | P29: 2 | R29: 45719
A30: R | B30: 341 | C30: CHANDLER TECHNOLOGY CENTER | D30: 7406 W Detroit | F30: Chandler, AZ | G30: 39285 | H30: Daifuku Cleanroom America Corporation | I30: 41642.1 | J30: =I30/G30 -> 1.06 | K30: 44784.9 | L30: =K30/G30 -> 1.14 | M30: =(K30/I30)-1 -> 0.075471698 | N30: 0.03 | O30: TI, 2 Months free, Marc Pierce (Lee), Base Year | P30: 7 | Q30: 45777 | R30: 45778
A31: R | B31: 341 | C31: CHANDLER TECHNOLOGY CENTER | D31: 7404 W Detroit | E31: 140 | F31: Chandler, AZ 85226 | G31: 12730 | H31: Med Fibers, Inc | I31: 14512.2 | J31: =I31/G31 -> 1.14 | K31: 16167.1 | L31: =K31/G31 -> 1.27 | M31: =(K31/I31)-1 -> 0.11403509 | N31: 0.06 | O31: No TI, No Free rent, No outside agent, Base Year Gross | P31: 5 | Q31: 46022 | R31: 46023
A32: R | B32: 341 | C32: CHANDLER TECHNOLOGY CENTER | D32: 7400 W Detroit | E32: 160 | F32: Chandler, AZ | G32: 1525 | H32: SO Esthetics, LLC | I32: 1601.25 | J32: =I32/G32 -> 1.05 | K32: 1677.5 | L32: =K32/G32 -> 1.1 | M32: =(K32/I32)-1 -> 0.047619048 | O32: No TI, No Free rent, No outside agent, Base Year Gross | P32: 1 | Q32: 46081 | R32: 46082
A33: R | B33: 350 | C33: Chicago Business Park | D33: 6710 W Chicago St | E33: 3 | F33: Chandler, AZ | G33: 2804 | H33: Ameri-Sol, LLC | I33: 3056.36 | J33: =I33/G33 -> 1.09 | K33: 3757.36 | L33: =K33/G33 -> 1.34 | M33: =(K33/I33)-1 -> 0.2293578 | N33: 0.07 | O33: No TI, 1 Mo Free rent (tenant to replace EVAP), No outside agent, Base Year Gross | P33: 3 | Q33: 45838 | R33: 45839
A34: R | B34: 350 | C34: Chicago Business Park | D34: 6700 W Chicago | E34: 5 | F34: Chandler, 85226 | G34: 2487 | H34: WATER SYSTEMS SOLUTIONS, LLC | I34: 2860.05 | J34: =I34/G34 -> 1.15 | K34: 3208.23 | L34: =K34/G34 -> 1.29 | M34: =(K34/I34)-1 -> 0.12173913 | N34: 0.06 | O34: No TI, No Free rent, No outside agent, Base Year Gross | P34: 5 | Q34: 45900 | R34: 45901
A35: R | B35: 350 | C35: Chicago Business Park | D35: 6730 W Chicago St | E35: 4, 5 | F35: Contract | G35: 21320 | H35: Scriven Precision Fabricating | I35: 21054.32 | J35: =I35/G35 -> 0.98753846 | K35: 23452 | L35: =K35/G35 -> 1.1 | M35: =(K35/I35)-1 -> 0.11388067 | N35: 0.05 | O35: No TI, No Free rent, Kathleen Hampton, Base Year Gross | P35: 3 | Q35: 45747 | R35: 45901
A36: New | B36: 350 | C36: Chicago Business Park | D36: 6710 W Chicago Street, Suite 5 | E36: 5 | F36: Lease | G36: 1574 | H36: Happy Jack Distillers, LLC | K36: =G36*L36 -> 2140.64 | L36: 1.36 | N36: 0.04 | O36: 2 | P36: 5 | R36: 45992
A37: New | B37: 350 | C37: Chicago Business Park | D37: 6730 W Chicago Street, Suite 1 | E37: 1 | F37: Lease | G37: 1574 | H37: Steel & Grace Overhead Doors LLC | K37: =G37*L37 -> 2172.12 | L37: 1.38 | N37: 0.06 | P37: 2 | R37: 45992
A38: R | B38: 350 | C38: Chicago Business Park | D38: 6700 W Chicago | E38: 4 | F38: Chandler, AZ 85226 | G38: 2487 | H38: CELTIC FORKLIFT, INC. | I38: 2860.05 | J38: =I38/G38 -> 1.15 | K38: 3456.93 | L38: =K38/G38 -> 1.39 | M38: =(K38/I38)-1 -> 0.20869565 | O38: No TI, No Free rent, No outside agent, Base Year Gross | P38: 1 | Q38: 45991 | R38: 45992
A39: RX | B39: 370 | C39: Deer Valley Commerce Center | D39: 1725 W Williams Dr | F39: Phoenix, AZ 85027 | G39: 11700 | H39: Cornel Hasna | I39: 9740.25 | J39: =I39/G39 -> 0.8325 | K39: 16029 | L39: =K39/G39 -> 1.37 | M39: 0.23 | N39: 0.06 | O39: Tenant is expanding and renewing their lease. They will now have suites 25, 26, 27, 28 and have renewed for 3 years | P39: 3 | Q39: 45716 | R39: 45717
A40: New | B40: 370 | C40: Deer Valley Commerce Center | D40: 1725 W Williams Dr | E40: 57,58 | F40: Lease | G40: 5850 | H40: Maverix Baseball Academy LLC | K40: =G40*L40 -> 8482.5 | L40: 1.45 | N40: 0.05 | O40: 2 | P40: 5 | R40: 45809
A41: R | B41: 370 | C41: Deer Valley Commerce Center | D41: 1725 W Williams Dr | E41: 54 | F41: Phoenix, AZ 85027 | G41: 3076 | H41: Engaging Media | I41: 3229.8 | J41: =I41/G41 -> 1.05 | K41: 4306.4 | L41: =K41/G41 -> 1.4 | M41: =(K41/I41)-1 -> 0.33333333 | N41: 0.06 | O41: Tenant agreed to a 3 year NNN renewal | P41: 3 | Q41: 45808 | R41: 45809
A42: R | B42: 370 | C42: Deer Valley Commerce Center | D42: 1725 W Williams Dr | E42: 2 | F42: Phoenix, AZ 85027 | G42: 2925 | H42: Fechete Euro Flooring | I42: 3129.75 | J42: =I42/$G42 -> 1.07 | K42: 4095 | L42: =K42/$G42 -> 1.4 | M42: =(K42/I42)-1 -> 0.30841121 | N42: 0.06 | O42: Tenant has agreed to a 3 year renewal | P42: 3 | Q42: 45808 | R42: 45809
A43: R | B43: 370 | C43: Deer Valley Commerce Center | D43: 1725 W Williams Dr | E43: 1 | F43: Phoenix, AZ 85027 | G43: 2925 | H43: Phoenix Granite | I43: 3129.75 | J43: =I43/$G43 -> 1.07 | K43: 4153.5 | L43: =K43/$G43 -> 1.42 | M43: =(K43/I43)-1 -> 0.3271028 | N43: 0.06 | O43: Tenant has agreed to a 3 year renewal | P43: 3 | Q43: 45808 | R43: 45809
A44: R | B44: 370 | C44: Deer Valley Commerce Center | D44: 1725 W Williams Dr | E44: 53 | F44: Phoenix, AZ 85027 | G44: 3076 | H44: Five Star Finish | I44: 3229.8 | J44: =I44/G44 -> 1.05 | K44: 4367.92 | L44: =K44/G44 -> 1.42 | M44: =(K44/I44)-1 -> 0.35238095 | N44: 0.06 | O44: Tenant has agreed to a 3 year NNN renewal | P44: 3 | Q44: 45838 | R44: 45839
A45: R | B45: 370 | C45: Deer Valley Commerce Center | D45: 1725 W Williams Dr | E45: 49 | F45: Phoenix, AZ 85027 | G45: 2925 | H45: Danmarpan LLC | I45: 2983.5 | J45: =I45/G45 -> 1.02 | K45: 3948.75 | L45: =K45/G45 -> 1.35 | M45: =(K45/I45)-1 -> 0.32352941 | N45: 0.06 | O45: Waiting for Equus to sign | P45: 3 | Q45: 45930 | R45: 45931
A46: R | B46: 370 | C46: Deer Valley Commerce Center | D46: 1725 W Williams Dr | E46: 3 | F46: Phoenix, AZ 85027 | G46: 2925 | H46: Limitless Graphix | I46: 2925 | J46: =I46/G46 -> 1 | K46: 4095 | L46: =K46/G46 -> 1.4 | M46: =(K46/I46)-1 -> 0.4 | N46: 0.06 | O46: Tenant agreed to a 3 year NNN renewal | P46: 3 | Q46: 45930 | R46: 45931
A47: OFS | B47: 370 | C47: Deer Valley Commerce Center | D47: 1725 W Williams Dr | E47: 61 & 63 | F47: Phoenix, AZ 85027 | G47: 5850 | H47: Elevated Design | I47: 3363.75 | J47: =I47/G47 -> 0.575 | K47: 7956 | L47: =K47/G47 -> 1.36 | M47: =(K47/I47)-1 -> 1.3652174 | N47: 0.06 | O47: Tenant is expanding into suite 63 to take 5,850 sf. | P47: 3 | Q47: 45961 | R47: 45962
A48: New | B48: 370 | C48: Deer Valley Commerce Center | D48: 1725 W. Williams Drive, Sutie 64 | G48: 2925 | H48: Disbrow, Inc, d/b/a Varsity Zone HVAC N Phoenix | K48: =G48*L48 -> 3948.75 | L48: 1.35 | N48: 0.05 | O48: Lease comments are with Equus attorney for review | P48: 3 | R48: 45992
A49: New | B49: 370 | C49: Deer Valley Commerce Center | D49: 1725 W Williams Drive, Suite 63 | G49: 2925 | H49: Elite Wake Services, LLC | K49: =G49*L49 -> 3978 | L49: 1.36 | N49: 0.06 | O49: Waiting on COI | P49: 3 | R49: 45992
A50: New | B50: 370 | C50: Deer Valley Commerce Center | D50: 1725 W Williams Dr | E50: 35 | F50: Lease | G50: 2925 | H50: AZ Alignment LLC | K50: 4153.5 | L50: =K50/G50 -> 1.42 | N50: 0.06 | P50: 3
A51: New | B51: 370 | C51: Deer Valley Commerce Center | D51: 1725 W Williams Drive, Suties 67 & 68 | G51: 6152 | H51: BCA Investments, LLC d/b/a Discount Motorsports | K51: =G51*L51 -> 0 | O51: Waiting on COI
A52: New | B52: 370 | C52: Deer Valley Commerce Center | D52: 1725 W Williams Dr | E52: 23 | F52: Lease | G52: 2925 | H52: Complete Water Systems LLC | K52: 3948.75 | L52: =K52/G52 -> 1.35 | P52: 5
A53: New | B53: 370 | C53: Deer Valley Commerce Center | D53: 1725 W. Williams Drive, Suite 7 | G53: 3948.75 | H53: Earvolution, Inc | K53: 4476.15 | L53: =K53/G53 -> 1.1335613 | N53: 0.06 | P53: 3
A54: New | B54: 370 | C54: Deer Valley Commerce Center | D54: 1725 W Williams Dr | E54: 4 | F54: Lease | G54: 2925 | H54: R3M&D AZ LLC | K54: 4036.5 | L54: =K54/G54 -> 1.38
A55: R | B55: 511 | C55: Fiesta Ranch | D55: 1015 N McQueen | E55: 165 | F55: Gilbert, AZ | G55: 2933 | H55: Sticky Solutions, LLC | I55: 3431.11 | J55: =I55/G55 -> 1.1698295 | K55: 4223.52 | L55: =K55/G55 -> 1.44 | M55: =(K55/I55)-1 -> 0.23094859 | N55: 0.07 | O55: No TI, No Free rent, No outside agent, Base Year Gross | P55: 2 | Q55: 45716 | R55: 45717
A56: R | B56: 511 | C56: Fiesta Ranch | D56: 1015 N McQueen | E56: 163 | F56: Gilbert, AZ | G56: 2937 | H56: Star Hardware Inc | I56: 3113.22 | J56: =I56/G56 -> 1.06 | K56: 4199.91 | L56: =K56/G56 -> 1.43 | M56: =(K56/I56)-1 -> 0.3490566 | N56: 0.075 | O56: No TI, No Free rent, No outside agent, Base Year Gross | P56: 3 | Q56: 45777 | R56: 45778
A57: R | B57: 511 | C57: Fiesta Ranch | D57: 1025 N McQueen | E57: 157 | F57: Contract | G57: 2752 | H57: BC MOTOR SPORTS | I57: 2862.08 | J57: =I57/G57 -> 1.04 | K57: 3852.8 | L57: =K57/G57 -> 1.4 | M57: =(K57/I57)-1 -> 0.34615385 | N57: 0.07 | O57: No TI, No Free rent, No outside agent, Base Year Gross | P57: 3 | Q57: 45869 | R57: 45870
A58: R | B58: 511 | C58: Fiesta Ranch | D58: 1025 N McQueen Rd | E58: 150, 152 | F58: Gilbert, AZ | G58: 8431 | H58: AUTOMOTIVE PERFORMANCE REPAIR | I58: 6913.42 | J58: =I58/G58 -> 0.82 | K58: 10538.75 | L58: =K58/G58 -> 1.25 | M58: =(K58/I58)-1 -> 0.52439024 | N58: 0.06 | O58: No TI, No Free rent, CBRE (Serena), Base Year Gross | P58: 5 | Q58: 45900 | R58: 45901
A59: R | B59: 508 | C59: Falcon Field Industrial | D59: 3960 E Palm | E59: 1 | F59: Mesa, AZ | G59: 2240 | H59: Aggregate Machinery, INC. | I59: 2912 | J59: =I59/G59 -> 1.3 | K59: 3136 | L59: =K59/G59 -> 1.4 | M59: =(K59/I59)-1 -> 0.076923077 | N59: 0.07 | O59: No TI, No Free rent, No outside agent, Base Year Gross | P59: 3 | Q59: 45688 | R59: 45689
A60: New | B60: 508 | C60: Falcon Field Industrial | D60: 3960 E Palm | E60: 2 | F60: Lease | G60: 2240 | H60: American Matrial Processing Equipment | K60: =G60*L60 -> 3584 | L60: 1.6 | N60: 0.07 | O60: 0 | P60: 3 | R60: 45717
A61: R | B61: 508 | C61: Falcon Field Industrial | D61: 3035 N Maple | E61: 5 | F61: Mesa, AZ | G61: 3000 | H61: Redline Contracting Group | I61: 3600 | J61: =I61/$G61 -> 1.2 | K61: 4500 | L61: =K61/$G61 -> 1.5 | M61: =(K61/I61)-1 -> 0.25 | N61: 0.07 | O61: No TI, 1 mo Free rent, No outside agent, Base Year Gross | P61: 3 | Q61: 45777 | R61: 45778
A62: R | B62: 508 | C62: Falcon Field Industrial | D62: 3035 E Maple | E62: 2 | F62: Mesa | G62: 4000 | H62: AZ Truck & Equipment Sales LLC | I62: 3520 | J62: =I62/G62 -> 0.88 | K62: 5800 | L62: =K62/G62 -> 1.45 | M62: =(K62/I62)-1 -> 0.64772727 | N62: 0.075 | O62: No TI, No Free rent, No outside agent, Base Year Gross | P62: 3 | Q62: 45869 | R62: 45870
A63: R | B63: 508 | C63: Falcon Field Industrial | D63: 3960 E Palm | E63: 4 | F63: Mesa, AZ 85215 | G63: 2240 | H63: N-R-G Foam, Inc. | I63: 2396.8 | J63: =I63/G63 -> 1.07 | K63: 3225.6 | L63: =K63/G63 -> 1.44 | M63: =(K63/I63)-1 -> 0.34579439 | N63: 0.075 | O63: No TI, No Free rent, No outside agent, NNN | P63: 3 | Q63: 45930 | R63: 45931
A64: New | B64: 508 | C64: Falcon Field Industrial | D64: 3960 E. Palm Street, Suite 6 | G64: 2240 | H64: The Fur Seasons AZ LLC | K64: =G64*L64 -> 3360 | L64: 1.5 | N64: 0.06 | O64: 3 | P64: 5 | R64: 45992
A65: New | B65: 508 | C65: Falcon Field Industrial | D65: 3035 N Maple Street, Building 6 | G65: 3000 | H65: TMD Investments, LLC d/b/a Signarama and Fully Promoted | K65: =G65*L65 -> 4500 | L65: 1.5 | N65: 0.06 | P65: 3 | R65: 45992
A66: RX | B66: 503 | C66: Fiesta Center | D66: 75 W Baseline | E66: 52 | F66: Gilbert, AZ | G66: 4102 | H66: Eliete Packout LLC | I66: 4717.2 | J66: =I66/G66 -> 1.1499756 | K66: 10206.8 | L66: =K66/G66 -> 2.4882496 | M66: =(K66/I66)-1 -> 1.1637412 | N66: 0.07 | O66: No TI, No Free rent, No outside agent, Base Year Gross | P66: 2 | Q66: 45688 | R66: 45689
A67: New | B67: 503 | C67: Fiesta Center | D67: 75 W Baseline | E67: 50 | F67: Lease | G67: 3960 | H67: Desert Springs Bottlers, LLC | K67: =G67*L67 -> 5544 | L67: 1.4 | N67: 0.05 | O67: 1 | P67: 3 | R67: 45717
A68: R | B68: 503 | C68: Fiesta Center | D68: 75 W Baseline | E68: 11 | F68: Gilbert, AZ | G68: 1982 | H68: Anytime Home Services LLC | I68: 2457.68 | J68: =I68/$G68 -> 1.24 | K68: 2873.9 | L68: =K68/$G68 -> 1.45 | M68: =(K68/I68)-1 -> 0.16935484 | N68: 0.08 | O68: No TI, No Free rent, No outside agent, Base Year Gross, Tenant downsized | P68: 3 | Q68: 45747 | R68: 45748
A69: New | B69: 503 | C69: Fiesta Center | D69: 75 W Baseline | E69: 10 | F69: Lease | G69: 1982 | H69: Armor Fire | K69: =G69*L69 -> 2774.8 | L69: 1.4 | N69: 0.07 | O69: 2 | P69: 3 | R69: 45778
A70: New | B70: 503 | C70: Fiesta Center | D70: 75 W Baseline | E70: 4 | F70: Lease | G70: 2378 | H70: Quick Roofing | K70: =G70*L70 -> 3329.2 | L70: 1.4 | N70: 0.05 | O70: 1 | P70: 2 | R70: 45809
A71: R | B71: 503 | C71: Fiesta Center | D71: 75 W Baseline | E71: 44 | F71: Gilbert, AZ | G71: 6740 | H71: PurePak Technology Corp | I71: 5594.2 | J71: =I71/G71 -> 0.83 | K71: 9099 | L71: =K71/G71 -> 1.35 | M71: =(K71/I71)-1 -> 0.62650602 | N71: 0.07 | O71: No TI, No Free rent, No outside agent, Base Year Gross | P71: 3 | Q71: 45838 | R71: 45839
A72: New | B72: 503 | C72: Fiesta Center | D72: 75 W. Baseline Road, Suite 49 | E72: 49 | G72: 11051 | H72: Aquadei, LLC | K72: =G72*L72 -> 13813.75 | L72: 1.25 | N72: 0.05 | O72: 1 | P72: 5 | R72: 45931
A73: New | B73: 503 | C73: Fiesta Center | D73: 75 W. Baseline Road, Suite 14 | E73: 14 | G73: 1932 | H73: D & R Machinery Exchange L.L.C. | K73: =G73*L73 -> 2511.6 | L73: 1.3 | N73: 0.085 | P73: 3 | R73: 45931
A74: New | B74: 503 | C74: Fiesta Center | E74: 19-20 | F74: Lease | G74: 4506 | H74: Eco Roofing Solutions LLC | K74: =G74*L74 -> 6308.4 | L74: 1.4 | N74: 0.05 | O74: 3 | P74: 5 | R74: 45931
A75: OFS | B75: 503 | C75: Fiesta Center | D75: 75 W Baseline | E75: 9 | F75: Gilbert, AZ 85233 | G75: 1920 | H75: Connect Hearing, Inc. | I75: 2265.6 | J75: =I75/G75 -> 1.18 | K75: 2592 | L75: =K75/G75 -> 1.35 | M75: =(K75/I75)-1 -> 0.1440678 | N75: 0.075 | O75: No TI, No Free rent, No outside agent, Base Year Gross | P75: 3 | Q75: 45930 | R75: 45931
A76: R | B76: 503 | C76: Fiesta Center | D76: 75 W Baseline | E76: 17 | F76: Gilbert, AZ 85233 | G76: 1763 | H76: Big Show Autos | I76: 1921.67 | J76: =I76/G76 -> 1.09 | K76: 2291.9 | L76: =K76/G76 -> 1.3 | M76: =(K76/I76)-1 -> 0.19266055 | N76: 0.06 | O76: No TI, No Free rent, No outside agent, Base Year Gross | P76: 3 | Q76: 45991 | R76: 45992
A77: OFS | B77: 503 | C77: Fiesta Center | D77: 75 W Baseline | E77: 32 | F77: Gilbert, AZ 85233 | G77: 4000 | H77: ORKIN, LLC (Rollins AC) | I77: 5400 | J77: =I77/G77 -> 1.35 | K77: 6200 | L77: =K77/G77 -> 1.55 | M77: =(K77/I77)-1 -> 0.14814815 | N77: 0.06 | O77: No TI, 1 Mo Free rent, Site Selection outside agent, Base Year Gross | P77: 3 | Q77: 46022 | R77: 46023
A78: New | B78: 525 | C78: Fry Road Business Park | D78: 5609 W Frye | E78: 4 | F78: Lease | G78: 1222 | H78: Floteq USA LLC | K78: =G78*L78 -> 1588.6 | L78: 1.3 | N78: 0.05 | O78: 0 | P78: 3 | R78: 45778
A79: New | B79: 525 | C79: Fry Road Business Park | D79: 6505 W Frye | E79: 21 | F79: Lease | G79: 1260 | H79: K-Harper Corp d/b/a Sapper HVAC | K79: =G79*L79 -> 1638 | L79: 1.3 | N79: 0.05 | O79: 3 | P79: 3 | R79: 45823
A80: R | B80: 525 | C80: Fry Road Business Park | D80: 6505 W Frye Rd | E80: 22 | F80: Chandler, AZ | G80: 1260 | H80: Azpenn Power and Controls LLC | I80: 1449 | J80: =I80/G80 -> 1.15 | K80: 1675.8 | L80: =K80/G80 -> 1.33 | M80: =(K80/I80)-1 -> 0.15652174 | O80: No TI, No Free rent, No outside agent, Base Year Gross | P80: 1 | Q80: 45869 | R80: 45870
A81: New | B81: 525 | C81: Fry Road Business Park | D81: 6509 W Frye | E81: 5 | F81: Lease | G81: 1222 | H81: 5150 Motorsport LLC | K81: =G81*L81 -> 1649.7 | L81: 1.35 | N81: 0.06 | O81: 0 | P81: 3 | R81: 45901
A82: R | B82: 525 | C82: Fry Road Business Park | D82: 6501 W Frye | E82: 16 | F82: Chandler, 85226 | G82: 1460 | H82: BBQ Fans LLC | I82: 1270.2 | J82: =I82/G82 -> 0.87 | K82: 1898 | L82: =K82/G82 -> 1.3 | M82: =(K82/I82)-1 -> 0.49425287 | N82: 0.06 | O82: No TI, No Free rent, No outside agent, Base Year Gross | P82: 5 | Q82: 45900 | R82: 45901
A83: RX | B83: 525 | C83: Fry Road Business Park | D83: 6509 W Frye | E83: 6 | F83: Lease | G83: 2780 | H83: Perfect Party Planing | K83: =G83*L83 -> 3753 | L83: 1.35 | N83: 0.05 | P83: 3 | R83: 45901
A84: R | B84: 525 | C84: Fry Road Business Park | D84: 6509 W Frye Rd | E84: 12 | F84: Chandler, AZ 85226 | G84: 2780 | H84: Liquiserve, LLC | I84: 3196 | J84: =I84/G84 -> 1.1496403 | K84: 3780.8 | L84: =K84/G84 -> 1.36 | M84: =(K84/I84)-1 -> 0.18297872 | N84: 0.07 | O84: No TI, No Free rent, No outside agent, Base Year Gross | P84: 3 | Q84: 45930 | R84: 45931
A85: OFS | B85: 525 | C85: Fry Road Business Park | D85: 6505 W Frye Rd | E85: 23 | F85: Chandler, AZ 85226 | G85: 1260 | H85: PREMIER AIR SOLUTIONS ,INC | I85: 1701 | J85: =I85/G85 -> 1.35 | K85: 1789.2 | L85: =K85/G85 -> 1.42 | M85: =(K85/I85)-1 -> 0.051851852 | O85: No TI, No Free rent, No outside agent, Base Year Gross | P85: 1 | Q85: 45991 | R85: 45992
A86: R | B86: 537 | C86: Hayden Park | D86: 420 S Perry Ln | E86: 1, 2 | F86: Tempe, AZ | G86: 7590 | H86: The Grateful Bread | I86: 6678.33 | J86: =I86/G86 -> 0.87988538 | K86: 7590 | L86: =K86/G86 -> 1 | M86: =(K86/I86)-1 -> 0.13651167 | N86: 0.1 | O86: No TI, No Free rent, No outside agent, Base Year Gross | P86: 5 | Q86: 45716 | R86: 45717
A87: R | B87: 537 | C87: Hayden Park | D87: 402 S Perry Ln | E87: 3 | F87: Tempe, AZ | G87: 8772 | H87: Trusted Auto Sales Inc | I87: 8772 | J87: =I87/G87 -> 1 | K87: 10526.4 | L87: =K87/G87 -> 1.2 | M87: =(K87/I87)-1 -> 0.2 | N87: 0.055 | O87: No TI, No Free rent, No outside agent, Base Year Gross | P87: 3 | Q87: 45747 | R87: 45748
A88: New | B88: 537 | C88: Hayden Park | D88: 425 S McClintock | E88: 1,2 | F88: Lease | G88: 2995 | H88: Ms Fabrication LLC | K88: =G88*L88 -> 3444.25 | L88: 1.15 | N88: 0.05 | O88: 2 | P88: 3 | R88: 45809
A89: R | B89: 537 | C89: Hayden Park | D89: 415 S McClintock | E89: 5 | F89: Tempe, AZ | G89: 1768 | H89: Tim's Garage | I89: 1838.72 | J89: =I89/G89 -> 1.04 | K89: 2121.6 | L89: =K89/G89 -> 1.2 | M89: =(K89/I89)-1 -> 0.15384615 | N89: 0.05 | O89: No TI, No Free rent, No outside agent, Base Year Gross | P89: 3 | Q89: 45930 | R89: 45931
A90: R | B90: 537 | C90: Hayden Park | D90: 402 S Perry | E90: Suite 01 | F90: Tempe 85283 | G90: 4530 | H90: Tempe Speed and Performance | I90: 4711.2 | J90: =I90/G90 -> 1.04 | K90: 5209.5 | L90: =K90/G90 -> 1.15 | M90: =(K90/I90)-1 -> 0.10576923 | N90: 0.05 | O90: Repair roll up, No Free rent, Langdon Bridges (CPI), Base Year Gross | P90: 3 | Q90: 45961 | R90: 45962
A91: R | B91: 537 | C91: Hayden Park | D91: 425 S McClintock | E91: 5 | F91: Tempe, AZ | G91: 1536 | H91: Lihongsheng, LLC | I91: 1704.96 | J91: =I91/G91 -> 1.11 | K91: 1904.64 | L91: =K91/G91 -> 1.24 | M91: =(K91/I91)-1 -> 0.11711712 | N91: 0.06 | O91: No TI, 2 months Free rent, No outside agent, Base Year Gross | P91: 5 | Q91: 46022 | R91: 46023
A92: New | B92: 537 | C92: Hayden Park | F92: Lease | G92: 1427 | H92: LTJ Systems LLC | K92: =G92*L92 -> 0
A93: R | B93: 538 | C93: Horne Commerce Center | D93: 1817 S Horne | E93: 12 | F93: Mesa, AZ | G93: 2184 | H93: Bla Bla Auto Sales, LLC | I93: 2118.48 | J93: =I93/G93 -> 0.97 | K93: 2861.04 | L93: =K93/G93 -> 1.31 | M93: =(K93/I93)-1 -> 0.35051546 | N93: 0.07 | O93: No TI, No Free rent, No outside agent, Base Year Gross | P93: 3 | Q93: 45688 | R93: 45689
A94: R | B94: 538 | C94: Horne Commerce Center | D94: 1817 S Horne | E94: 7 | F94: Mesa, AZ | G94: 2184 | H94: Copper Sky Homes LLC | I94: 2817.36 | J94: =I94/G94 -> 1.29 | K94: 3188.64 | L94: =K94/G94 -> 1.46 | M94: =(K94/I94)-1 -> 0.13178295 | O94: No TI, No Free rent, No outside agent, Base Year Gross | P94: 1 | Q94: 45688 | R94: 45689
A95: New | B95: 538 | C95: Horne Commerce Center | D95: 1817 S Horne | E95: 11 | F95: Lease | G95: 2028 | H95: CTK Fabrication LLC | K95: =G95*L95 -> 2636.4 | L95: 1.3 | N95: 0.05 | O95: 1 | P95: 2 | R95: 45705
A96: New | B96: 538 | C96: Horne Commerce Center | D96: 1829 S Horne | E96: 4 | F96: Lease | G96: 2028 | H96: Shorai Service LLC | K96: =G96*L96 -> 2636.4 | L96: 1.3 | N96: 0.05 | P96: 2 | R96: 45809
A97: R | B97: 538 | C97: Horne Commerce Center | D97: 1829 S Horne | E97: 11 | F97: Mesa, AZ | G97: 2184 | H97: GreenTec Laboratories LLC | I97: 2511.6 | J97: =I97/G97 -> 1.15 | K97: 2970.24 | L97: =K97/G97 -> 1.36 | M97: =(K97/I97)-1 -> 0.1826087 | N97: 0.07 | O97: No TI, No Free rent, No outside agent, Base Year Gross | P97: 3 | Q97: 45838 | R97: 45839
A98: R | B98: 538 | C98: Horne Commerce Center | D98: 1817 S Horne | E98: 9 | F98: Mesa, AZ | G98: 2184 | H98: Peter W. Dreyer | I98: 2336.88 | J98: =I98/G98 -> 1.07 | K98: 2992.08 | L98: =K98/G98 -> 1.37 | M98: =(K98/I98)-1 -> 0.28037383 | N98: 0.07 | O98: No TI, No Free rent, No outside agent, Base Year Gross | P98: 3 | Q98: 45838 | R98: 45839
A99: New | B99: 538 | C99: Horne Commerce Center | D99: 1829 S Horne | E99: 8 | F99: Lease | G99: 2184 | H99: Cactus Golf Club LLC | K99: =G99*L99 -> 3057.6 | L99: 1.4 | N99: 0.05 | O99: 2 | P99: 3 | R99: 45901
A100: R | B100: 538 | C100: Horne Commerce Center | D100: 1817 S Horne | E100: Suite 1 & 2 | F100: Mesa, AZ 85204 | G100: 3276 | H100: The Jukebox Grounds | I100: 3505.32 | J100: =I100/G100 -> 1.07 | K100: 4389.84 | L100: =K100/G100 -> 1.34 | M100: =(K100/I100)-1 -> 0.25233645 | N100: 0.06 | O100: No TI, No Free rent, No outside agent, Base Year Gross | P100: 5 | Q100: =#REF! -> #REF! | R100: 45931
...

Sheet 120_Golden Key Plaza
A1: Golden Key Plaza | C1: 120 | D1: 2 | F1: =IFERROR(MATCH($C$1,'Working - CPI'!$A:$A,0),"") -> 224 | G1: =IFERROR(MATCH($C$1,'Lease Report 2025'!$B:$B,0),"") -> 2 | T1: Leasing Pipeline Report
A2: Gilbert, Arizona | C2: =IF(G2=0,"",(G2-E47)/G2) -> 0.94261858 | D2: % Occupancy | F2: SF | G2: ='Occupancy Summary Schedule'!$D$13 -> 63714 | U2: =TODAY() -> 46009 | AH2: SF Threshold
A3: ='Occupancy Summary Schedule'!F53 -> 0.88710744 | B3: % CPI Portfolio Occupancy | AH3: 5000
A4: Active Lease Deals | W4: NER Calculations | AJ4: # | AK4: List
G5: RENT | J5: TERM | L5: TI | N5: Free Rent | P5: Bumps (%) | Q5: LCs | R5: NER | S5: NER Check | V5: NER Check | W5: Subtotals | AB5: Budget / Actual | AE5: Term | AJ5: 0 | AK5: Good | AM5: Raleigh Light Industrial - Rent Bump Calculation | BD5: Raleigh Light Industrial - Rent Bump Calculation (Monthly Rents)
A6: Broker | B6: Tenant | C6: Building | D6: Suite | E6: SF | F6: Type | G6: Current | H6: CPI Proj | I6: Proposed | J6: Budget | K6: Proposed | L6: Budget | M6: Proposed | N6: Budget | O6: Proposed | P6: Proposed | Q6: Proposed | R6: Proposed | T6: Expiration | U6: Comments | W6: Revenue | X6: Bumps | Y6: TIs | Z6: LCs | AA6: FR | AB6: Rent | AC6: FR | AD6: TI | AE6: Years | AF6: Month | AG6: Total | AH6: Term Check | AJ6: 1 | AK6: Check Term | AL6: Month: | AM6: 12 | AN6: =AM6+12 -> 24 | AO6: =AN6+12 -> 36 | AP6: =AO6+12 -> 48 | AQ6: =AP6+12 -> 60 | AR6: =AQ6+12 -> 72 | AS6: =AR6+12 -> 84 | AT6: =AS6+12 -> 96 | AU6: =AT6+12 -> 108 | ... BB6: =BA6+12 -> 192 | BD6: =AM6 -> 12 | BE6: =AN6 -> 24 | BF6: =AO6 -> 36 | BG6: =AP6 -> 48 | BH6: =AQ6 -> 60 | BI6: =AR6 -> 72 | BJ6: =AS6 -> 84 | BK6: =AT6 -> 96 | ... BS6: =BB6 -> 192
W7: =AB7*E7*(AG7/12) -> 0 | X7: =SUMIFS($AM7:$BB7,$AM$6:$BB$6,"<="&AG7)+(INDEX($BD7:$BS7,MATCH(AG7+12,$AM$6:$BB$6))*(AG7-INDEX($AM$6:$BB$6,MATCH(AG7,$AM$6:$BB$6))))-W7 -> #N/A | Y7: =AD7*E7 -> 0 | Z7: =SUM(W7:X7)*Q7 -> #N/A | AA7: =AB7/12*E7*AC7 -> 0 | AB7: =IF(I7="",H7,I7) -> 0 | AC7: =IF(O7="",N7,O7) -> 0 | AD7: =IF(M7="",L7,M7) -> 0 | AE7: =IFERROR(LEFT(K7, FIND("-", K7) - 1),J7) -> 0 | AF7: =IFERROR(RIGHT(K7,LEN(K7)-SEARCH("-",K7)),0) -> 0 | AG7: =_xlfn.NUMBERVALUE(AE7)*12+_xlfn.NUMBERVALUE(AF7) -> 0 | AH7: =IF(E7<$AH$3,36,60) -> 36 | AJ7: 2 | AK7: Check | AM7: =AB7*$E7 -> 0 | AN7: =AM7*(1+$P7) -> 0 | AO7: =AN7*(1+$P7) -> 0 | AP7: =AO7*(1+$P7) -> 0 | AQ7: =AP7*(1+$P7) -> 0 | AR7: =AQ7*(1+$P7) -> 0 | AS7: =AR7*(1+$P7) -> 0 | AT7: =AS7*(1+$P7) -> 0 | AU7: =AT7*(1+$P7) -> 0 | ... BB7: =BA7*(1+$P7) -> 0 | BD7: =AM7/12 -> 0 | BE7: =AN7/12 -> 0 | BF7: =AO7/12 -> 0 | BG7: =AP7/12 -> 0 | BH7: =AQ7/12 -> 0 | BI7: =AR7/12 -> 0 | BJ7: =AS7/12 -> 0 | BK7: =AT7/12 -> 0 | ... BS7: =BB7/12 -> 0
W9: =AB9*E9*(AG9/12) -> 0 | X9: =SUMIFS($AM9:$BB9,$AM$6:$BB$6,"<="&AG9)+(INDEX($BD9:$BS9,MATCH(AG9+12,$AM$6:$BB$6))*(AG9-INDEX($AM$6:$BB$6,MATCH(AG9,$AM$6:$BB$6))))-W9 -> #N/A | Y9: =AD9*E9 -> 0 | Z9: =SUM(W9:X9)*Q9 -> #N/A | AA9: =AB9/12*E9*AC9 -> 0 | AB9: =IF(I9="",H9,I9) -> 0 | AC9: =IF(O9="",N9,O9) -> 0 | AD9: =IF(M9="",L9,M9) -> 0 | AE9: =IFERROR(LEFT(K9, FIND("-", K9) - 1),J9) -> 0 | AF9: =IFERROR(RIGHT(K9,LEN(K9)-SEARCH("-",K9)),0) -> 0 | AG9: =_xlfn.NUMBERVALUE(AE9)*12+_xlfn.NUMBERVALUE(AF9) -> 0 | AH9: =IF(E9<$AH$3,36,60) -> 36 | AM9: =AB9*$E9 -> 0 | AN9: =AM9*(1+$P9) -> 0 | AO9: =AN9*(1+$P9) -> 0 | AP9: =AO9*(1+$P9) -> 0 | AQ9: =AP9*(1+$P9) -> 0 | AR9: =AQ9*(1+$P9) -> 0 | AS9: =AR9*(1+$P9) -> 0 | AT9: =AS9*(1+$P9) -> 0 | AU9: =AT9*(1+$P9) -> 0 | ... BB9: =BA9*(1+$P9) -> 0 | BD9: =AM9/12 -> 0 | BE9: =AN9/12 -> 0 | BF9: =AO9/12 -> 0 | BG9: =AP9/12 -> 0 | BH9: =AQ9/12 -> 0 | BI9: =AR9/12 -> 0 | BJ9: =AS9/12 -> 0 | BK9: =AT9/12 -> 0 | ... BS9: =BB9/12 -> 0
W10: =AB10*E10*(AG10/12) -> 0 | X10: =SUMIFS($AM10:$BB10,$AM$6:$BB$6,"<="&AG10)+(INDEX($BD10:$BS10,MATCH(AG10+12,$AM$6:$BB$6))*(AG10-INDEX($AM$6:$BB$6,MATCH(AG10,$AM$6:$BB$6))))-W10 -> #N/A | Y10: =AD10*E10 -> 0 | Z10: =SUM(W10:X10)*Q10 -> #N/A | AA10: =AB10/12*E10*AC10 -> 0 | AB10: =IF(I10="",H10,I10) -> 0 | AC10: =IF(O10="",N10,O10) -> 0 | AD10: =IF(M10="",L10,M10) -> 0 | AE10: =IFERROR(LEFT(K10, FIND("-", K10) - 1),J10) -> 0 | AF10: =IFERROR(RIGHT(K10,LEN(K10)-SEARCH("-",K10)),0) -> 0 | AG10: =_xlfn.NUMBERVALUE(AE10)*12+_xlfn.NUMBERVALUE(AF10) -> 0 | AH10: =IF(E10<$AH$3,36,60) -> 36 | AM10: =AB10*$E10 -> 0 | AN10: =AM10*(1+$P10) -> 0 | AO10: =AN10*(1+$P10) -> 0 | AP10: =AO10*(1+$P10) -> 0 | AQ10: =AP10*(1+$P10) -> 0 | AR10: =AQ10*(1+$P10) -> 0 | AS10: =AR10*(1+$P10) -> 0 | AT10: =AS10*(1+$P10) -> 0 | AU10: =AT10*(1+$P10) -> 0 | ... BB10: =BA10*(1+$P10) -> 0 | BD10: =AM10/12 -> 0 | BE10: =AN10/12 -> 0 | BF10: =AO10/12 -> 0 | BG10: =AP10/12 -> 0 | BH10: =AQ10/12 -> 0 | BI10: =AR10/12 -> 0 | BJ10: =AS10/12 -> 0 | BK10: =AT10/12 -> 0 | ... BS10: =BB10/12 -> 0
A11: Tenants Expiring - Next 6 months
A13: Broker | B13: Tenant | C13: Building | D13: Suite | E13: SF | F13: Expires | G13: Current | H13: Budget | I13: Proposed 3 Year | J13: Proposed 5 Year | K13: Notes | W13: Revenue | X13: Bumps | Y13: TIs | Z13: LCs | AA13: FR | AB13: Rent | AC13: FR | AD13: TI | AE13: Years | AF13: Month | AG13: Total | AH13: Term Check | AJ13: 1 | AK13: Check Term | AL13: Month: | AM13: 12 | AN13: =AM13+12 -> 24 | AO13: =AN13+12 -> 36 | AP13: =AO13+12 -> 48 | AQ13: =AP13+12 -> 60 | AR13: =AQ13+12 -> 72 | AS13: =AR13+12 -> 84 | AT13: =AS13+12 -> 96 | AU13: =AT13+12 -> 108 | ... BB13: =BA13+12 -> 192 | BD13: =AM13 -> 12 | BE13: =AN13 -> 24 | BF13: =AO13 -> 36 | BG13: =AP13 -> 48 | BH13: =AQ13 -> 60 | BI13: =AR13 -> 72 | BJ13: =AS13 -> 84 | BK13: =AT13 -> 96 | ... BS13: =BB13 -> 192
B14: =IF($D$1="","",IF(INDEX('January 2026 Renewals'!$A:$A,$D$1+ROW()-ROW($B$14))<>$C$1,"",INDEX('January 2026 Renewals'!$H:$H,$D$1+ROW()-ROW($B$14)))) -> Essen Floors LLC | C14: =IF($D$1="","",IF(INDEX('January 2026 Renewals'!$A:$A,$D$1+ROW()-ROW($B$14))<>$C$1,"",INDEX('January 2026 Renewals'!$C:$C,$D$1+ROW()-ROW($B$14)))) -> 751-121 | D14: =IF($D$1="","",IF(INDEX('January 2026 Renewals'!$A:$A,$D$1+ROW()-ROW($B$14))<>$C$1,"",INDEX('January 2026 Renewals'!$E:$E,$D$1+ROW()-ROW($B$14)))) -> 121 | E14: =IF($D$1="","",IF(INDEX('January 2026 Renewals'!$A:$A,$D$1+ROW()-ROW($B$14))<>$C$1,"",INDEX('January 2026 Renewals'!$G:$G,$D$1+ROW()-ROW($B$14)))) -> 1191 | F14: =IF($D$1="","",IF(INDEX('January 2026 Renewals'!$A:$A,$D$1+ROW()-ROW($B$14))<>$C$1,"",INDEX('January 2026 Renewals'!$I:$I,$D$1+ROW()-ROW($B$14)))) -> 46053 | G14: =IF($D$1="","",IF(INDEX('January 2026 Renewals'!$A:$A,$D$1+ROW()-ROW($B$14))<>$C$1,"",INDEX('January 2026 Renewals'!$Q:$Q,$D$1+ROW()-ROW($B$14)))) -> 1.4 | H14: =IF($D$1="","",IF(INDEX('January 2026 Renewals'!$A:$A,$D$1+ROW()-ROW($B$14))<>$C$1,"",INDEX('January 2026 Renewals'!$R:$R,$D$1+ROW()-ROW($B$14)))) -> 1.4 | I14: =IF($D$1="","",IF(INDEX('January 2026 Renewals'!$A:$A,$D$1+ROW()-ROW($B$14))<>$C$1,"",INDEX('January 2026 Renewals'!$W:$W,$D$1+ROW()-ROW($B$14)))) -> 1.47 | J14: =IF($D$1="","",IF(INDEX('January 2026 Renewals'!$A:$A,$D$1+ROW()-ROW($B$14))<>$C$1,"",INDEX('January 2026 Renewals'!$AC:$AC,$D$1+ROW()-ROW($B$14)))) -> 1.47 | K14: =IF($D$1="","",IF(INDEX('January 2026 Renewals'!$A:$A,$D$1+ROW()-ROW($B$14))<>$C$1,"",INDEX('January 2026 Renewals'!$AM:$AM,$D$1+ROW()-ROW($B$14)))) -> 12.8.25 Follow up Email
B15: =IF($D$1="","",IF(INDEX('January 2026 Renewals'!$A:$A,$D$1+ROW()-ROW($B$14))<>$C$1,"",INDEX('January 2026 Renewals'!$H:$H,$D$1+ROW()-ROW($B$14)))) -> FLY PROMOTIONS LLC | C15: =IF($D$1="","",IF(INDEX('January 2026 Renewals'!$A:$A,$D$1+ROW()-ROW($B$14))<>$C$1,"",INDEX('January 2026 Renewals'!$C:$C,$D$1+ROW()-ROW($B$14)))) -> 751-111 | D15: =IF($D$1="","",IF(INDEX('January 2026 Renewals'!$A:$A,$D$1+ROW()-ROW($B$14))<>$C$1,"",INDEX('January 2026 Renewals'!$E:$E,$D$1+ROW()-ROW($B$14)))) -> 111 | E15: =IF($D$1="","",IF(INDEX('January 2026 Renewals'!$A:$A,$D$1+ROW()-ROW($B$14))<>$C$1,"",INDEX('January 2026 Renewals'!$G:$G,$D$1+ROW()-ROW($B$14)))) -> 1191 | F15: =IF($D$1="","",IF(INDEX('January 2026 Renewals'!$A:$A,$D$1+ROW()-ROW($B$14))<>$C$1,"",INDEX('January 2026 Renewals'!$I:$I,$D$1+ROW()-ROW($B$14)))) -> 46053 | G15: =IF($D$1="","",IF(INDEX('January 2026 Renewals'!$A:$A,$D$1+ROW()-ROW($B$14))<>$C$1,"",INDEX('January 2026 Renewals'!$Q:$Q,$D$1+ROW()-ROW($B$14)))) -> 1.47 | H15: =IF($D$1="","",IF(INDEX('January 2026 Renewals'!$A:$A,$D$1+ROW()-ROW($B$14))<>$C$1,"",INDEX('January 2026 Renewals'!$R:$R,$D$1+ROW()-ROW($B$14)))) -> 1.4 | I15: =IF($D$1="","",IF(INDEX('January 2026 Renewals'!$A:$A,$D$1+ROW()-ROW($B$14))<>$C$1,"",INDEX('January 2026 Renewals'!$W:$W,$D$1+ROW()-ROW($B$14)))) -> 1.54 | J15: =IF($D$1="","",IF(INDEX('January 2026 Renewals'!$A:$A,$D$1+ROW()-ROW($B$14))<>$C$1,"",INDEX('January 2026 Renewals'!$AC:$AC,$D$1+ROW()-ROW($B$14)))) -> 1.54 | K15: =IF($D$1="","",IF(INDEX('January 2026 Renewals'!$A:$A,$D$1+ROW()-ROW($B$14))<>$C$1,"",INDEX('January 2026 Renewals'!$AM:$AM,$D$1+ROW()-ROW($B$14)))) -> 12.8.25 Follow up Email
B16: =IF($D$1="","",IF(INDEX('January 2026 Renewals'!$A:$A,$D$1+ROW()-ROW($B$14))<>$C$1,"",INDEX('January 2026 Renewals'!$H:$H,$D$1+ROW()-ROW($B$14)))) -> Samuel Coffey and Brianne Coffey | C16: =IF($D$1="","",IF(INDEX('January 2026 Renewals'!$A:$A,$D$1+ROW()-ROW($B$14))<>$C$1,"",INDEX('January 2026 Renewals'!$C:$C,$D$1+ROW()-ROW($B$14)))) -> 751-117 | D16: =IF($D$1="","",IF(INDEX('January 2026 Renewals'!$A:$A,$D$1+ROW()-ROW($B$14))<>$C$1,"",INDEX('January 2026 Renewals'!$E:$E,$D$1+ROW()-ROW($B$14)))) -> 117 | E16: =IF($D$1="","",IF(INDEX('January 2026 Renewals'!$A:$A,$D$1+ROW()-ROW($B$14))<>$C$1,"",INDEX('January 2026 Renewals'!$G:$G,$D$1+ROW()-ROW($B$14)))) -> 1191 | F16: =IF($D$1="","",IF(INDEX('January 2026 Renewals'!$A:$A,$D$1+ROW()-ROW($B$14))<>$C$1,"",INDEX('January 2026 Renewals'!$I:$I,$D$1+ROW()-ROW($B$14)))) -> 46081 | G16: =IF($D$1="","",IF(INDEX('January 2026 Renewals'!$A:$A,$D$1+ROW()-ROW($B$14))<>$C$1,"",INDEX('January 2026 Renewals'!$Q:$Q,$D$1+ROW()-ROW($B$14)))) -> 1.47 | H16: =IF($D$1="","",IF(INDEX('January 2026 Renewals'!$A:$A,$D$1+ROW()-ROW($B$14))<>$C$1,"",INDEX('January 2026 Renewals'!$R:$R,$D$1+ROW()-ROW($B$14)))) -> 1.4 | I16: =IF($D$1="","",IF(INDEX('January 2026 Renewals'!$A:$A,$D$1+ROW()-ROW($B$14))<>$C$1,"",INDEX('January 2026 Renewals'!$W:$W,$D$1+ROW()-ROW($B$14)))) -> 1.54 | J16: =IF($D$1="","",IF(INDEX('January 2026 Renewals'!$A:$A,$D$1+ROW()-ROW($B$14))<>$C$1,"",INDEX('January 2026 Renewals'!$AC:$AC,$D$1+ROW()-ROW($B$14)))) -> 1.54 | K16: =IF($D$1="","",IF(INDEX('January 2026 Renewals'!$A:$A,$D$1+ROW()-ROW($B$14))<>$C$1,"",INDEX('January 2026 Renewals'!$AM:$AM,$D$1+ROW()-ROW($B$14)))) -> Terminating
B17: =IF($D$1="","",IF(INDEX('January 2026 Renewals'!$A:$A,$D$1+ROW()-ROW($B$14))<>$C$1,"",INDEX('January 2026 Renewals'!$H:$H,$D$1+ROW()-ROW($B$14)))) -> Innovative Cutting Systems | C17: =IF($D$1="","",IF(INDEX('January 2026 Renewals'!$A:$A,$D$1+ROW()-ROW($B$14))<>$C$1,"",INDEX('January 2026 Renewals'!$C:$C,$D$1+ROW()-ROW($B$14)))) -> 425-105/761-102 | D17: =IF($D$1="","",IF(INDEX('January 2026 Renewals'!$A:$A,$D$1+ROW()-ROW($B$14))<>$C$1,"",INDEX('January 2026 Renewals'!$E:$E,$D$1+ROW()-ROW($B$14)))) -> Base | E17: =IF($D$1="","",IF(INDEX('January 2026 Renewals'!$A:$A,$D$1+ROW()-ROW($B$14))<>$C$1,"",INDEX('January 2026 Renewals'!$G:$G,$D$1+ROW()-ROW($B$14)))) -> 4173 | F17: =IF($D$1="","",IF(INDEX('January 2026 Renewals'!$A:$A,$D$1+ROW()-ROW($B$14))<>$C$1,"",INDEX('January 2026 Renewals'!$I:$I,$D$1+ROW()-ROW($B$14)))) -> 46203 | G17: =IF($D$1="","",IF(INDEX('January 2026 Renewals'!$A:$A,$D$1+ROW()-ROW($B$14))<>$C$1,"",INDEX('January 2026 Renewals'!$Q:$Q,$D$1+ROW()-ROW($B$14)))) -> 1.27 | H17: =IF($D$1="","",IF(INDEX('January 2026 Renewals'!$A:$A,$D$1+ROW()-ROW($B$14))<>$C$1,"",INDEX('January 2026 Renewals'!$R:$R,$D$1+ROW()-ROW($B$14)))) -> 1.4 | I17: =IF($D$1="","",IF(INDEX('January 2026 Renewals'!$A:$A,$D$1+ROW()-ROW($B$14))<>$C$1,"",INDEX('January 2026 Renewals'!$W:$W,$D$1+ROW()-ROW($B$14)))) -> 1.37 | J17: =IF($D$1="","",IF(INDEX('January 2026 Renewals'!$A:$A,$D$1+ROW()-ROW($B$14))<>$C$1,"",INDEX('January 2026 Renewals'!$AC:$AC,$D$1+ROW()-ROW($B$14)))) -> 1.36 | K17: =IF($D$1="","",IF(INDEX('January 2026 Renewals'!$A:$A,$D$1+ROW()-ROW($B$14))<>$C$1,"",INDEX('January 2026 Renewals'!$AM:$AM,$D$1+ROW()-ROW($B$14)))) -> 0
B18: =IF($D$1="","",IF(INDEX('January 2026 Renewals'!$A:$A,$D$1+ROW()-ROW($B$14))<>$C$1,"",INDEX('January 2026 Renewals'!$H:$H,$D$1+ROW()-ROW($B$14)))) | C18: =IF($D$1="","",IF(INDEX('January 2026 Renewals'!$A:$A,$D$1+ROW()-ROW($B$14))<>$C$1,"",INDEX('January 2026 Renewals'!$C:$C,$D$1+ROW()-ROW($B$14)))) | D18: =IF($D$1="","",IF(INDEX('January 2026 Renewals'!$A:$A,$D$1+ROW()-ROW($B$14))<>$C$1,"",INDEX('January 2026 Renewals'!$E:$E,$D$1+ROW()-ROW($B$14)))) | E18: =IF($D$1="","",IF(INDEX('January 2026 Renewals'!$A:$A,$D$1+ROW()-ROW($B$14))<>$C$1,"",INDEX('January 2026 Renewals'!$G:$G,$D$1+ROW()-ROW($B$14)))) | F18: =IF($D$1="","",IF(INDEX('January 2026 Renewals'!$A:$A,$D$1+ROW()-ROW($B$14))<>$C$1,"",INDEX('January 2026 Renewals'!$I:$I,$D$1+ROW()-ROW($B$14)))) | G18: =IF($D$1="","",IF(INDEX('January 2026 Renewals'!$A:$A,$D$1+ROW()-ROW($B$14))<>$C$1,"",INDEX('January 2026 Renewals'!$Q:$Q,$D$1+ROW()-ROW($B$14)))) | H18: =IF($D$1="","",IF(INDEX('January 2026 Renewals'!$A:$A,$D$1+ROW()-ROW($B$14))<>$C$1,"",INDEX('January 2026 Renewals'!$R:$R,$D$1+ROW()-ROW($B$14)))) | I18: =IF($D$1="","",IF(INDEX('January 2026 Renewals'!$A:$A,$D$1+ROW()-ROW($B$14))<>$C$1,"",INDEX('January 2026 Renewals'!$W:$W,$D$1+ROW()-ROW($B$14)))) | J18: =IF($D$1="","",IF(INDEX('January 2026 Renewals'!$A:$A,$D$1+ROW()-ROW($B$14))<>$C$1,"",INDEX('January 2026 Renewals'!$AC:$AC,$D$1+ROW()-ROW($B$14)))) | K18: =IF($D$1="","",IF(INDEX('January 2026 Renewals'!$A:$A,$D$1+ROW()-ROW($B$14))<>$C$1,"",INDEX('January 2026 Renewals'!$AM:$AM,$D$1+ROW()-ROW($B$14))))
B19: =IF($D$1="","",IF(INDEX('January 2026 Renewals'!$A:$A,$D$1+ROW()-ROW($B$14))<>$C$1,"",INDEX('January 2026 Renewals'!$H:$H,$D$1+ROW()-ROW($B$14)))) | C19: =IF($D$1="","",IF(INDEX('January 2026 Renewals'!$A:$A,$D$1+ROW()-ROW($B$14))<>$C$1,"",INDEX('January 2026 Renewals'!$C:$C,$D$1+ROW()-ROW($B$14)))) | D19: =IF($D$1="","",IF(INDEX('January 2026 Renewals'!$A:$A,$D$1+ROW()-ROW($B$14))<>$C$1,"",INDEX('January 2026 Renewals'!$E:$E,$D$1+ROW()-ROW($B$14)))) | E19: =IF($D$1="","",IF(INDEX('January 2026 Renewals'!$A:$A,$D$1+ROW()-ROW($B$14))<>$C$1,"",INDEX('January 2026 Renewals'!$G:$G,$D$1+ROW()-ROW($B$14)))) | F19: =IF($D$1="","",IF(INDEX('January 2026 Renewals'!$A:$A,$D$1+ROW()-ROW($B$14))<>$C$1,"",INDEX('January 2026 Renewals'!$I:$I,$D$1+ROW()-ROW($B$14)))) | G19: =IF($D$1="","",IF(INDEX('January 2026 Renewals'!$A:$A,$D$1+ROW()-ROW($B$14))<>$C$1,"",INDEX('January 2026 Renewals'!$Q:$Q,$D$1+ROW()-ROW($B$14)))) | H19: =IF($D$1="","",IF(INDEX('January 2026 Renewals'!$A:$A,$D$1+ROW()-ROW($B$14))<>$C$1,"",INDEX('January 2026 Renewals'!$R:$R,$D$1+ROW()-ROW($B$14)))) | I19: =IF($D$1="","",IF(INDEX('January 2026 Renewals'!$A:$A,$D$1+ROW()-ROW($B$14))<>$C$1,"",INDEX('January 2026 Renewals'!$W:$W,$D$1+ROW()-ROW($B$14)))) | J19: =IF($D$1="","",IF(INDEX('January 2026 Renewals'!$A:$A,$D$1+ROW()-ROW($B$14))<>$C$1,"",INDEX('January 2026 Renewals'!$AC:$AC,$D$1+ROW()-ROW($B$14)))) | K19: =IF($D$1="","",IF(INDEX('January 2026 Renewals'!$A:$A,$D$1+ROW()-ROW($B$14))<>$C$1,"",INDEX('January 2026 Renewals'!$AM:$AM,$D$1+ROW()-ROW($B$14))))
B20: =IF($D$1="","",IF(INDEX('January 2026 Renewals'!$A:$A,$D$1+ROW()-ROW($B$14))<>$C$1,"",INDEX('January 2026 Renewals'!$H:$H,$D$1+ROW()-ROW($B$14)))) | C20: =IF($D$1="","",IF(INDEX('January 2026 Renewals'!$A:$A,$D$1+ROW()-ROW($B$14))<>$C$1,"",INDEX('January 2026 Renewals'!$C:$C,$D$1+ROW()-ROW($B$14)))) | D20: =IF($D$1="","",IF(INDEX('January 2026 Renewals'!$A:$A,$D$1+ROW()-ROW($B$14))<>$C$1,"",INDEX('January 2026 Renewals'!$E:$E,$D$1+ROW()-ROW($B$14)))) | E20: =IF($D$1="","",IF(INDEX('January 2026 Renewals'!$A:$A,$D$1+ROW()-ROW($B$14))<>$C$1,"",INDEX('January 2026 Renewals'!$G:$G,$D$1+ROW()-ROW($B$14)))) | F20: =IF($D$1="","",IF(INDEX('January 2026 Renewals'!$A:$A,$D$1+ROW()-ROW($B$14))<>$C$1,"",INDEX('January 2026 Renewals'!$I:$I,$D$1+ROW()-ROW($B$14)))) | G20: =IF($D$1="","",IF(INDEX('January 2026 Renewals'!$A:$A,$D$1+ROW()-ROW($B$14))<>$C$1,"",INDEX('January 2026 Renewals'!$Q:$Q,$D$1+ROW()-ROW($B$14)))) | H20: =IF($D$1="","",IF(INDEX('January 2026 Renewals'!$A:$A,$D$1+ROW()-ROW($B$14))<>$C$1,"",INDEX('January 2026 Renewals'!$R:$R,$D$1+ROW()-ROW($B$14)))) | I20: =IF($D$1="","",IF(INDEX('January 2026 Renewals'!$A:$A,$D$1+ROW()-ROW($B$14))<>$C$1,"",INDEX('January 2026 Renewals'!$W:$W,$D$1+ROW()-ROW($B$14)))) | J20: =IF($D$1="","",IF(INDEX('January 2026 Renewals'!$A:$A,$D$1+ROW()-ROW($B$14))<>$C$1,"",INDEX('January 2026 Renewals'!$AC:$AC,$D$1+ROW()-ROW($B$14)))) | K20: =IF($D$1="","",IF(INDEX('January 2026 Renewals'!$A:$A,$D$1+ROW()-ROW($B$14))<>$C$1,"",INDEX('January 2026 Renewals'!$AM:$AM,$D$1+ROW()-ROW($B$14))))
B21: =IF($D$1="","",IF(INDEX('January 2026 Renewals'!$A:$A,$D$1+ROW()-ROW($B$14))<>$C$1,"",INDEX('January 2026 Renewals'!$H:$H,$D$1+ROW()-ROW($B$14)))) | C21: =IF($D$1="","",IF(INDEX('January 2026 Renewals'!$A:$A,$D$1+ROW()-ROW($B$14))<>$C$1,"",INDEX('January 2026 Renewals'!$C:$C,$D$1+ROW()-ROW($B$14)))) | D21: =IF($D$1="","",IF(INDEX('January 2026 Renewals'!$A:$A,$D$1+ROW()-ROW($B$14))<>$C$1,"",INDEX('January 2026 Renewals'!$E:$E,$D$1+ROW()-ROW($B$14)))) | E21: =IF($D$1="","",IF(INDEX('January 2026 Renewals'!$A:$A,$D$1+ROW()-ROW($B$14))<>$C$1,"",INDEX('January 2026 Renewals'!$G:$G,$D$1+ROW()-ROW($B$14)))) | F21: =IF($D$1="","",IF(INDEX('January 2026 Renewals'!$A:$A,$D$1+ROW()-ROW($B$14))<>$C$1,"",INDEX('January 2026 Renewals'!$I:$I,$D$1+ROW()-ROW($B$14)))) | G21: =IF($D$1="","",IF(INDEX('January 2026 Renewals'!$A:$A,$D$1+ROW()-ROW($B$14))<>$C$1,"",INDEX('January 2026 Renewals'!$Q:$Q,$D$1+ROW()-ROW($B$14)))) | H21: =IF($D$1="","",IF(INDEX('January 2026 Renewals'!$A:$A,$D$1+ROW()-ROW($B$14))<>$C$1,"",INDEX('January 2026 Renewals'!$R:$R,$D$1+ROW()-ROW($B$14)))) | I21: =IF($D$1="","",IF(INDEX('January 2026 Renewals'!$A:$A,$D$1+ROW()-ROW($B$14))<>$C$1,"",INDEX('January 2026 Renewals'!$W:$W,$D$1+ROW()-ROW($B$14)))) | J21: =IF($D$1="","",IF(INDEX('January 2026 Renewals'!$A:$A,$D$1+ROW()-ROW($B$14))<>$C$1,"",INDEX('January 2026 Renewals'!$AC:$AC,$D$1+ROW()-ROW($B$14)))) | K21: =IF($D$1="","",IF(INDEX('January 2026 Renewals'!$A:$A,$D$1+ROW()-ROW($B$14))<>$C$1,"",INDEX('January 2026 Renewals'!$AM:$AM,$D$1+ROW()-ROW($B$14))))
B22: =IF($D$1="","",IF(INDEX('January 2026 Renewals'!$A:$A,$D$1+ROW()-ROW($B$14))<>$C$1,"",INDEX('January 2026 Renewals'!$H:$H,$D$1+ROW()-ROW($B$14)))) | C22: =IF($D$1="","",IF(INDEX('January 2026 Renewals'!$A:$A,$D$1+ROW()-ROW($B$14))<>$C$1,"",INDEX('January 2026 Renewals'!$C:$C,$D$1+ROW()-ROW($B$14)))) | D22: =IF($D$1="","",IF(INDEX('January 2026 Renewals'!$A:$A,$D$1+ROW()-ROW($B$14))<>$C$1,"",INDEX('January 2026 Renewals'!$E:$E,$D$1+ROW()-ROW($B$14)))) | E22: =IF($D$1="","",IF(INDEX('January 2026 Renewals'!$A:$A,$D$1+ROW()-ROW($B$14))<>$C$1,"",INDEX('January 2026 Renewals'!$G:$G,$D$1+ROW()-ROW($B$14)))) | F22: =IF($D$1="","",IF(INDEX('January 2026 Renewals'!$A:$A,$D$1+ROW()-ROW($B$14))<>$C$1,"",INDEX('January 2026 Renewals'!$I:$I,$D$1+ROW()-ROW($B$14)))) | G22: =IF($D$1="","",IF(INDEX('January 2026 Renewals'!$A:$A,$D$1+ROW()-ROW($B$14))<>$C$1,"",INDEX('January 2026 Renewals'!$Q:$Q,$D$1+ROW()-ROW($B$14)))) | H22: =IF($D$1="","",IF(INDEX('January 2026 Renewals'!$A:$A,$D$1+ROW()-ROW($B$14))<>$C$1,"",INDEX('January 2026 Renewals'!$R:$R,$D$1+ROW()-ROW($B$14)))) | I22: =IF($D$1="","",IF(INDEX('January 2026 Renewals'!$A:$A,$D$1+ROW()-ROW($B$14))<>$C$1,"",INDEX('January 2026 Renewals'!$W:$W,$D$1+ROW()-ROW($B$14)))) | J22: =IF($D$1="","",IF(INDEX('January 2026 Renewals'!$A:$A,$D$1+ROW()-ROW($B$14))<>$C$1,"",INDEX('January 2026 Renewals'!$AC:$AC,$D$1+ROW()-ROW($B$14)))) | K22: =IF($D$1="","",IF(INDEX('January 2026 Renewals'!$A:$A,$D$1+ROW()-ROW($B$14))<>$C$1,"",INDEX('January 2026 Renewals'!$AM:$AM,$D$1+ROW()-ROW($B$14))))
B23: =IF($D$1="","",IF(INDEX('January 2026 Renewals'!$A:$A,$D$1+ROW()-ROW($B$14))<>$C$1,"",INDEX('January 2026 Renewals'!$H:$H,$D$1+ROW()-ROW($B$14)))) | C23: =IF($D$1="","",IF(INDEX('January 2026 Renewals'!$A:$A,$D$1+ROW()-ROW($B$14))<>$C$1,"",INDEX('January 2026 Renewals'!$C:$C,$D$1+ROW()-ROW($B$14)))) | D23: =IF($D$1="","",IF(INDEX('January 2026 Renewals'!$A:$A,$D$1+ROW()-ROW($B$14))<>$C$1,"",INDEX('January 2026 Renewals'!$E:$E,$D$1+ROW()-ROW($B$14)))) | E23: =IF($D$1="","",IF(INDEX('January 2026 Renewals'!$A:$A,$D$1+ROW()-ROW($B$14))<>$C$1,"",INDEX('January 2026 Renewals'!$G:$G,$D$1+ROW()-ROW($B$14)))) | F23: =IF($D$1="","",IF(INDEX('January 2026 Renewals'!$A:$A,$D$1+ROW()-ROW($B$14))<>$C$1,"",INDEX('January 2026 Renewals'!$I:$I,$D$1+ROW()-ROW($B$14)))) | G23: =IF($D$1="","",IF(INDEX('January 2026 Renewals'!$A:$A,$D$1+ROW()-ROW($B$14))<>$C$1,"",INDEX('January 2026 Renewals'!$Q:$Q,$D$1+ROW()-ROW($B$14)))) | H23: =IF($D$1="","",IF(INDEX('January 2026 Renewals'!$A:$A,$D$1+ROW()-ROW($B$14))<>$C$1,"",INDEX('January 2026 Renewals'!$R:$R,$D$1+ROW()-ROW($B$14)))) | I23: =IF($D$1="","",IF(INDEX('January 2026 Renewals'!$A:$A,$D$1+ROW()-ROW($B$14))<>$C$1,"",INDEX('January 2026 Renewals'!$W:$W,$D$1+ROW()-ROW($B$14)))) | J23: =IF($D$1="","",IF(INDEX('January 2026 Renewals'!$A:$A,$D$1+ROW()-ROW($B$14))<>$C$1,"",INDEX('January 2026 Renewals'!$AC:$AC,$D$1+ROW()-ROW($B$14)))) | K23: =IF($D$1="","",IF(INDEX('January 2026 Renewals'!$A:$A,$D$1+ROW()-ROW($B$14))<>$C$1,"",INDEX('January 2026 Renewals'!$AM:$AM,$D$1+ROW()-ROW($B$14))))
B24: =IF($D$1="","",IF(INDEX('January 2026 Renewals'!$A:$A,$D$1+ROW()-ROW($B$14))<>$C$1,"",INDEX('January 2026 Renewals'!$H:$H,$D$1+ROW()-ROW($B$14)))) | C24: =IF($D$1="","",IF(INDEX('January 2026 Renewals'!$A:$A,$D$1+ROW()-ROW($B$14))<>$C$1,"",INDEX('January 2026 Renewals'!$C:$C,$D$1+ROW()-ROW($B$14)))) | D24: =IF($D$1="","",IF(INDEX('January 2026 Renewals'!$A:$A,$D$1+ROW()-ROW($B$14))<>$C$1,"",INDEX('January 2026 Renewals'!$E:$E,$D$1+ROW()-ROW($B$14)))) | E24: =IF($D$1="","",IF(INDEX('January 2026 Renewals'!$A:$A,$D$1+ROW()-ROW($B$14))<>$C$1,"",INDEX('January 2026 Renewals'!$G:$G,$D$1+ROW()-ROW($B$14)))) | F24: =IF($D$1="","",IF(INDEX('January 2026 Renewals'!$A:$A,$D$1+ROW()-ROW($B$14))<>$C$1,"",INDEX('January 2026 Renewals'!$I:$I,$D$1+ROW()-ROW($B$14)))) | G24: =IF($D$1="","",IF(INDEX('January 2026 Renewals'!$A:$A,$D$1+ROW()-ROW($B$14))<>$C$1,"",INDEX('January 2026 Renewals'!$Q:$Q,$D$1+ROW()-ROW($B$14)))) | H24: =IF($D$1="","",IF(INDEX('January 2026 Renewals'!$A:$A,$D$1+ROW()-ROW($B$14))<>$C$1,"",INDEX('January 2026 Renewals'!$R:$R,$D$1+ROW()-ROW($B$14)))) | I24: =IF($D$1="","",IF(INDEX('January 2026 Renewals'!$A:$A,$D$1+ROW()-ROW($B$14))<>$C$1,"",INDEX('January 2026 Renewals'!$W:$W,$D$1+ROW()-ROW($B$14)))) | J24: =IF($D$1="","",IF(INDEX('January 2026 Renewals'!$A:$A,$D$1+ROW()-ROW($B$14))<>$C$1,"",INDEX('January 2026 Renewals'!$AC:$AC,$D$1+ROW()-ROW($B$14)))) | K24: =IF($D$1="","",IF(INDEX('January 2026 Renewals'!$A:$A,$D$1+ROW()-ROW($B$14))<>$C$1,"",INDEX('January 2026 Renewals'!$AM:$AM,$D$1+ROW()-ROW($B$14))))
B25: Total | E25: =SUM(E14:E24) -> 7746
A26: Current Availibilities
A27: *can also include prospects that have turned down the site and why
B28: Tenant | C28: Building | D28: Suite | E28: SF | F28: Date Suite Taken Back | G28: Days on Market | H28: Market Effective Rent | I28: On Lock Box | J28: Lease Ready | K28: Comments | R28: CPI Comments
B29: Tenant Occupied | C29: =IF($F$1="","",INDEX('Working - CPI'!$B:$B,$F$1+ROW()-ROW($B$29))) -> 761 N Monterey | D29: =IF($F$1="","",INDEX('Working - CPI'!$C:$C,$F$1+ROW()-ROW($B$29))) -> 105 | E29: =IF($F$1="","",INDEX('Working - CPI'!$D:$D,$F$1+ROW()-ROW($B$29))) -> 1671 | F29: =IF($F$1="","",INDEX('Working - CPI'!$E:$E,$F$1+ROW()-ROW($B$29))) -> 45961 | G29: =IF($F$1="","",INDEX('Working - CPI'!$F:$F,$F$1+ROW()-ROW($B$29))) -> 48.527668 | H29: =IF($F$1="","",INDEX('Working - CPI'!$G:$G,$F$1+ROW()-ROW($B$29))) -> 1.4 | I29: =IF($F$1="","",INDEX('Working - CPI'!$H:$H,$F$1+ROW()-ROW($B$29))) -> Yes | J29: =IF($F$1="","",INDEX('Working - CPI'!$I:$I,$F$1+ROW()-ROW($B$29))) -> No | K29: =IF($F$1="","",INDEX('Working - CPI'!$J:$J,$F$1+ROW()-ROW($B$29))) -> Vacant, in good shape. Will get flooring and paint, pending bids from GC - Has broken rafter in roof, pending structural engineer | R29: Broken Roof Beam
B30: =IF($F$1="","",IF(INDEX('Working - CPI'!$D:$D,$F$1+ROW()-ROW($B$29))>0,"Vacant","")) -> Vacant | C30: =IF($F$1="","",INDEX('Working - CPI'!$B:$B,$F$1+ROW()-ROW($B$29))) -> 761 N Monterey | D30: =IF($F$1="","",INDEX('Working - CPI'!$C:$C,$F$1+ROW()-ROW($B$29))) -> 101 | E30: =IF($F$1="","",INDEX('Working - CPI'!$D:$D,$F$1+ROW()-ROW($B$29))) -> 1985 | F30: =IF($F$1="","",INDEX('Working - CPI'!$E:$E,$F$1+ROW()-ROW($B$29))) -> 45991 | G30: =IF($F$1="","",INDEX('Working - CPI'!$F:$F,$F$1+ROW()-ROW($B$29))) -> 18.527668 | H30: =IF($F$1="","",INDEX('Working - CPI'!$G:$G,$F$1+ROW()-ROW($B$29))) -> 1.4 | I30: =IF($F$1="","",INDEX('Working - CPI'!$H:$H,$F$1+ROW()-ROW($B$29))) -> No | J30: =IF($F$1="","",INDEX('Working - CPI'!$I:$I,$F$1+ROW()-ROW($B$29))) -> No | K30: =IF($F$1="","",INDEX('Working - CPI'!$J:$J,$F$1+ROW()-ROW($B$29))) -> Pending trash out- scheduled for 12/22, removing WH structures, will get paint and flooring, upgraded lighting to LED, move in could be for 2/1/26
B47: Deal Pending | C47: =SUMIF(B29:B42,B47,E29:E42) -> 0 | E47: =SUM(E29:E46) -> 3656 | G47: Vacant | H47: =SUMIF(B29:B42,G47,E29:E42) -> 1985
A48: Executed Leases | W48: NER Calculations
G49: RENT | I49: TERM | K49: TI | M49: Free Rent | O49: Bumps | P49: LCs | Q49: NER | R49: NER Check | W49: Subtotals | AB49: Budget / Actual | AE49: Term
B50: Tenant | C50: Building | D50: Suite | E50: SF | F50: Type | G50: New | H50: Budget | I50: New | J50: Budget | K50: New | L50: Budget | M50: New | N50: Budget | O50: Actual | P50: Actual | Q50: Actual | R50: =S6 -> 0 | S50: Execution | T50: Comments | W50: Revenue | X50: Bumps | Y50: TIs | Z50: LCs | AA50: FR | AB50: Rent | AC50: FR | AD50: TI | AE50: Years | AF50: Month | AG50: Total | AH50: Term Check | AM50: =AM5 -> Raleigh Light Industrial - Rent Bump Calculation | BD50: =BD5 -> Raleigh Light Industrial - Rent Bump Calculation (Monthly Rents)
B51: =IF($G$1="","",INDEX('Lease Report 2025'!$H:$H,$G$1+ROW()-ROW($B$51))) -> Scale X Pro LLC | C51: =IF($G$1="","",INDEX('Lease Report 2025'!$D:$D,$G$1+ROW()-ROW($B$51))) -> 751 N Monterey | D51: =IF($G$1="","",INDEX('Lease Report 2025'!$E:$E,$G$1+ROW()-ROW($B$51))) -> 113 | E51: =IF($G$1="","",INDEX('Lease Report 2025'!$G:$G,$G$1+ROW()-ROW($B$51))) -> 1191 | F51: =IF($G$1="","",INDEX('Lease Report 2025'!$A:$A,$G$1+ROW()-ROW($B$51))) -> RX | G51: =IF($G$1="","",INDEX('Lease Report 2025'!$L:$L,$G$1+ROW()-ROW($B$51))) -> 2.72 | I51: =IF($G$1="","",INDEX('Lease Report 2025'!$P:$P,$G$1+ROW()-ROW($B$51))) -> 3 | O51: =IF($G$1="","",INDEX('Lease Report 2025'!$N:$N,$G$1+ROW()-ROW($B$51))) -> 0.07 | S51: =IF($G$1="","",INDEX('Lease Report 2025'!$R:$R,$G$1+ROW()-ROW($B$51))) -> 45689 | T51: =IF($G$1="","",INDEX('Lease Report 2025'!$O:$O,$G$1+ROW()-ROW($B$51))) -> Minor TI, No Free rent, No outside agent, Base Year Gross | W51: =AB51*E51*(AG51/12) -> 9718.56 | X51: =SUMIFS($AM51:$BB51,$AM$6:$BB$6,"<="&AG51)+(INDEX($BD51:$BS51,MATCH(AG51+12,$AM$6:$BB$6))*(AG51-INDEX($AM$6:$BB$6,MATCH(AG51,$AM$6:$BB$6))))-W51 -> 696.17285 | Y51: =AD51*E51 -> 0 | Z51: =SUM(W51:X51)*P51 -> 0 | AA51: =AB51/12*E51*AC51 -> 0 | AB51: =IF(H51="",G51,H51) -> 2.72 | AC51: =IF(N51="",M51,N51) -> 0 | AD51: =IF(L51="",K51,L51) -> 0 | AE51: =IFERROR(LEFT(J51, FIND("-", J51) - 1),I51) -> 3 | AF51: =IFERROR(RIGHT(J51,LEN(J51)-SEARCH("-",J51)),0) -> 0 | AG51: =_xlfn.NUMBERVALUE(AE51)*12+_xlfn.NUMBERVALUE(AF51) -> 36 | AH51: =IF(E51<$AH$3,36,60) -> 36 | AM51: =AB51*$E51 -> 3239.52 | AN51: =AM51*(1+$O51) -> 3466.2864 | AO51: =AN51*(1+$O51) -> 3708.9264 | AP51: =AO51*(1+$O51) -> 3968.5513 | AQ51: =AP51*(1+$O51) -> 4246.3499 | AR51: =AQ51*(1+$O51) -> 4543.5944 | AS51: =AR51*(1+$O51) -> 4861.646 | AT51: =AS51*(1+$O51) -> 5201.9612 | AU51: =AT51*(1+$O51) -> 5566.0985 | ... BB51: =BA51*(1+$O51) -> 8937.9379 | BD51: =AM51/12 -> 269.96 | BE51: =AN51/12 -> 288.8572 | BF51: =AO51/12 -> 309.0772 | BG51: =AP51/12 -> 330.71261 | BH51: =AQ51/12 -> 353.86249 | BI51: =AR51/12 -> 378.63287 | BJ51: =AS51/12 -> 405.13717 | BK51: =AT51/12 -> 433.49677 | ... BS51: =BB51/12 -> 744.82815
B52: =IF($G$1="","",INDEX('Lease Report 2025'!$H:$H,$G$1+ROW()-ROW($B$51))) -> Luxe Cabinetry | C52: =IF($G$1="","",INDEX('Lease Report 2025'!$D:$D,$G$1+ROW()-ROW($B$51))) -> 425 W Guadalupe | D52: =IF($G$1="","",INDEX('Lease Report 2025'!$E:$E,$G$1+ROW()-ROW($B$51))) -> 114 | E52: =IF($G$1="","",INDEX('Lease Report 2025'!$G:$G,$G$1+ROW()-ROW($B$51))) -> 2502 | F52: =IF($G$1="","",INDEX('Lease Report 2025'!$A:$A,$G$1+ROW()-ROW($B$51))) -> New | G52: =IF($G$1="","",INDEX('Lease Report 2025'!$L:$L,$G$1+ROW()-ROW($B$51))) -> 1.25 | I52: =IF($G$1="","",INDEX('Lease Report 2025'!$P:$P,$G$1+ROW()-ROW($B$51))) -> 3 | O52: =IF($G$1="","",INDEX('Lease Report 2025'!$N:$N,$G$1+ROW()-ROW($B$51))) -> 0.06 | S52: =IF($G$1="","",INDEX('Lease Report 2025'!$R:$R,$G$1+ROW()-ROW($B$51))) -> 45748 | T52: =IF($G$1="","",INDEX('Lease Report 2025'!$O:$O,$G$1+ROW()-ROW($B$51))) -> 3 | W52: =AB52*E52*(AG52/12) -> 9382.5 | X52: =SUMIFS($AM52:$BB52,$AM$6:$BB$6,"<="&AG52)+(INDEX($BD52:$BS52,MATCH(AG52+12,$AM$6:$BB$6))*(AG52-INDEX($AM$6:$BB$6,MATCH(AG52,$AM$6:$BB$6))))-W52 -> 574.209 | Y52: =AD52*E52 -> 0 | Z52: =SUM(W52:X52)*P52 -> 0 | AA52: =AB52/12*E52*AC52 -> 0 | AB52: =IF(H52="",G52,H52) -> 1.25 | AC52: =IF(N52="",M52,N52) -> 0 | AD52: =IF(L52="",K52,L52) -> 0 | AE52: =IFERROR(LEFT(J52, FIND("-", J52) - 1),I52) -> 3 | AF52: =IFERROR(RIGHT(J52,LEN(J52)-SEARCH("-",J52)),0) -> 0 | AG52: =_xlfn.NUMBERVALUE(AE52)*12+_xlfn.NUMBERVALUE(AF52) -> 36 | AH52: =IF(E52<$AH$3,36,60) -> 36 | AM52: =AB52*$E52 -> 3127.5 | AN52: =AM52*(1+$O52) -> 3315.15 | AO52: =AN52*(1+$O52) -> 3514.059 | AP52: =AO52*(1+$O52) -> 3724.9025 | AQ52: =AP52*(1+$O52) -> 3948.3967 | AR52: =AQ52*(1+$O52) -> 4185.3005 | AS52: =AR52*(1+$O52) -> 4436.4185 | AT52: =AS52*(1+$O52) -> 4702.6036 | AU52: =AT52*(1+$O52) -> 4984.7599 | ... BB52: =BA52*(1+$O52) -> 7495.2357 | BD52: =AM52/12 -> 260.625 | BE52: =AN52/12 -> 276.2625 | BF52: =AO52/12 -> 292.83825 | BG52: =AP52/12 -> 310.40855 | BH52: =AQ52/12 -> 329.03306 | BI52: =AR52/12 -> 348.77504 | BJ52: =AS52/12 -> 369.70154 | BK52: =AT52/12 -> 391.88364 | ... BS52: =BB52/12 -> 624.60298
B53: =IF($G$1="","",INDEX('Lease Report 2025'!$H:$H,$G$1+ROW()-ROW($B$51))) -> JRL Goods LLC | C53: =IF($G$1="","",INDEX('Lease Report 2025'!$D:$D,$G$1+ROW()-ROW($B$51))) -> 425 W Guadalupe | D53: =IF($G$1="","",INDEX('Lease Report 2025'!$E:$E,$G$1+ROW()-ROW($B$51))) -> 115, 116 | E53: =IF($G$1="","",INDEX('Lease Report 2025'!$G:$G,$G$1+ROW()-ROW($B$51))) -> 3494 | F53: =IF($G$1="","",INDEX('Lease Report 2025'!$A:$A,$G$1+ROW()-ROW($B$51))) -> R | G53: =IF($G$1="","",INDEX('Lease Report 2025'!$L:$L,$G$1+ROW()-ROW($B$51))) -> 1.36 | I53: =IF($G$1="","",INDEX('Lease Report 2025'!$P:$P,$G$1+ROW()-ROW($B$51))) -> 3 | O53: =IF($G$1="","",INDEX('Lease Report 2025'!$N:$N,$G$1+ROW()-ROW($B$51))) -> 0.07 | S53: =IF($G$1="","",INDEX('Lease Report 2025'!$R:$R,$G$1+ROW()-ROW($B$51))) -> 45778 | T53: =IF($G$1="","",INDEX('Lease Report 2025'!$O:$O,$G$1+ROW()-ROW($B$51))) -> No TI, No Free rent, No outside agent, Base Year Gross
B54: =IF($G$1="","",INDEX('Lease Report 2025'!$H:$H,$G$1+ROW()-ROW($B$51))) -> Eagle One Appliance Repair | C54: =IF($G$1="","",INDEX('Lease Report 2025'!$D:$D,$G$1+ROW()-ROW($B$51))) -> 751 N Monterey | D54: =IF($G$1="","",INDEX('Lease Report 2025'!$E:$E,$G$1+ROW()-ROW($B$51))) -> 114 | E54: =IF($G$1="","",INDEX('Lease Report 2025'!$G:$G,$G$1+ROW()-ROW($B$51))) -> 1191 | F54: =IF($G$1="","",INDEX('Lease Report 2025'!$A:$A,$G$1+ROW()-ROW($B$51))) -> R | G54: =IF($G$1="","",INDEX('Lease Report 2025'!$L:$L,$G$1+ROW()-ROW($B$51))) -> 1.41 | I54: =IF($G$1="","",INDEX('Lease Report 2025'!$P:$P,$G$1+ROW()-ROW($B$51))) -> 3 | O54: =IF($G$1="","",INDEX('Lease Report 2025'!$N:$N,$G$1+ROW()-ROW($B$51))) -> 0.07 | S54: =IF($G$1="","",INDEX('Lease Report 2025'!$R:$R,$G$1+ROW()-ROW($B$51))) -> 45839 | T54: =IF($G$1="","",INDEX('Lease Report 2025'!$O:$O,$G$1+ROW()-ROW($B$51))) -> No TI, No Free rent, No outside agent, Base Year Gross
B55: =IF($G$1="","",INDEX('Lease Report 2025'!$H:$H,$G$1+ROW()-ROW($B$51))) -> Joshua Daniel Brown d/b/a Superstition Merch | C55: =IF($G$1="","",INDEX('Lease Report 2025'!$D:$D,$G$1+ROW()-ROW($B$51))) -> 761 N Monterey | D55: =IF($G$1="","",INDEX('Lease Report 2025'!$E:$E,$G$1+ROW()-ROW($B$51))) -> 103 | E55: =IF($G$1="","",INDEX('Lease Report 2025'!$G:$G,$G$1+ROW()-ROW($B$51))) -> 1671 | F55: =IF($G$1="","",INDEX('Lease Report 2025'!$A:$A,$G$1+ROW()-ROW($B$51))) -> New | G55: =IF($G$1="","",INDEX('Lease Report 2025'!$L:$L,$G$1+ROW()-ROW($B$51))) -> 1.25 | I55: =IF($G$1="","",INDEX('Lease Report 2025'!$P:$P,$G$1+ROW()-ROW($B$51))) -> 2 | O55: =IF($G$1="","",INDEX('Lease Report 2025'!$N:$N,$G$1+ROW()-ROW($B$51))) -> 0.05 | S55: =IF($G$1="","",INDEX('Lease Report 2025'!$R:$R,$G$1+ROW()-ROW($B$51))) -> 45901 | T55: =IF($G$1="","",INDEX('Lease Report 2025'!$O:$O,$G$1+ROW()-ROW($B$51))) -> 0
B56: =IF($G$1="","",INDEX('Lease Report 2025'!$H:$H,$G$1+ROW()-ROW($B$51))) -> Lamp Service Products Arizona | C56: =IF($G$1="","",INDEX('Lease Report 2025'!$D:$D,$G$1+ROW()-ROW($B$51))) -> 761 N Monterey St | D56: =IF($G$1="","",INDEX('Lease Report 2025'!$E:$E,$G$1+ROW()-ROW($B$51))) -> 107 | E56: =IF($G$1="","",INDEX('Lease Report 2025'!$G:$G,$G$1+ROW()-ROW($B$51))) -> 1676 | F56: =IF($G$1="","",INDEX('Lease Report 2025'!$A:$A,$G$1+ROW()-ROW($B$51))) -> R | G56: =IF($G$1="","",INDEX('Lease Report 2025'!$L:$L,$G$1+ROW()-ROW($B$51))) -> 1.3 | I56: =IF($G$1="","",INDEX('Lease Report 2025'!$P:$P,$G$1+ROW()-ROW($B$51))) -> 5 | O56: =IF($G$1="","",INDEX('Lease Report 2025'!$N:$N,$G$1+ROW()-ROW($B$51))) -> 0.06 | S56: =IF($G$1="","",INDEX('Lease Report 2025'!$R:$R,$G$1+ROW()-ROW($B$51))) -> 45901 | T56: =IF($G$1="","",INDEX('Lease Report 2025'!$O:$O,$G$1+ROW()-ROW($B$51))) -> HVAC Replacement, No Free rent, No outside agent, Base Year Gross
B57: =IF($G$1="","",INDEX('Lease Report 2025'!$H:$H,$G$1+ROW()-ROW($B$51))) -> Batti-Performance, LLC | C57: =IF($G$1="","",INDEX('Lease Report 2025'!$D:$D,$G$1+ROW()-ROW($B$51))) -> 425 W. Guadalupe Road, Suite 115 | D57: =IF($G$1="","",INDEX('Lease Report 2025'!$E:$E,$G$1+ROW()-ROW($B$51))) -> 115 | E57: =IF($G$1="","",INDEX('Lease Report 2025'!$G:$G,$G$1+ROW()-ROW($B$51))) -> 1784 | F57: =IF($G$1="","",INDEX('Lease Report 2025'!$A:$A,$G$1+ROW()-ROW($B$51))) -> New | G57: =IF($G$1="","",INDEX('Lease Report 2025'!$L:$L,$G$1+ROW()-ROW($B$51))) -> 1.3 | I57: =IF($G$1="","",INDEX('Lease Report 2025'!$P:$P,$G$1+ROW()-ROW($B$51))) -> 3 | O57: =IF($G$1="","",INDEX('Lease Report 2025'!$N:$N,$G$1+ROW()-ROW($B$51))) -> 0.05 | S57: =IF($G$1="","",INDEX('Lease Report 2025'!$R:$R,$G$1+ROW()-ROW($B$51))) -> 45962 | T57: =IF($G$1="","",INDEX('Lease Report 2025'!$O:$O,$G$1+ROW()-ROW($B$51))) -> 1 Month free
B58: =IF($G$1="","",INDEX('Lease Report 2025'!$H:$H,$G$1+ROW()-ROW($B$51))) -> Madbrows LLC | C58: =IF($G$1="","",INDEX('Lease Report 2025'!$D:$D,$G$1+ROW()-ROW($B$51))) -> 425 W Guadalupe Rd Suite 116 | D58: =IF($G$1="","",INDEX('Lease Report 2025'!$E:$E,$G$1+ROW()-ROW($B$51))) -> 116 | E58: =IF($G$1="","",INDEX('Lease Report 2025'!$G:$G,$G$1+ROW()-ROW($B$51))) -> 1710 | F58: =IF($G$1="","",INDEX('Lease Report 2025'!$A:$A,$G$1+ROW()-ROW($B$51))) -> New | G58: =IF($G$1="","",INDEX('Lease Report 2025'!$L:$L,$G$1+ROW()-ROW($B$51))) -> 1.25 | I58: =IF($G$1="","",INDEX('Lease Report 2025'!$P:$P,$G$1+ROW()-ROW($B$51))) -> 5 | O58: =IF($G$1="","",INDEX('Lease Report 2025'!$N:$N,$G$1+ROW()-ROW($B$51))) -> 0.05 | S58: =IF($G$1="","",INDEX('Lease Report 2025'!$R:$R,$G$1+ROW()-ROW($B$51))) -> 45992 | T58: =IF($G$1="","",INDEX('Lease Report 2025'!$O:$O,$G$1+ROW()-ROW($B$51))) -> 2
B59: =IF($G$1="","",INDEX('Lease Report 2025'!$H:$H,$G$1+ROW()-ROW($B$51))) -> Miller Chiropractic Center Inc | C59: =IF($G$1="","",INDEX('Lease Report 2025'!$D:$D,$G$1+ROW()-ROW($B$51))) -> 425 W Guadalupe | D59: =IF($G$1="","",INDEX('Lease Report 2025'!$E:$E,$G$1+ROW()-ROW($B$51))) -> 113 | E59: =IF($G$1="","",INDEX('Lease Report 2025'!$G:$G,$G$1+ROW()-ROW($B$51))) -> 1421 | F59: =IF($G$1="","",INDEX('Lease Report 2025'!$A:$A,$G$1+ROW()-ROW($B$51))) -> OFS | G59: =IF($G$1="","",INDEX('Lease Report 2025'!$L:$L,$G$1+ROW()-ROW($B$51))) -> 1.66 | I59: =IF($G$1="","",INDEX('Lease Report 2025'!$P:$P,$G$1+ROW()-ROW($B$51))) -> 1 | O59: =IF($G$1="","",INDEX('Lease Report 2025'!$N:$N,$G$1+ROW()-ROW($B$51))) -> 0 | S59: =IF($G$1="","",INDEX('Lease Report 2025'!$R:$R,$G$1+ROW()-ROW($B$51))) -> 46023 | T59: =IF($G$1="","",INDEX('Lease Report 2025'!$O:$O,$G$1+ROW()-ROW($B$51))) -> No TI, No Free rent, No outside agent, Base Year Gross
B60: =IF($G$1="","",INDEX('Lease Report 2025'!$H:$H,$G$1+ROW()-ROW($B$51))) -> DRT Fabrication LLC | C60: =IF($G$1="","",INDEX('Lease Report 2025'!$D:$D,$G$1+ROW()-ROW($B$51))) -> 761 N Monterey | D60: =IF($G$1="","",INDEX('Lease Report 2025'!$E:$E,$G$1+ROW()-ROW($B$51))) -> 104 | E60: =IF($G$1="","",INDEX('Lease Report 2025'!$G:$G,$G$1+ROW()-ROW($B$51))) -> 1671 | F60: =IF($G$1="","",INDEX('Lease Report 2025'!$A:$A,$G$1+ROW()-ROW($B$51))) -> New | G60: =IF($G$1="","",INDEX('Lease Report 2025'!$L:$L,$G$1+ROW()-ROW($B$51))) -> 1.35 | I60: =IF($G$1="","",INDEX('Lease Report 2025'!$P:$P,$G$1+ROW()-ROW($B$51))) -> 3 | O60: =IF($G$1="","",INDEX('Lease Report 2025'!$N:$N,$G$1+ROW()-ROW($B$51))) -> 0.05 | S60: =IF($G$1="","",INDEX('Lease Report 2025'!$R:$R,$G$1+ROW()-ROW($B$51))) -> 0 | T60: =IF($G$1="","",INDEX('Lease Report 2025'!$O:$O,$G$1+ROW()-ROW($B$51))) -> 1 Month free
A61: Dead Deals
A62: *can also include prospects that have turned down the site and why
A63: Broker | B63: Tenant | C63: Building | D63: Suite | E63: SF | F63: Expiration

Sheet 120_RR
D2: GOLDEN KEY PLAZA
C3: As Of : 11/21/2025
E5: SQFT | H5: Annual | I5: Monthly | N5: Rent | AC5: Lease
A6: Suite | B6: Tenant Name | E6: Rentable | G6: Leased | H6: Rent | I6: Rent | K6: P.S.F | L6: Suite(s) | N6: Begin | T6: End | W6: Base Rent | X6: P.S.F | AC6: Begin | AD6: End | AE6: SitePlan_Label | AF6: Exp_Bucket
A7: 425-101 | B7: BIG MARLIN GROUP, LLC | E7: 1710 | G7: 1710 | H7: 99993.6 | I7: 8332.8 | K7: 14.4 | L7: 425-101, 425-102, 425-103, 425-104 | N7: 45931 | T7: 46295 | W7: 8332.8 | X7: 14.4 | AC7: 45566 | AD7: 09/30/2029 | AE7: =B7&CHAR(10)&TEXT(SUMIF($B$7:$B$137,B7,$E$7:$E$137),"#,##0")&" SF"&IF(B7="Vacant","",CHAR(10)&IF(AD7="", "", TEXT(IF(ISNUMBER(AD7),AD7,DATEVALUE(AD7)),"m/d/yy"))) -> BIG MARLIN GROUP, LLC 6,944 SF 9/30/29 | AF7: =IF(B7="Vacant","Vacant",IF(AD7="","",IF(IF(ISNUMBER(AD7),AD7,DATEVALUE(AD7))<TODAY(),"Expired",IF(IF(ISNUMBER(AD7),AD7,DATEVALUE(AD7))<=EDATE(TODAY(),12),"0-12 mo",IF(IF(ISNUMBER(AD7),AD7,DATEVALUE(AD7))<=EDATE(TODAY(),24),"12-24 mo",">24 mo"))))) -> >24 mo
N8: 46296 | T8: 46660 | W8: 8680 | X8: 15
N9: 46661 | T9: 47026 | W9: 9027.2 | X9: 15.6
N10: 47027 | T10: 47391 | W10: 9374.4 | X10: 16.2
A12: 425-102 | B12: BIG MARLIN GROUP, LLC | E12: 1710 | G12: 1710 | K12: 0 | L12: 425-101, 425-102, 425-103, 425-104 | X12: 0 | AC12: 45566 | AD12: 09/30/2029 | AE12: =B12&CHAR(10)&TEXT(SUMIF($B$7:$B$137,B12,$E$7:$E$137),"#,##0")&" SF"&IF(B12="Vacant","",CHAR(10)&IF(AD12="", "", TEXT(IF(ISNUMBER(AD12),AD12,DATEVALUE(AD12)),"m/d/yy"))) -> BIG MARLIN GROUP, LLC 6,944 SF 9/30/29 | AF12: =IF(B12="Vacant","Vacant",IF(AD12="","",IF(IF(ISNUMBER(AD12),AD12,DATEVALUE(AD12))<TODAY(),"Expired",IF(IF(ISNUMBER(AD12),AD12,DATEVALUE(AD12))<=EDATE(TODAY(),12),"0-12 mo",IF(IF(ISNUMBER(AD12),AD12,DATEVALUE(AD12))<=EDATE(TODAY(),24),"12-24 mo",">24 mo"))))) -> >24 mo
A14: 425-103 | B14: BIG MARLIN GROUP, LLC | E14: 1736 | G14: 1736 | K14: 0 | L14: 425-101, 425-102, 425-103, 425-104 | X14: 0 | AC14: 45566 | AD14: 09/30/2029 | AE14: =B14&CHAR(10)&TEXT(SUMIF($B$7:$B$137,B14,$E$7:$E$137),"#,##0")&" SF"&IF(B14="Vacant","",CHAR(10)&IF(AD14="", "", TEXT(IF(ISNUMBER(AD14),AD14,DATEVALUE(AD14)),"m/d/yy"))) -> BIG MARLIN GROUP, LLC 6,944 SF 9/30/29 | AF14: =IF(B14="Vacant","Vacant",IF(AD14="","",IF(IF(ISNUMBER(AD14),AD14,DATEVALUE(AD14))<TODAY(),"Expired",IF(IF(ISNUMBER(AD14),AD14,DATEVALUE(AD14))<=EDATE(TODAY(),12),"0-12 mo",IF(IF(ISNUMBER(AD14),AD14,DATEVALUE(AD14))<=EDATE(TODAY(),24),"12-24 mo",">24 mo"))))) -> >24 mo
A16: 425-104 | B16: BIG MARLIN GROUP, LLC | E16: 1788 | G16: 1788 | K16: 0 | L16: 425-101, 425-102, 425-103, 425-104 | X16: 0 | AC16: 45566 | AD16: 09/30/2029 | AE16: =B16&CHAR(10)&TEXT(SUMIF($B$7:$B$137,B16,$E$7:$E$137),"#,##0")&" SF"&IF(B16="Vacant","",CHAR(10)&IF(AD16="", "", TEXT(IF(ISNUMBER(AD16),AD16,DATEVALUE(AD16)),"m/d/yy"))) -> BIG MARLIN GROUP, LLC 6,944 SF 9/30/29 | AF16: =IF(B16="Vacant","Vacant",IF(AD16="","",IF(IF(ISNUMBER(AD16),AD16,DATEVALUE(AD16))<TODAY(),"Expired",IF(IF(ISNUMBER(AD16),AD16,DATEVALUE(AD16))<=EDATE(TODAY(),12),"0-12 mo",IF(IF(ISNUMBER(AD16),AD16,DATEVALUE(AD16))<=EDATE(TODAY(),24),"12-24 mo",">24 mo"))))) -> >24 mo
A18: 425-105 | B18: INNOVATIVE CUTTING SYSTEMS | E18: 2502 | G18: 2502 | H18: 63596.52 | I18: 5299.71 | K18: 15.24 | L18: 425-105, 761-102 | N18: 45839 | T18: 46203 | W18: 5299.71 | X18: 15.24 | AC18: 45108 | AD18: 06/30/2026 | AE18: =B18&CHAR(10)&TEXT(SUMIF($B$7:$B$137,B18,$E$7:$E$137),"#,##0")&" SF"&IF(B18="Vacant","",CHAR(10)&IF(AD18="", "", TEXT(IF(ISNUMBER(AD18),AD18,DATEVALUE(AD18)),"m/d/yy"))) -> INNOVATIVE CUTTING SYSTEMS 4,173 SF 6/30/26 | AF18: =IF(B18="Vacant","Vacant",IF(AD18="","",IF(IF(ISNUMBER(AD18),AD18,DATEVALUE(AD18))<TODAY(),"Expired",IF(IF(ISNUMBER(AD18),AD18,DATEVALUE(AD18))<=EDATE(TODAY(),12),"0-12 mo",IF(IF(ISNUMBER(AD18),AD18,DATEVALUE(AD18))<=EDATE(TODAY(),24),"12-24 mo",">24 mo"))))) -> 0-12 mo
A20: 425-106 | B20: SCRUBS N SCOPES MANAGEMENT | E20: 1421 | G20: 1421 | H20: 113650.32 | I20: 9470.86 | K20: 14.64 | L20: 425-106, 425-107, 425-108, 425-109, 425-110 | N20: 45962 | T20: 46326 | W20: 9470.86 | X20: 14.64 | AC20: 44866 | AD20: 10/31/2027 | AE20: =B20&CHAR(10)&TEXT(SUMIF($B$7:$B$137,B20,$E$7:$E$137),"#,##0")&" SF"&IF(B20="Vacant","",CHAR(10)&IF(AD20="", "", TEXT(IF(ISNUMBER(AD20),AD20,DATEVALUE(AD20)),"m/d/yy"))) -> SCRUBS N SCOPES MANAGEMENT 7,763 SF 10/31/27 | AF20: =IF(B20="Vacant","Vacant",IF(AD20="","",IF(IF(ISNUMBER(AD20),AD20,DATEVALUE(AD20))<TODAY(),"Expired",IF(IF(ISNUMBER(AD20),AD20,DATEVALUE(AD20))<=EDATE(TODAY(),12),"0-12 mo",IF(IF(ISNUMBER(AD20),AD20,DATEVALUE(AD20))<=EDATE(TODAY(),24),"12-24 mo",">24 mo"))))) -> 12-24 mo
N21: 46327 | T21: 46691 | W21: 9859.01 | X21: 15.24
A23: 425-107 | B23: SCRUBS N SCOPES MANAGEMENT | E23: 1421 | G23: 1421 | K23: 0 | L23: 425-106, 425-107, 425-108, 425-109, 425-110 | X23: 0 | AC23: 44866 | AD23: 10/31/2027 | AE23: =B23&CHAR(10)&TEXT(SUMIF($B$7:$B$137,B23,$E$7:$E$137),"#,##0")&" SF"&IF(B23="Vacant","",CHAR(10)&IF(AD23="", "", TEXT(IF(ISNUMBER(AD23),AD23,DATEVALUE(AD23)),"m/d/yy"))) -> SCRUBS N SCOPES MANAGEMENT 7,763 SF 10/31/27 | AF23: =IF(B23="Vacant","Vacant",IF(AD23="","",IF(IF(ISNUMBER(AD23),AD23,DATEVALUE(AD23))<TODAY(),"Expired",IF(IF(ISNUMBER(AD23),AD23,DATEVALUE(AD23))<=EDATE(TODAY(),12),"0-12 mo",IF(IF(ISNUMBER(AD23),AD23,DATEVALUE(AD23))<=EDATE(TODAY(),24),"12-24 mo",">24 mo"))))) -> 12-24 mo
A25: 425-108 | B25: SCRUBS N SCOPES MANAGEMENT | E25: 1421 | G25: 1421 | K25: 0 | L25: 425-106, 425-107, 425-108, 425-109, 425-110 | X25: 0 | AC25: 44866 | AD25: 10/31/2027 | AE25: =B25&CHAR(10)&TEXT(SUMIF($B$7:$B$137,B25,$E$7:$E$137),"#,##0")&" SF"&IF(B25="Vacant","",CHAR(10)&IF(AD25="", "", TEXT(IF(ISNUMBER(AD25),AD25,DATEVALUE(AD25)),"m/d/yy"))) -> SCRUBS N SCOPES MANAGEMENT 7,763 SF 10/31/27 | AF25: =IF(B25="Vacant","Vacant",IF(AD25="","",IF(IF(ISNUMBER(AD25),AD25,DATEVALUE(AD25))<TODAY(),"Expired",IF(IF(ISNUMBER(AD25),AD25,DATEVALUE(AD25))<=EDATE(TODAY(),12),"0-12 mo",IF(IF(ISNUMBER(AD25),AD25,DATEVALUE(AD25))<=EDATE(TODAY(),24),"12-24 mo",">24 mo"))))) -> 12-24 mo
A27: 425-109 | B27: SCRUBS N SCOPES MANAGEMENT | E27: 1750 | G27: 1750 | K27: 0 | L27: 425-106, 425-107, 425-108, 425-109, 425-110 | X27: 0 | AC27: 44866 | AD27: 10/31/2027 | AE27: =B27&CHAR(10)&TEXT(SUMIF($B$7:$B$137,B27,$E$7:$E$137),"#,##0")&" SF"&IF(B27="Vacant","",CHAR(10)&IF(AD27="", "", TEXT(IF(ISNUMBER(AD27),AD27,DATEVALUE(AD27)),"m/d/yy"))) -> SCRUBS N SCOPES MANAGEMENT 7,763 SF 10/31/27 | AF27: =IF(B27="Vacant","Vacant",IF(AD27="","",IF(IF(ISNUMBER(AD27),AD27,DATEVALUE(AD27))<TODAY(),"Expired",IF(IF(ISNUMBER(AD27),AD27,DATEVALUE(AD27))<=EDATE(TODAY(),12),"0-12 mo",IF(IF(ISNUMBER(AD27),AD27,DATEVALUE(AD27))<=EDATE(TODAY(),24),"12-24 mo",">24 mo"))))) -> 12-24 mo
A29: 425-110 | B29: SCRUBS N SCOPES MANAGEMENT | E29: 1750 | G29: 1750 | K29: 0 | L29: 425-106, 425-107, 425-108, 425-109, 425-110 | X29: 0 | AC29: 44866 | AD29: 10/31/2027 | AE29: =B29&CHAR(10)&TEXT(SUMIF($B$7:$B$137,B29,$E$7:$E$137),"#,##0")&" SF"&IF(B29="Vacant","",CHAR(10)&IF(AD29="", "", TEXT(IF(ISNUMBER(AD29),AD29,DATEVALUE(AD29)),"m/d/yy"))) -> SCRUBS N SCOPES MANAGEMENT 7,763 SF 10/31/27 | AF29: =IF(B29="Vacant","Vacant",IF(AD29="","",IF(IF(ISNUMBER(AD29),AD29,DATEVALUE(AD29))<TODAY(),"Expired",IF(IF(ISNUMBER(AD29),AD29,DATEVALUE(AD29))<=EDATE(TODAY(),12),"0-12 mo",IF(IF(ISNUMBER(AD29),AD29,DATEVALUE(AD29))<=EDATE(TODAY(),24),"12-24 mo",">24 mo"))))) -> 12-24 mo
A31: 425-111 | B31: ZAMBEZI MEDICAL, LLC | E31: 1421 | G31: 1421 | H31: 46381.44 | I31: 3865.12 | K31: 16.32 | L31: 425-111, 425-112 | N31: 45689 | T31: 46053 | W31: 3865.12 | X31: 16.32 | AC31: 44958 | AD31: 01/31/2028 | AE31: =B31&CHAR(10)&TEXT(SUMIF($B$7:$B$137,B31,$E$7:$E$137),"#,##0")&" SF"&IF(B31="Vacant","",CHAR(10)&IF(AD31="", "", TEXT(IF(ISNUMBER(AD31),AD31,DATEVALUE(AD31)),"m/d/yy"))) -> ZAMBEZI MEDICAL, LLC 2,842 SF 1/31/28 | AF31: =IF(B31="Vacant","Vacant",IF(AD31="","",IF(IF(ISNUMBER(AD31),AD31,DATEVALUE(AD31))<TODAY(),"Expired",IF(IF(ISNUMBER(AD31),AD31,DATEVALUE(AD31))<=EDATE(TODAY(),12),"0-12 mo",IF(IF(ISNUMBER(AD31),AD31,DATEVALUE(AD31))<=EDATE(TODAY(),24),"12-24 mo",">24 mo"))))) -> >24 mo
N32: 46054 | T32: 46418 | W32: 4035.64 | X32: 17.04
N33: 46419 | T33: 46783 | W33: 4206.16 | X33: 17.76
A35: 425-112 | B35: ZAMBEZI MEDICAL, LLC | E35: 1421 | G35: 1421 | K35: 0 | L35: 425-111, 425-112 | X35: 0 | AC35: 44958 | AD35: 01/31/2028 | AE35: =B35&CHAR(10)&TEXT(SUMIF($B$7:$B$137,B35,$E$7:$E$137),"#,##0")&" SF"&IF(B35="Vacant","",CHAR(10)&IF(AD35="", "", TEXT(IF(ISNUMBER(AD35),AD35,DATEVALUE(AD35)),"m/d/yy"))) -> ZAMBEZI MEDICAL, LLC 2,842 SF 1/31/28 | AF35: =IF(B35="Vacant","Vacant",IF(AD35="","",IF(IF(ISNUMBER(AD35),AD35,DATEVALUE(AD35))<TODAY(),"Expired",IF(IF(ISNUMBER(AD35),AD35,DATEVALUE(AD35))<=EDATE(TODAY(),12),"0-12 mo",IF(IF(ISNUMBER(AD35),AD35,DATEVALUE(AD35))<=EDATE(TODAY(),24),"12-24 mo",">24 mo"))))) -> >24 mo
A37: 425-113 | B37: MILLER CHIROPRACTIC CENTER INC | E37: 1421 | G37: 1421 | H37: 28306.32 | I37: 2358.86 | K37: 19.92 | N37: 45658 | T37: 46022 | W37: 2358.86 | X37: 19.92 | AC37: 45658 | AD37: 12/31/2025 | AE37: =B37&CHAR(10)&TEXT(SUMIF($B$7:$B$137,B37,$E$7:$E$137),"#,##0")&" SF"&IF(B37="Vacant","",CHAR(10)&IF(AD37="", "", TEXT(IF(ISNUMBER(AD37),AD37,DATEVALUE(AD37)),"m/d/yy"))) -> MILLER CHIROPRACTIC CENTER INC 1,421 SF 12/31/25 | AF37: =IF(B37="Vacant","Vacant",IF(AD37="","",IF(IF(ISNUMBER(AD37),AD37,DATEVALUE(AD37))<TODAY(),"Expired",IF(IF(ISNUMBER(AD37),AD37,DATEVALUE(AD37))<=EDATE(TODAY(),12),"0-12 mo",IF(IF(ISNUMBER(AD37),AD37,DATEVALUE(AD37))<=EDATE(TODAY(),24),"12-24 mo",">24 mo"))))) -> 0-12 mo
A39: 425-114 | B39: LUXE CABINETRY & DESIGN LLC | E39: 2502 | G39: 2502 | H39: 37530 | I39: 3127.5 | K39: 15 | N39: 45748 | T39: 46203 | W39: 3127.5 | X39: 15 | AC39: 45748 | AD39: 06/30/2028 | AE39: =B39&CHAR(10)&TEXT(SUMIF($B$7:$B$137,B39,$E$7:$E$137),"#,##0")&" SF"&IF(B39="Vacant","",CHAR(10)&IF(AD39="", "", TEXT(IF(ISNUMBER(AD39),AD39,DATEVALUE(AD39)),"m/d/yy"))) -> LUXE CABINETRY & DESIGN LLC 2,502 SF 6/30/28 | AF39: =IF(B39="Vacant","Vacant",IF(AD39="","",IF(IF(ISNUMBER(AD39),AD39,DATEVALUE(AD39))<TODAY(),"Expired",IF(IF(ISNUMBER(AD39),AD39,DATEVALUE(AD39))<=EDATE(TODAY(),12),"0-12 mo",IF(IF(ISNUMBER(AD39),AD39,DATEVALUE(AD39))<=EDATE(TODAY(),24),"12-24 mo",">24 mo"))))) -> >24 mo
N40: 46204 | T40: 46568 | W40: 3277.62 | X40: 15.72
N41: 46569 | T41: 46934 | W41: 3427.74 | X41: 16.44
A43: 425-115 | B43: BATTI-PERFORMANCE, LLC | E43: 1784 | G43: 1784 | H43: 27830.4 | I43: 2319.2 | K43: 15.6 | N43: 45962 | T43: 46356 | W43: 2319.2 | X43: 15.6 | AC43: 45962 | AD43: 11/30/2028 | AE43: =B43&CHAR(10)&TEXT(SUMIF($B$7:$B$137,B43,$E$7:$E$137),"#,##0")&" SF"&IF(B43="Vacant","",CHAR(10)&IF(AD43="", "", TEXT(IF(ISNUMBER(AD43),AD43,DATEVALUE(AD43)),"m/d/yy"))) -> BATTI-PERFORMANCE, LLC 1,784 SF 11/30/28 | AF43: =IF(B43="Vacant","Vacant",IF(AD43="","",IF(IF(ISNUMBER(AD43),AD43,DATEVALUE(AD43))<TODAY(),"Expired",IF(IF(ISNUMBER(AD43),AD43,DATEVALUE(AD43))<=EDATE(TODAY(),12),"0-12 mo",IF(IF(ISNUMBER(AD43),AD43,DATEVALUE(AD43))<=EDATE(TODAY(),24),"12-24 mo",">24 mo"))))) -> >24 mo
N44: 46357 | T44: 46721 | W44: 2408.4 | X44: 16.2
N45: 46722 | T45: 47087 | W45: 2497.6 | X45: 16.8
A47: 425-116 | B47: Vacant | E47: 1710 | G47: 0 | K47: 0 | X47: 0 | AE47: =B47&CHAR(10)&TEXT(SUMIF($B$7:$B$137,B47,$E$7:$E$137),"#,##0")&" SF"&IF(B47="Vacant","",CHAR(10)&IF(AD47="", "", TEXT(IF(ISNUMBER(AD47),AD47,DATEVALUE(AD47)),"m/d/yy"))) -> Vacant 3,381 SF | AF47: =IF(B47="Vacant","Vacant",IF(AD47="","",IF(IF(ISNUMBER(AD47),AD47,DATEVALUE(AD47))<TODAY(),"Expired",IF(IF(ISNUMBER(AD47),AD47,DATEVALUE(AD47))<=EDATE(TODAY(),12),"0-12 mo",IF(IF(ISNUMBER(AD47),AD47,DATEVALUE(AD47))<=EDATE(TODAY(),24),"12-24 mo",">24 mo"))))) -> Vacant
A49: 425-117 | B49: ATW ENTERPRISES, LLC | E49: 1710 | G49: 1710 | H49: 24829.2 | I49: 2069.1 | K49: 14.52 | N49: 45901 | T49: 46265 | W49: 2069.1 | X49: 14.52 | AC49: 44805 | AD49: 08/31/2027 | AE49: =B49&CHAR(10)&TEXT(SUMIF($B$7:$B$137,B49,$E$7:$E$137),"#,##0")&" SF"&IF(B49="Vacant","",CHAR(10)&IF(AD49="", "", TEXT(IF(ISNUMBER(AD49),AD49,DATEVALUE(AD49)),"m/d/yy"))) -> ATW ENTERPRISES, LLC 1,710 SF 8/31/27 | AF49: =IF(B49="Vacant","Vacant",IF(AD49="","",IF(IF(ISNUMBER(AD49),AD49,DATEVALUE(AD49))<TODAY(),"Expired",IF(IF(ISNUMBER(AD49),AD49,DATEVALUE(AD49))<=EDATE(TODAY(),12),"0-12 mo",IF(IF(ISNUMBER(AD49),AD49,DATEVALUE(AD49))<=EDATE(TODAY(),24),"12-24 mo",">24 mo"))))) -> 12-24 mo
N50: 46266 | T50: 46630 | W50: 2154.6 | X50: 15.12
A52: 425-118 | B52: THE GAMING ZONE LLC | E52: 1710 | G52: 1710 | H52: 23803.2 | I52: 1983.6 | K52: 13.92 | N52: 45962 | T52: 46326 | W52: 1983.6 | X52: 13.92 | AC52: 44866 | AD52: 10/31/2027 | AE52: =B52&CHAR(10)&TEXT(SUMIF($B$7:$B$137,B52,$E$7:$E$137),"#,##0")&" SF"&IF(B52="Vacant","",CHAR(10)&IF(AD52="", "", TEXT(IF(ISNUMBER(AD52),AD52,DATEVALUE(AD52)),"m/d/yy"))) -> THE GAMING ZONE LLC 1,710 SF 10/31/27 | AF52: =IF(B52="Vacant","Vacant",IF(AD52="","",IF(IF(ISNUMBER(AD52),AD52,DATEVALUE(AD52))<TODAY(),"Expired",IF(IF(ISNUMBER(AD52),AD52,DATEVALUE(AD52))<=EDATE(TODAY(),12),"0-12 mo",IF(IF(ISNUMBER(AD52),AD52,DATEVALUE(AD52))<=EDATE(TODAY(),24),"12-24 mo",">24 mo"))))) -> 12-24 mo
N53: 46327 | T53: 46691 | W53: 2069.1 | X53: 14.52
A55: 751-111 | B55: FLY PROMOTIONS LLC | E55: 1191 | G55: 1191 | H55: 21009.24 | I55: 1750.77 | K55: 17.64 | N55: 45689 | T55: 46053 | W55: 1750.77 | X55: 17.64 | AC55: 45323 | AD55: 01/31/2026 | AE55: =B55&CHAR(10)&TEXT(SUMIF($B$7:$B$137,B55,$E$7:$E$137),"#,##0")&" SF"&IF(B55="Vacant","",CHAR(10)&IF(AD55="", "", TEXT(IF(ISNUMBER(AD55),AD55,DATEVALUE(AD55)),"m/d/yy"))) -> FLY PROMOTIONS LLC 1,191 SF 1/31/26 | AF55: =IF(B55="Vacant","Vacant",IF(AD55="","",IF(IF(ISNUMBER(AD55),AD55,DATEVALUE(AD55))<TODAY(),"Expired",IF(IF(ISNUMBER(AD55),AD55,DATEVALUE(AD55))<=EDATE(TODAY(),12),"0-12 mo",IF(IF(ISNUMBER(AD55),AD55,DATEVALUE(AD55))<=EDATE(TODAY(),24),"12-24 mo",">24 mo"))))) -> 0-12 mo
A57: 751-112 | B57: MARK SNYDER ELECTRIC | E57: 1191 | G57: 1191 | H57: 20437.56 | I57: 1703.13 | K57: 17.16 | N57: 45717 | T57: 46081 | W57: 1703.13 | X57: 17.16 | AC57: 45352 | AD57: 02/28/2027 | AE57: =B57&CHAR(10)&TEXT(SUMIF($B$7:$B$137,B57,$E$7:$E$137),"#,##0")&" SF"&IF(B57="Vacant","",CHAR(10)&IF(AD57="", "", TEXT(IF(ISNUMBER(AD57),AD57,DATEVALUE(AD57)),"m/d/yy"))) -> MARK SNYDER ELECTRIC 1,191 SF 2/28/27 | AF57: =IF(B57="Vacant","Vacant",IF(AD57="","",IF(IF(ISNUMBER(AD57),AD57,DATEVALUE(AD57))<TODAY(),"Expired",IF(IF(ISNUMBER(AD57),AD57,DATEVALUE(AD57))<=EDATE(TODAY(),12),"0-12 mo",IF(IF(ISNUMBER(AD57),AD57,DATEVALUE(AD57))<=EDATE(TODAY(),24),"12-24 mo",">24 mo"))))) -> 12-24 mo
N58: 46082 | T58: 46446 | W58: 1786.5 | X58: 18
A60: 751-113 | B60: SCALE X PRO LLC | E60: 1191 | G60: 1191 | H60: 38874.24 | I60: 3239.52 | K60: 16.32 | L60: 751-113, 751-122 | N60: 45717 | T60: 46053 | W60: 3239.52 | X60: 16.32 | AC60: 45689 | AD60: 01/31/2028 | AE60: =B60&CHAR(10)&TEXT(SUMIF($B$7:$B$137,B60,$E$7:$E$137),"#,##0")&" SF"&IF(B60="Vacant","",CHAR(10)&IF(AD60="", "", TEXT(IF(ISNUMBER(AD60),AD60,DATEVALUE(AD60)),"m/d/yy"))) -> SCALE X PRO LLC 2,382 SF 1/31/28 | AF60: =IF(B60="Vacant","Vacant",IF(AD60="","",IF(IF(ISNUMBER(AD60),AD60,DATEVALUE(AD60))<TODAY(),"Expired",IF(IF(ISNUMBER(AD60),AD60,DATEVALUE(AD60))<=EDATE(TODAY(),12),"0-12 mo",IF(IF(ISNUMBER(AD60),AD60,DATEVALUE(AD60))<=EDATE(TODAY(),24),"12-24 mo",">24 mo"))))) -> >24 mo
N61: 46054 | T61: 46418 | W61: 3406.26 | X61: 17.16
N62: 46419 | T62: 46783 | W62: 3573 | X62: 18
A64: 751-114 | B64: EAGLE ONE APPLIANCE REPAIR | E64: 1191 | G64: 1191 | H64: 20151.6 | I64: 1679.3 | K64: 16.919899 | N64: 45839 | T64: 46203 | W64: 1679.3 | X64: 16.919899 | AC64: 45839 | AD64: 06/30/2028 | AE64: =B64&CHAR(10)&TEXT(SUMIF($B$7:$B$137,B64,$E$7:$E$137),"#,##0")&" SF"&IF(B64="Vacant","",CHAR(10)&IF(AD64="", "", TEXT(IF(ISNUMBER(AD64),AD64,DATEVALUE(AD64)),"m/d/yy"))) -> EAGLE ONE APPLIANCE REPAIR 1,191 SF 6/30/28 | AF64: =IF(B64="Vacant","Vacant",IF(AD64="","",IF(IF(ISNUMBER(AD64),AD64,DATEVALUE(AD64))<TODAY(),"Expired",IF(IF(ISNUMBER(AD64),AD64,DATEVALUE(AD64))<=EDATE(TODAY(),12),"0-12 mo",IF(IF(ISNUMBER(AD64),AD64,DATEVALUE(AD64))<=EDATE(TODAY(),24),"12-24 mo",">24 mo"))))) -> >24 mo
N65: 46204 | T65: 46568 | W65: 1762.68 | X65: 17.76
N66: 46569 | T66: 46934 | W66: 1846.05 | X66: 18.6
A68: 751-115 | B68: LIFETIME PRECISION | E68: 1191 | G68: 1191 | H68: 19294.2 | I68: 1607.85 | K68: 16.2 | N68: 45627 | T68: 45991 | W68: 1607.85 | X68: 16.2 | AC68: 45627 | AD68: 11/30/2027 | AE68: =B68&CHAR(10)&TEXT(SUMIF($B$7:$B$137,B68,$E$7:$E$137),"#,##0")&" SF"&IF(B68="Vacant","",CHAR(10)&IF(AD68="", "", TEXT(IF(ISNUMBER(AD68),AD68,DATEVALUE(AD68)),"m/d/yy"))) -> LIFETIME PRECISION 1,191 SF 11/30/27 | AF68: =IF(B68="Vacant","Vacant",IF(AD68="","",IF(IF(ISNUMBER(AD68),AD68,DATEVALUE(AD68))<TODAY(),"Expired",IF(IF(ISNUMBER(AD68),AD68,DATEVALUE(AD68))<=EDATE(TODAY(),12),"0-12 mo",IF(IF(ISNUMBER(AD68),AD68,DATEVALUE(AD68))<=EDATE(TODAY(),24),"12-24 mo",">24 mo"))))) -> 12-24 mo
N69: 45992 | T69: 46356 | W69: 1691.22 | X69: 17.04
N70: 46357 | T70: 46721 | W70: 1774.59 | X70: 17.88
A72: 751-116 | B72: ARIZONA INTERLOCKS, LLC | E72: 1191 | G72: 1191 | H72: 19437.12 | I72: 1619.76 | K72: 16.32 | N72: 45627 | T72: 45991 | W72: 1619.76 | X72: 16.32 | AC72: 45627 | AD72: 11/30/2027 | AE72: =B72&CHAR(10)&TEXT(SUMIF($B$7:$B$137,B72,$E$7:$E$137),"#,##0")&" SF"&IF(B72="Vacant","",CHAR(10)&IF(AD72="", "", TEXT(IF(ISNUMBER(AD72),AD72,DATEVALUE(AD72)),"m/d/yy"))) -> ARIZONA INTERLOCKS, LLC 1,191 SF 11/30/27 | AF72: =IF(B72="Vacant","Vacant",IF(AD72="","",IF(IF(ISNUMBER(AD72),AD72,DATEVALUE(AD72))<TODAY(),"Expired",IF(IF(ISNUMBER(AD72),AD72,DATEVALUE(AD72))<=EDATE(TODAY(),12),"0-12 mo",IF(IF(ISNUMBER(AD72),AD72,DATEVALUE(AD72))<=EDATE(TODAY(),24),"12-24 mo",">24 mo"))))) -> 12-24 mo
N73: 45992 | T73: 46356 | W73: 1703.13 | X73: 17.16
N74: 46357 | T74: 46721 | W74: 1786.5 | X74: 18
A76: 751-117 | B76: SAMUEL COFFEY AND BRIANNE COFFEY | E76: 1191 | G76: 1191 | H76: 21009.24 | I76: 1750.77 | K76: 17.64 | N76: 45717 | T76: 46081 | W76: 1750.77 | X76: 17.64 | AC76: 45323 | AD76: 02/28/2026 | AE76: =B76&CHAR(10)&TEXT(SUMIF($B$7:$B$137,B76,$E$7:$E$137),"#,##0")&" SF"&IF(B76="Vacant","",CHAR(10)&IF(AD76="", "", TEXT(IF(ISNUMBER(AD76),AD76,DATEVALUE(AD76)),"m/d/yy"))) -> SAMUEL COFFEY AND BRIANNE COFFEY 1,191 SF 2/28/26 | AF76: =IF(B76="Vacant","Vacant",IF(AD76="","",IF(IF(ISNUMBER(AD76),AD76,DATEVALUE(AD76))<TODAY(),"Expired",IF(IF(ISNUMBER(AD76),AD76,DATEVALUE(AD76))<=EDATE(TODAY(),12),"0-12 mo",IF(IF(ISNUMBER(AD76),AD76,DATEVALUE(AD76))<=EDATE(TODAY(),24),"12-24 mo",">24 mo"))))) -> 0-12 mo
A78: 751-118 | B78: IMPERIAL ELECTRIC COMPANY LLC | E78: 1191 | G78: 1191 | H78: 19580.04 | I78: 1631.67 | K78: 16.44 | N78: 45627 | T78: 45991 | W78: 1631.67 | X78: 16.44 | AC78: 45627 | AD78: 11/30/2026 | AE78: =B78&CHAR(10)&TEXT(SUMIF($B$7:$B$137,B78,$E$7:$E$137),"#,##0")&" SF"&IF(B78="Vacant","",CHAR(10)&IF(AD78="", "", TEXT(IF(ISNUMBER(AD78),AD78,DATEVALUE(AD78)),"m/d/yy"))) -> IMPERIAL ELECTRIC COMPANY LLC 1,191 SF 11/30/26 | AF78: =IF(B78="Vacant","Vacant",IF(AD78="","",IF(IF(ISNUMBER(AD78),AD78,DATEVALUE(AD78))<TODAY(),"Expired",IF(IF(ISNUMBER(AD78),AD78,DATEVALUE(AD78))<=EDATE(TODAY(),12),"0-12 mo",IF(IF(ISNUMBER(AD78),AD78,DATEVALUE(AD78))<=EDATE(TODAY(),24),"12-24 mo",">24 mo"))))) -> 0-12 mo
N79: 45992 | T79: 46356 | W79: 1703.13 | X79: 17.16
A81: 751-119 | B81: ARIZONA ARMS SALES LLC | E81: 1191 | G81: 1191 | H81: 39160.08 | I81: 3263.34 | K81: 16.44 | L81: 751-119, 751-120 | N81: 45658 | T81: 46022 | W81: 3263.34 | X81: 16.44 | AC81: 45261 | AD81: 12/31/2026 | AE81: =B81&CHAR(10)&TEXT(SUMIF($B$7:$B$137,B81,$E$7:$E$137),"#,##0")&" SF"&IF(B81="Vacant","",CHAR(10)&IF(AD81="", "", TEXT(IF(ISNUMBER(AD81),AD81,DATEVALUE(AD81)),"m/d/yy"))) -> ARIZONA ARMS SALES LLC 2,382 SF 12/31/26 | AF81: =IF(B81="Vacant","Vacant",IF(AD81="","",IF(IF(ISNUMBER(AD81),AD81,DATEVALUE(AD81))<TODAY(),"Expired",IF(IF(ISNUMBER(AD81),AD81,DATEVALUE(AD81))<=EDATE(TODAY(),12),"0-12 mo",IF(IF(ISNUMBER(AD81),AD81,DATEVALUE(AD81))<=EDATE(TODAY(),24),"12-24 mo",">24 mo"))))) -> 12-24 mo
N82: 46023 | T82: 46387 | W82: 3382.44 | X82: 17.04
A84: 751-120 | B84: ARIZONA ARMS SALES LLC | E84: 1191 | G84: 1191 | K84: 0 | L84: 751-119, 751-120 | X84: 0 | AC84: 45261 | AD84: 12/31/2026 | AE84: =B84&CHAR(10)&TEXT(SUMIF($B$7:$B$137,B84,$E$7:$E$137),"#,##0")&" SF"&IF(B84="Vacant","",CHAR(10)&IF(AD84="", "", TEXT(IF(ISNUMBER(AD84),AD84,DATEVALUE(AD84)),"m/d/yy"))) -> ARIZONA ARMS SALES LLC 2,382 SF 12/31/26 | AF84: =IF(B84="Vacant","Vacant",IF(AD84="","",IF(IF(ISNUMBER(AD84),AD84,DATEVALUE(AD84))<TODAY(),"Expired",IF(IF(ISNUMBER(AD84),AD84,DATEVALUE(AD84))<=EDATE(TODAY(),12),"0-12 mo",IF(IF(ISNUMBER(AD84),AD84,DATEVALUE(AD84))<=EDATE(TODAY(),24),"12-24 mo",">24 mo"))))) -> 12-24 mo
A86: 751-121 | B86: ESSEN FLOORS LLC | E86: 1191 | G86: 1191 | H86: 20008.8 | I86: 1667.4 | K86: 16.8 | N86: 45689 | T86: 46053 | W86: 1667.4 | X86: 16.8 | AC86: 45323 | AD86: 01/31/2026 | AE86: =B86&CHAR(10)&TEXT(SUMIF($B$7:$B$137,B86,$E$7:$E$137),"#,##0")&" SF"&IF(B86="Vacant","",CHAR(10)&IF(AD86="", "", TEXT(IF(ISNUMBER(AD86),AD86,DATEVALUE(AD86)),"m/d/yy"))) -> ESSEN FLOORS LLC 1,191 SF 1/31/26 | AF86: =IF(B86="Vacant","Vacant",IF(AD86="","",IF(IF(ISNUMBER(AD86),AD86,DATEVALUE(AD86))<TODAY(),"Expired",IF(IF(ISNUMBER(AD86),AD86,DATEVALUE(AD86))<=EDATE(TODAY(),12),"0-12 mo",IF(IF(ISNUMBER(AD86),AD86,DATEVALUE(AD86))<=EDATE(TODAY(),24),"12-24 mo",">24 mo"))))) -> 0-12 mo
A88: 751-122 | B88: SCALE X PRO LLC | E88: 1191 | G88: 1191 | K88: 0 | L88: 751-113, 751-122 | X88: 0 | AC88: 45689 | AD88: 01/31/2028 | AE88: =B88&CHAR(10)&TEXT(SUMIF($B$7:$B$137,B88,$E$7:$E$137),"#,##0")&" SF"&IF(B88="Vacant","",CHAR(10)&IF(AD88="", "", TEXT(IF(ISNUMBER(AD88),AD88,DATEVALUE(AD88)),"m/d/yy"))) -> SCALE X PRO LLC 2,382 SF 1/31/28 | AF88: =IF(B88="Vacant","Vacant",IF(AD88="","",IF(IF(ISNUMBER(AD88),AD88,DATEVALUE(AD88))<TODAY(),"Expired",IF(IF(ISNUMBER(AD88),AD88,DATEVALUE(AD88))<=EDATE(TODAY(),12),"0-12 mo",IF(IF(ISNUMBER(AD88),AD88,DATEVALUE(AD88))<=EDATE(TODAY(),24),"12-24 mo",">24 mo"))))) -> >24 mo
A90: 751-123 | B90: KACHINA CONTRACTING CORP | E90: 1191 | G90: 1191 | H90: 20008.8 | I90: 1667.4 | K90: 16.8 | N90: 45748 | T90: 46112 | W90: 1667.4 | X90: 16.8 | AC90: 45689 | AD90: 03/31/2027 | AE90: =B90&CHAR(10)&TEXT(SUMIF($B$7:$B$137,B90,$E$7:$E$137),"#,##0")&" SF"&IF(B90="Vacant","",CHAR(10)&IF(AD90="", "", TEXT(IF(ISNUMBER(AD90),AD90,DATEVALUE(AD90)),"m/d/yy"))) -> KACHINA CONTRACTING CORP 1,191 SF 3/31/27 | AF90: =IF(B90="Vacant","Vacant",IF(AD90="","",IF(IF(ISNUMBER(AD90),AD90,DATEVALUE(AD90))<TODAY(),"Expired",IF(IF(ISNUMBER(AD90),AD90,DATEVALUE(AD90))<=EDATE(TODAY(),12),"0-12 mo",IF(IF(ISNUMBER(AD90),AD90,DATEVALUE(AD90))<=EDATE(TODAY(),24),"12-24 mo",">24 mo"))))) -> 12-24 mo
N91: 46113 | T91: 46477 | W91: 1726.95 | X91: 17.4
A93: 761-101 | B93: RED EYE CONSTRUCTION LLC | E93: 1985 | G93: 1985 | H93: 32394 | I93: 2699.5 | K93: 16.319395 | N93: 45627 | T93: 45991 | W93: 2699.5 | X93: 16.319395 | AC93: 45261 | AD93: 11/30/2026 | AE93: =B93&CHAR(10)&TEXT(SUMIF($B$7:$B$137,B93,$E$7:$E$137),"#,##0")&" SF"&IF(B93="Vacant","",CHAR(10)&IF(AD93="", "", TEXT(IF(ISNUMBER(AD93),AD93,DATEVALUE(AD93)),"m/d/yy"))) -> RED EYE CONSTRUCTION LLC 1,985 SF 11/30/26 | AF93: =IF(B93="Vacant","Vacant",IF(AD93="","",IF(IF(ISNUMBER(AD93),AD93,DATEVALUE(AD93))<TODAY(),"Expired",IF(IF(ISNUMBER(AD93),AD93,DATEVALUE(AD93))<=EDATE(TODAY(),12),"0-12 mo",IF(IF(ISNUMBER(AD93),AD93,DATEVALUE(AD93))<=EDATE(TODAY(),24),"12-24 mo",">24 mo"))))) -> 0-12 mo
N94: 45992 | T94: 46356 | W94: 2818.7 | X94: 17.04
A96: 761-102 | B96: INNOVATIVE CUTTING SYSTEMS | E96: 1671 | G96: 1671 | K96: 0 | L96: 425-105, 761-102 | X96: 0 | AC96: 45108 | AD96: 06/30/2026 | AE96: =B96&CHAR(10)&TEXT(SUMIF($B$7:$B$137,B96,$E$7:$E$137),"#,##0")&" SF"&IF(B96="Vacant","",CHAR(10)&IF(AD96="", "", TEXT(IF(ISNUMBER(AD96),AD96,DATEVALUE(AD96)),"m/d/yy"))) -> INNOVATIVE CUTTING SYSTEMS 4,173 SF 6/30/26 | AF96: =IF(B96="Vacant","Vacant",IF(AD96="","",IF(IF(ISNUMBER(AD96),AD96,DATEVALUE(AD96))<TODAY(),"Expired",IF(IF(ISNUMBER(AD96),AD96,DATEVALUE(AD96))<=EDATE(TODAY(),12),"0-12 mo",IF(IF(ISNUMBER(AD96),AD96,DATEVALUE(AD96))<=EDATE(TODAY(),24),"12-24 mo",">24 mo"))))) -> 0-12 mo
A98: 761-103 | B98: JOSHUA DANIEL BROWN | E98: 1671 | G98: 1671 | H98: 25065 | I98: 2088.75 | K98: 15 | N98: 45901 | T98: 46265 | W98: 2088.75 | X98: 15 | AC98: 45901 | AD98: 08/31/2027 | AE98: =B98&CHAR(10)&TEXT(SUMIF($B$7:$B$137,B98,$E$7:$E$137),"#,##0")&" SF"&IF(B98="Vacant","",CHAR(10)&IF(AD98="", "", TEXT(IF(ISNUMBER(AD98),AD98,DATEVALUE(AD98)),"m/d/yy"))) -> JOSHUA DANIEL BROWN 1,671 SF 8/31/27 | AF98: =IF(B98="Vacant","Vacant",IF(AD98="","",IF(IF(ISNUMBER(AD98),AD98,DATEVALUE(AD98))<TODAY(),"Expired",IF(IF(ISNUMBER(AD98),AD98,DATEVALUE(AD98))<=EDATE(TODAY(),12),"0-12 mo",IF(IF(ISNUMBER(AD98),AD98,DATEVALUE(AD98))<=EDATE(TODAY(),24),"12-24 mo",">24 mo"))))) -> 12-24 mo
N99: 46266 | T99: 46630 | W99: 2172.3 | X99: 15.6
A101: 761-104 | B101: DRT FABRICATION LLC | E101: 1671 | G101: 1671 | H101: 27070.2 | I101: 2255.85 | K101: 16.2 | N101: 45901 | T101: 46295 | W101: 2255.85 | X101: 16.2 | AC101: 45901 | AD101: 09/30/2028 | AE101: =B101&CHAR(10)&TEXT(SUMIF($B$7:$B$137,B101,$E$7:$E$137),"#,##0")&" SF"&IF(B101="Vacant","",CHAR(10)&IF(AD101="", "", TEXT(IF(ISNUMBER(AD101),AD101,DATEVALUE(AD101)),"m/d/yy"))) -> DRT FABRICATION LLC 1,671 SF 9/30/28 | AF101: =IF(B101="Vacant","Vacant",IF(AD101="","",IF(IF(ISNUMBER(AD101),AD101,DATEVALUE(AD101))<TODAY(),"Expired",IF(IF(ISNUMBER(AD101),AD101,DATEVALUE(AD101))<=EDATE(TODAY(),12),"0-12 mo",IF(IF(ISNUMBER(AD101),AD101,DATEVALUE(AD101))<=EDATE(TODAY(),24),"12-24 mo",">24 mo"))))) -> >24 mo
N102: 46296 | T102: 46660 | W102: 2339.4 | X102: 16.8
N103: 46661 | T103: 47026 | W103: 2422.95 | X103: 17.4
A105: 761-105 | B105: Vacant | E105: 1671 | G105: 0 | K105: 0 | X105: 0 | AE105: =B105&CHAR(10)&TEXT(SUMIF($B$7:$B$137,B105,$E$7:$E$137),"#,##0")&" SF"&IF(B105="Vacant","",CHAR(10)&IF(AD105="", "", TEXT(IF(ISNUMBER(AD105),AD105,DATEVALUE(AD105)),"m/d/yy"))) -> Vacant 3,381 SF | AF105: =IF(B105="Vacant","Vacant",IF(AD105="","",IF(IF(ISNUMBER(AD105),AD105,DATEVALUE(AD105))<TODAY(),"Expired",IF(IF(ISNUMBER(AD105),AD105,DATEVALUE(AD105))<=EDATE(TODAY(),12),"0-12 mo",IF(IF(ISNUMBER(AD105),AD105,DATEVALUE(AD105))<=EDATE(TODAY(),24),"12-24 mo",">24 mo"))))) -> Vacant
A107: 761-106 | B107: VALLEY WIDE SOLUTIONS LLC | E107: 1671 | G107: 1671 | H107: 28674.36 | I107: 2389.53 | K107: 17.16 | N107: 45809 | T107: 46173 | W107: 2389.53 | X107: 17.16 | AC107: 45444 | AD107: 05/31/2027 | AE107: =B107&CHAR(10)&TEXT(SUMIF($B$7:$B$137,B107,$E$7:$E$137),"#,##0")&" SF"&IF(B107="Vacant","",CHAR(10)&IF(AD107="", "", TEXT(IF(ISNUMBER(AD107),AD107,DATEVALUE(AD107)),"m/d/yy"))) -> VALLEY WIDE SOLUTIONS LLC 1,671 SF 5/31/27 | AF107: =IF(B107="Vacant","Vacant",IF(AD107="","",IF(IF(ISNUMBER(AD107),AD107,DATEVALUE(AD107))<TODAY(),"Expired",IF(IF(ISNUMBER(AD107),AD107,DATEVALUE(AD107))<=EDATE(TODAY(),12),"0-12 mo",IF(IF(ISNUMBER(AD107),AD107,DATEVALUE(AD107))<=EDATE(TODAY(),24),"12-24 mo",">24 mo"))))) -> 12-24 mo
N108: 46174 | T108: 46538 | W108: 2506.5 | X108: 18
A110: 761-107 | B110: LAMP SERVICE PRODUCTS ARIZONA | E110: 1676 | G110: 1676 | H110: 26145.6 | I110: 2178.8 | K110: 15.6 | N110: 45901 | T110: 46265 | W110: 2178.8 | X110: 15.6 | AC110: 45901 | AD110: 08/31/2030 | AE110: =B110&CHAR(10)&TEXT(SUMIF($B$7:$B$137,B110,$E$7:$E$137),"#,##0")&" SF"&IF(B110="Vacant","",CHAR(10)&IF(AD110="", "", TEXT(IF(ISNUMBER(AD110),AD110,DATEVALUE(AD110)),"m/d/yy"))) -> LAMP SERVICE PRODUCTS ARIZONA 1,676 SF 8/31/30 | AF110: =IF(B110="Vacant","Vacant",IF(AD110="","",IF(IF(ISNUMBER(AD110),AD110,DATEVALUE(AD110))<TODAY(),"Expired",IF(IF(ISNUMBER(AD110),AD110,DATEVALUE(AD110))<=EDATE(TODAY(),12),"0-12 mo",IF(IF(ISNUMBER(AD110),AD110,DATEVALUE(AD110))<=EDATE(TODAY(),24),"12-24 mo",">24 mo"))))) -> >24 mo
N111: 46266 | T111: 46630 | W111: 2279.36 | X111: 16.32
N112: 46631 | T112: 46996 | W112: 2379.92 | X112: 17.04
N113: 46997 | T113: 47361 | W113: 2480.48 | X113: 17.76
N114: 47362 | T114: 47726 | W114: 2597.8 | X114: 18.6
A116: 761-108 | B116: ARCHER MOTORSPORTS, INC. | E116: 1671 | G116: 1671 | H116: 55744.56 | I116: 4645.38 | K116: 16.68 | L116: 761-108, 761-109 | N116: 45870 | T116: 46234 | W116: 4645.38 | X116: 16.68 | AC116: 45139 | AD116: 07/31/2026 | AE116: =B116&CHAR(10)&TEXT(SUMIF($B$7:$B$137,B116,$E$7:$E$137),"#,##0")&" SF"&IF(B116="Vacant","",CHAR(10)&IF(AD116="", "", TEXT(IF(ISNUMBER(AD116),AD116,DATEVALUE(AD116)),"m/d/yy"))) -> ARCHER MOTORSPORTS, INC. 3,342 SF 7/31/26 | AF116: =IF(B116="Vacant","Vacant",IF(AD116="","",IF(IF(ISNUMBER(AD116),AD116,DATEVALUE(AD116))<TODAY(),"Expired",IF(IF(ISNUMBER(AD116),AD116,DATEVALUE(AD116))<=EDATE(TODAY(),12),"0-12 mo",IF(IF(ISNUMBER(AD116),AD116,DATEVALUE(AD116))<=EDATE(TODAY(),24),"12-24 mo",">24 mo"))))) -> 0-12 mo
A118: 761-109 | B118: ARCHER MOTORSPORTS, INC. | E118: 1671 | G118: 1671 | K118: 0 | L118: 761-108, 761-109 | X118: 0 | AC118: 45139 | AD118: 07/31/2026 | AE118: =B118&CHAR(10)&TEXT(SUMIF($B$7:$B$137,B118,$E$7:$E$137),"#,##0")&" SF"&IF(B118="Vacant","",CHAR(10)&IF(AD118="", "", TEXT(IF(ISNUMBER(AD118),AD118,DATEVALUE(AD118)),"m/d/yy"))) -> ARCHER MOTORSPORTS, INC. 3,342 SF 7/31/26 | AF118: =IF(B118="Vacant","Vacant",IF(AD118="","",IF(IF(ISNUMBER(AD118),AD118,DATEVALUE(AD118))<TODAY(),"Expired",IF(IF(ISNUMBER(AD118),AD118,DATEVALUE(AD118))<=EDATE(TODAY(),12),"0-12 mo",IF(IF(ISNUMBER(AD118),AD118,DATEVALUE(AD118))<=EDATE(TODAY(),24),"12-24 mo",">24 mo"))))) -> 0-12 mo
A120: 761-110 | B120: SIMPLIFIED MFG, INC. | E120: 1985 | G120: 1985 | H120: 33586.2 | I120: 2798.85 | K120: 16.92 | N120: 45870 | T120: 46234 | W120: 2798.85 | X120: 16.92 | AC120: 45488 | AD120: 07/31/2027 | AE120: =B120&CHAR(10)&TEXT(SUMIF($B$7:$B$137,B120,$E$7:$E$137),"#,##0")&" SF"&IF(B120="Vacant","",CHAR(10)&IF(AD120="", "", TEXT(IF(ISNUMBER(AD120),AD120,DATEVALUE(AD120)),"m/d/yy"))) -> SIMPLIFIED MFG, INC. 1,985 SF 7/31/27 | AF120: =IF(B120="Vacant","Vacant",IF(AD120="","",IF(IF(ISNUMBER(AD120),AD120,DATEVALUE(AD120))<TODAY(),"Expired",IF(IF(ISNUMBER(AD120),AD120,DATEVALUE(AD120))<=EDATE(TODAY(),12),"0-12 mo",IF(IF(ISNUMBER(AD120),AD120,DATEVALUE(AD120))<=EDATE(TODAY(),24),"12-24 mo",">24 mo"))))) -> 12-24 mo
N121: 46235 | T121: 46599 | W121: 2917.95 | X121: 17.64
J125: Report Totals :
J127: Rentable SQFT: | M127: 63714 | S127: Monthly Rent: | V127: 79464.32
S129: Annual Rent: | V129: 953571.84
J130: Leased SQFT: | M130: 60333
J133: Total Occupied | M133: 60333 | R133: % Occupancy | U133: 94.693474
J134: Total Vacant | M134: 3381 | R134: % Vacant | U134: 5.306526
J136: Total SQFT | M136: 63714

Sheet 167_Broadway
A1: Broadway Industrial Park | C1: 167 | D1: 6 | F1: =IFERROR(MATCH($C$1,'Working - CPI'!$A:$A,0),"") -> 517 | G1: =IFERROR(MATCH($C$1,'Lease Report 2025'!$B:$B,0),"") -> 13 | T1: Leasing Pipeline Report
A2: Tempe, Arizona | C2: =IF(G2=0,"",(G2-E40)/G2) -> 0.71567 | D2: % Occupancy | F2: SF | G2: ='Occupancy Summary Schedule'!$D$37 -> 43963 | U2: =TODAY() -> 46009 | AH2: SF Threshold
A3: ='Occupancy Summary Schedule'!F53 -> 0.88710744 | B3: % CPI Portfolio Occupancy | AH3: 5000
A4: Active Lease Deals | W4: NER Calculations | AJ4: # | AK4: List
G5: RENT | J5: TERM | L5: TI | N5: Free Rent | P5: Bumps (%) | Q5: LCs | R5: NER | S5: NER Check | V5: NER Check | W5: Subtotals | AB5: Budget / Actual | AE5: Term | AJ5: 0 | AK5: Good | AM5: Raleigh Light Industrial - Rent Bump Calculation | BD5: Raleigh Light Industrial - Rent Bump Calculation (Monthly Rents)
A6: Broker | B6: Tenant | C6: Building | D6: Suite | E6: SF | F6: Type | G6: Current | H6: CPI Proj | I6: Proposed | J6: Budget | K6: Proposed | L6: Budget | M6: Proposed | N6: Budget | O6: Proposed | P6: Proposed | Q6: Proposed | R6: Proposed | T6: Expiration | U6: Comments | W6: Revenue | X6: Bumps | Y6: TIs | Z6: LCs | AA6: FR | AB6: Rent | AC6: FR | AD6: TI | AE6: Years | AF6: Month | AG6: Total | AH6: Term Check | AJ6: 1 | AK6: Check Term | AL6: Month: | AM6: 12 | AN6: =AM6+12 -> 24 | AO6: =AN6+12 -> 36 | AP6: =AO6+12 -> 48 | AQ6: =AP6+12 -> 60 | AR6: =AQ6+12 -> 72 | AS6: =AR6+12 -> 84 | AT6: =AS6+12 -> 96 | AU6: =AT6+12 -> 108 | ... BB6: =BA6+12 -> 192 | BD6: =AM6 -> 12 | BE6: =AN6 -> 24 | BF6: =AO6 -> 36 | BG6: =AP6 -> 48 | BH6: =AQ6 -> 60 | BI6: =AR6 -> 72 | BJ6: =AS6 -> 84 | BK6: =AT6 -> 96 | ... BS6: =BB6 -> 192
A7: DE | B7: MCLC United Unlimited | C7: 819 W 22nd | D7: 104 | E7: 7500 | F7: New | H7: 1.3 | I7: 1.3 | J7: 3 | K7: 3 | L7: 0 | M7: 0 | N7: 0 | O7: 1 | P7: 0.04 | Q7: 0.06 | R7: =IFERROR((SUM(W7:X7)-Y7-Z7-AA7)/(AG7/12)/E7,0) -> 1.2354206 | S7: =VLOOKUP(IF(R7<$V7,2,IF(AG7>=$AH7,0,1)),$AJ$5:$AK$7,2) -> Check Term | U7: No TI, 2 months half rent, Outside agent, Base Year Gross | W7: =AB7*E7*(AG7/12) -> 29250 | X7: =SUMIFS($AM7:$BB7,$AM$6:$BB$6,"<="&AG7)+(INDEX($BD7:$BS7,MATCH(AG7+12,$AM$6:$BB$6))*(AG7-INDEX($AM$6:$BB$6,MATCH(AG7,$AM$6:$BB$6))))-W7 -> 1185.6 | Y7: =AD7*E7 -> 0 | Z7: =SUM(W7:X7)*Q7 -> 1826.136 | AA7: =AB7/12*E7*AC7 -> 812.5 | AB7: =IF(I7="",H7,I7) -> 1.3 | AC7: =IF(O7="",N7,O7) -> 1 | AD7: =IF(M7="",L7,M7) -> 0 | AE7: =IFERROR(LEFT(K7, FIND("-", K7) - 1),J7) -> 3 | AF7: =IFERROR(RIGHT(K7,LEN(K7)-SEARCH("-",K7)),0) -> 0 | AG7: =_xlfn.NUMBERVALUE(AE7)*12+_xlfn.NUMBERVALUE(AF7) -> 36 | AH7: =IF(E7<$AH$3,36,60) -> 60 | AJ7: 2 | AK7: Check | AM7: =AB7*$E7 -> 9750 | AN7: =AM7*(1+$P7) -> 10140 | AO7: =AN7*(1+$P7) -> 10545.6 | AP7: =AO7*(1+$P7) -> 10967.424 | AQ7: =AP7*(1+$P7) -> 11406.121 | AR7: =AQ7*(1+$P7) -> 11862.366 | AS7: =AR7*(1+$P7) -> 12336.86 | AT7: =AS7*(1+$P7) -> 12830.335 | AU7: =AT7*(1+$P7) -> 13343.548 | ... BB7: =BA7*(1+$P7) -> 17559.199 | BD7: =AM7/12 -> 812.5 | BE7: =AN7/12 -> 845 | BF7: =AO7/12 -> 878.8 | BG7: =AP7/12 -> 913.952 | BH7: =AQ7/12 -> 950.51008 | BI7: =AR7/12 -> 988.53048 | BJ7: =AS7/12 -> 1028.0717 | BK7: =AT7/12 -> 1069.1946 | ... BS7: =BB7/12 -> 1463.2666
A8: DB | B8: Desert Coating Systems, LLC | C8: 819 W 22nd | D8: 109 | E8: 5000 | F8: Renewal/Expansion | G8: 1.09 | H8: 1.3 | I8: 1.25 | J8: 3 | K8: 3 | L8: 0 | M8: 0 | N8: 0 | O8: 0 | P8: 0.05 | Q8: 0.025 | R8: =IFERROR((SUM(W8:X8)-Y8-Z8-AA8)/(AG8/12)/E8,0) -> 1.2807031 | S8: =VLOOKUP(IF(R8<$V8,2,IF(AG8>=$AH8,0,1)),$AJ$5:$AK$7,2) -> Check Term | T8: 46053 | U8: No TI, No Free rent, No Outside agent, Base Year Gross | W8: =AB8*E8*(AG8/12) -> 18750 | X8: =SUMIFS($AM8:$BB8,$AM$6:$BB$6,"<="&AG8)+(INDEX($BD8:$BS8,MATCH(AG8+12,$AM$6:$BB$6))*(AG8-INDEX($AM$6:$BB$6,MATCH(AG8,$AM$6:$BB$6))))-W8 -> 953.125 | Y8: =AD8*E8 -> 0 | Z8: =SUM(W8:X8)*Q8 -> 492.57812 | AA8: =AB8/12*E8*AC8 -> 0 | AB8: =IF(I8="",H8,I8) -> 1.25 | AC8: =IF(O8="",N8,O8) -> 0 | AD8: =IF(M8="",L8,M8) -> 0 | AE8: =IFERROR(LEFT(K8, FIND("-", K8) - 1),J8) -> 3 | AF8: =IFERROR(RIGHT(K8,LEN(K8)-SEARCH("-",K8)),0) -> 0 | AG8: =_xlfn.NUMBERVALUE(AE8)*12+_xlfn.NUMBERVALUE(AF8) -> 36 | AH8: =IF(E8<$AH$3,36,60) -> 60 | AM8: =AB8*$E8 -> 6250 | AN8: =AM8*(1+$P8) -> 6562.5 | AO8: =AN8*(1+$P8) -> 6890.625 | AP8: =AO8*(1+$P8) -> 7235.1562 | AQ8: =AP8*(1+$P8) -> 7596.9141 | AR8: =AQ8*(1+$P8) -> 7976.7598 | AS8: =AR8*(1+$P8) -> 8375.5978 | AT8: =AS8*(1+$P8) -> 8794.3776 | AU8: =AT8*(1+$P8) -> 9234.0965 | ... BB8: =BA8*(1+$P8) -> 12993.301 | BD8: =AM8/12 -> 520.83333 | BE8: =AN8/12 -> 546.875 | BF8: =AO8/12 -> 574.21875 | BG8: =AP8/12 -> 602.92969 | BH8: =AQ8/12 -> 633.07617 | BI8: =AR8/12 -> 664.72998 | BJ8: =AS8/12 -> 697.96648 | BK8: =AT8/12 -> 732.8648 | ... BS8: =BB8/12 -> 1082.7751
A9: DE | B9: Innovative Facility Services | C9: 835 E 22nd | D9: 110 | E9: 2500 | F9: New | H9: 1.3 | I9: 1.3 | J9: 3 | K9: 5 | P9: 0.05 | Q9: 0.05 | U9: Offer on 109. Pushing to suite 110
A11: Tenants Expiring - Next 6 months
A13: Broker | B13: Tenant | C13: Building | D13: Suite | E13: SF | F13: Expires | G13: Current | H13: Budget | I13: Proposed 3 Year | J13: Proposed 5 Year | K13: Notes | W13: Revenue | X13: Bumps | Y13: TIs | Z13: LCs | AA13: FR | AB13: Rent | AC13: FR | AD13: TI | AE13: Years | AF13: Month | AG13: Total | AH13: Term Check | AJ13: 1 | AK13: Check Term | AL13: Month: | AM13: 12 | AN13: =AM13+12 -> 24 | AO13: =AN13+12 -> 36 | AP13: =AO13+12 -> 48 | AQ13: =AP13+12 -> 60 | AR13: =AQ13+12 -> 72 | AS13: =AR13+12 -> 84 | AT13: =AS13+12 -> 96 | AU13: =AT13+12 -> 108 | ... BB13: =BA13+12 -> 192 | BD13: =AM13 -> 12 | BE13: =AN13 -> 24 | BF13: =AO13 -> 36 | BG13: =AP13 -> 48 | BH13: =AQ13 -> 60 | BI13: =AR13 -> 72 | BJ13: =AS13 -> 84 | BK13: =AT13 -> 96 | ... BS13: =BB13 -> 192
B14: =IF($D$1="","",IF(INDEX('January 2026 Renewals'!$A:$A,$D$1+ROW()-ROW($B$14))<>$C$1,"",INDEX('January 2026 Renewals'!$H:$H,$D$1+ROW()-ROW($B$14)))) -> Desert Coating Systems, LLC | C14: =IF($D$1="","",IF(INDEX('January 2026 Renewals'!$A:$A,$D$1+ROW()-ROW($B$14))<>$C$1,"",INDEX('January 2026 Renewals'!$C:$C,$D$1+ROW()-ROW($B$14)))) -> 835-103 | D14: =IF($D$1="","",IF(INDEX('January 2026 Renewals'!$A:$A,$D$1+ROW()-ROW($B$14))<>$C$1,"",INDEX('January 2026 Renewals'!$E:$E,$D$1+ROW()-ROW($B$14)))) -> 103 | E14: =IF($D$1="","",IF(INDEX('January 2026 Renewals'!$A:$A,$D$1+ROW()-ROW($B$14))<>$C$1,"",INDEX('January 2026 Renewals'!$G:$G,$D$1+ROW()-ROW($B$14)))) -> 2500 | F14: =IF($D$1="","",IF(INDEX('January 2026 Renewals'!$A:$A,$D$1+ROW()-ROW($B$14))<>$C$1,"",INDEX('January 2026 Renewals'!$I:$I,$D$1+ROW()-ROW($B$14)))) -> 46053 | G14: =IF($D$1="","",IF(INDEX('January 2026 Renewals'!$A:$A,$D$1+ROW()-ROW($B$14))<>$C$1,"",INDEX('January 2026 Renewals'!$Q:$Q,$D$1+ROW()-ROW($B$14)))) -> 1.09 | H14: =IF($D$1="","",IF(INDEX('January 2026 Renewals'!$A:$A,$D$1+ROW()-ROW($B$14))<>$C$1,"",INDEX('January 2026 Renewals'!$R:$R,$D$1+ROW()-ROW($B$14)))) -> 1.3 | I14: =IF($D$1="","",IF(INDEX('January 2026 Renewals'!$A:$A,$D$1+ROW()-ROW($B$14))<>$C$1,"",INDEX('January 2026 Renewals'!$W:$W,$D$1+ROW()-ROW($B$14)))) -> 1.29 | J14: =IF($D$1="","",IF(INDEX('January 2026 Renewals'!$A:$A,$D$1+ROW()-ROW($B$14))<>$C$1,"",INDEX('January 2026 Renewals'!$AC:$AC,$D$1+ROW()-ROW($B$14)))) -> 1.26 | K14: =IF($D$1="","",IF(INDEX('January 2026 Renewals'!$A:$A,$D$1+ROW()-ROW($B$14))<>$C$1,"",INDEX('January 2026 Renewals'!$AM:$AM,$D$1+ROW()-ROW($B$14)))) -> 3 Years, $1.25 PSF, Expanding into 109
B15: =IF($D$1="","",IF(INDEX('January 2026 Renewals'!$A:$A,$D$1+ROW()-ROW($B$14))<>$C$1,"",INDEX('January 2026 Renewals'!$H:$H,$D$1+ROW()-ROW($B$14)))) -> Dew Utility LLC | C15: =IF($D$1="","",IF(INDEX('January 2026 Renewals'!$A:$A,$D$1+ROW()-ROW($B$14))<>$C$1,"",INDEX('January 2026 Renewals'!$C:$C,$D$1+ROW()-ROW($B$14)))) -> 819-102 | D15: =IF($D$1="","",IF(INDEX('January 2026 Renewals'!$A:$A,$D$1+ROW()-ROW($B$14))<>$C$1,"",INDEX('January 2026 Renewals'!$E:$E,$D$1+ROW()-ROW($B$14)))) -> Base | E15: =IF($D$1="","",IF(INDEX('January 2026 Renewals'!$A:$A,$D$1+ROW()-ROW($B$14))<>$C$1,"",INDEX('January 2026 Renewals'!$G:$G,$D$1+ROW()-ROW($B$14)))) -> 2500 | F15: =IF($D$1="","",IF(INDEX('January 2026 Renewals'!$A:$A,$D$1+ROW()-ROW($B$14))<>$C$1,"",INDEX('January 2026 Renewals'!$I:$I,$D$1+ROW()-ROW($B$14)))) -> 46203 | G15: =IF($D$1="","",IF(INDEX('January 2026 Renewals'!$A:$A,$D$1+ROW()-ROW($B$14))<>$C$1,"",INDEX('January 2026 Renewals'!$Q:$Q,$D$1+ROW()-ROW($B$14)))) -> 1.24 | H15: =IF($D$1="","",IF(INDEX('January 2026 Renewals'!$A:$A,$D$1+ROW()-ROW($B$14))<>$C$1,"",INDEX('January 2026 Renewals'!$R:$R,$D$1+ROW()-ROW($B$14)))) -> 1.3 | I15: =IF($D$1="","",IF(INDEX('January 2026 Renewals'!$A:$A,$D$1+ROW()-ROW($B$14))<>$C$1,"",INDEX('January 2026 Renewals'!$W:$W,$D$1+ROW()-ROW($B$14)))) -> 1.3 | J15: =IF($D$1="","",IF(INDEX('January 2026 Renewals'!$A:$A,$D$1+ROW()-ROW($B$14))<>$C$1,"",INDEX('January 2026 Renewals'!$AC:$AC,$D$1+ROW()-ROW($B$14)))) -> 1.3 | K15: =IF($D$1="","",IF(INDEX('January 2026 Renewals'!$A:$A,$D$1+ROW()-ROW($B$14))<>$C$1,"",INDEX('January 2026 Renewals'!$AM:$AM,$D$1+ROW()-ROW($B$14)))) -> 0
B16: =IF($D$1="","",IF(INDEX('January 2026 Renewals'!$A:$A,$D$1+ROW()-ROW($B$14))<>$C$1,"",INDEX('January 2026 Renewals'!$H:$H,$D$1+ROW()-ROW($B$14)))) | C16: =IF($D$1="","",IF(INDEX('January 2026 Renewals'!$A:$A,$D$1+ROW()-ROW($B$14))<>$C$1,"",INDEX('January 2026 Renewals'!$C:$C,$D$1+ROW()-ROW($B$14)))) | D16: =IF($D$1="","",IF(INDEX('January 2026 Renewals'!$A:$A,$D$1+ROW()-ROW($B$14))<>$C$1,"",INDEX('January 2026 Renewals'!$E:$E,$D$1+ROW()-ROW($B$14)))) | E16: =IF($D$1="","",IF(INDEX('January 2026 Renewals'!$A:$A,$D$1+ROW()-ROW($B$14))<>$C$1,"",INDEX('January 2026 Renewals'!$G:$G,$D$1+ROW()-ROW($B$14)))) | F16: =IF($D$1="","",IF(INDEX('January 2026 Renewals'!$A:$A,$D$1+ROW()-ROW($B$14))<>$C$1,"",INDEX('January 2026 Renewals'!$I:$I,$D$1+ROW()-ROW($B$14)))) | G16: =IF($D$1="","",IF(INDEX('January 2026 Renewals'!$A:$A,$D$1+ROW()-ROW($B$14))<>$C$1,"",INDEX('January 2026 Renewals'!$Q:$Q,$D$1+ROW()-ROW($B$14)))) | H16: =IF($D$1="","",IF(INDEX('January 2026 Renewals'!$A:$A,$D$1+ROW()-ROW($B$14))<>$C$1,"",INDEX('January 2026 Renewals'!$R:$R,$D$1+ROW()-ROW($B$14)))) | I16: =IF($D$1="","",IF(INDEX('January 2026 Renewals'!$A:$A,$D$1+ROW()-ROW($B$14))<>$C$1,"",INDEX('January 2026 Renewals'!$W:$W,$D$1+ROW()-ROW($B$14)))) | J16: =IF($D$1="","",IF(INDEX('January 2026 Renewals'!$A:$A,$D$1+ROW()-ROW($B$14))<>$C$1,"",INDEX('January 2026 Renewals'!$AC:$AC,$D$1+ROW()-ROW($B$14)))) | K16: =IF($D$1="","",IF(INDEX('January 2026 Renewals'!$A:$A,$D$1+ROW()-ROW($B$14))<>$C$1,"",INDEX('January 2026 Renewals'!$AM:$AM,$D$1+ROW()-ROW($B$14))))
B17: =IF($D$1="","",IF(INDEX('January 2026 Renewals'!$A:$A,$D$1+ROW()-ROW($B$14))<>$C$1,"",INDEX('January 2026 Renewals'!$H:$H,$D$1+ROW()-ROW($B$14)))) | C17: =IF($D$1="","",IF(INDEX('January 2026 Renewals'!$A:$A,$D$1+ROW()-ROW($B$14))<>$C$1,"",INDEX('January 2026 Renewals'!$C:$C,$D$1+ROW()-ROW($B$14)))) | D17: =IF($D$1="","",IF(INDEX('January 2026 Renewals'!$A:$A,$D$1+ROW()-ROW($B$14))<>$C$1,"",INDEX('January 2026 Renewals'!$E:$E,$D$1+ROW()-ROW($B$14)))) | E17: =IF($D$1="","",IF(INDEX('January 2026 Renewals'!$A:$A,$D$1+ROW()-ROW($B$14))<>$C$1,"",INDEX('January 2026 Renewals'!$G:$G,$D$1+ROW()-ROW($B$14)))) | F17: =IF($D$1="","",IF(INDEX('January 2026 Renewals'!$A:$A,$D$1+ROW()-ROW($B$14))<>$C$1,"",INDEX('January 2026 Renewals'!$I:$I,$D$1+ROW()-ROW($B$14)))) | G17: =IF($D$1="","",IF(INDEX('January 2026 Renewals'!$A:$A,$D$1+ROW()-ROW($B$14))<>$C$1,"",INDEX('January 2026 Renewals'!$Q:$Q,$D$1+ROW()-ROW($B$14)))) | H17: =IF($D$1="","",IF(INDEX('January 2026 Renewals'!$A:$A,$D$1+ROW()-ROW($B$14))<>$C$1,"",INDEX('January 2026 Renewals'!$R:$R,$D$1+ROW()-ROW($B$14)))) | I17: =IF($D$1="","",IF(INDEX('January 2026 Renewals'!$A:$A,$D$1+ROW()-ROW($B$14))<>$C$1,"",INDEX('January 2026 Renewals'!$W:$W,$D$1+ROW()-ROW($B$14)))) | J17: =IF($D$1="","",IF(INDEX('January 2026 Renewals'!$A:$A,$D$1+ROW()-ROW($B$14))<>$C$1,"",INDEX('January 2026 Renewals'!$AC:$AC,$D$1+ROW()-ROW($B$14)))) | K17: =IF($D$1="","",IF(INDEX('January 2026 Renewals'!$A:$A,$D$1+ROW()-ROW($B$14))<>$C$1,"",INDEX('January 2026 Renewals'!$AM:$AM,$D$1+ROW()-ROW($B$14))))
B18: =IF($D$1="","",IF(INDEX('January 2026 Renewals'!$A:$A,$D$1+ROW()-ROW($B$14))<>$C$1,"",INDEX('January 2026 Renewals'!$H:$H,$D$1+ROW()-ROW($B$14)))) | C18: =IF($D$1="","",IF(INDEX('January 2026 Renewals'!$A:$A,$D$1+ROW()-ROW($B$14))<>$C$1,"",INDEX('January 2026 Renewals'!$C:$C,$D$1+ROW()-ROW($B$14)))) | D18: =IF($D$1="","",IF(INDEX('January 2026 Renewals'!$A:$A,$D$1+ROW()-ROW($B$14))<>$C$1,"",INDEX('January 2026 Renewals'!$E:$E,$D$1+ROW()-ROW($B$14)))) | E18: =IF($D$1="","",IF(INDEX('January 2026 Renewals'!$A:$A,$D$1+ROW()-ROW($B$14))<>$C$1,"",INDEX('January 2026 Renewals'!$G:$G,$D$1+ROW()-ROW($B$14)))) | F18: =IF($D$1="","",IF(INDEX('January 2026 Renewals'!$A:$A,$D$1+ROW()-ROW($B$14))<>$C$1,"",INDEX('January 2026 Renewals'!$I:$I,$D$1+ROW()-ROW($B$14)))) | G18: =IF($D$1="","",IF(INDEX('January 2026 Renewals'!$A:$A,$D$1+ROW()-ROW($B$14))<>$C$1,"",INDEX('January 2026 Renewals'!$Q:$Q,$D$1+ROW()-ROW($B$14)))) | H18: =IF($D$1="","",IF(INDEX('January 2026 Renewals'!$A:$A,$D$1+ROW()-ROW($B$14))<>$C$1,"",INDEX('January 2026 Renewals'!$R:$R,$D$1+ROW()-ROW($B$14)))) | I18: =IF($D$1="","",IF(INDEX('January 2026 Renewals'!$A:$A,$D$1+ROW()-ROW($B$14))<>$C$1,"",INDEX('January 2026 Renewals'!$W:$W,$D$1+ROW()-ROW($B$14)))) | J18: =IF($D$1="","",IF(INDEX('January 2026 Renewals'!$A:$A,$D$1+ROW()-ROW($B$14))<>$C$1,"",INDEX('January 2026 Renewals'!$AC:$AC,$D$1+ROW()-ROW($B$14)))) | K18: =IF($D$1="","",IF(INDEX('January 2026 Renewals'!$A:$A,$D$1+ROW()-ROW($B$14))<>$C$1,"",INDEX('January 2026 Renewals'!$AM:$AM,$D$1+ROW()-ROW($B$14))))
B19: =IF($D$1="","",IF(INDEX('January 2026 Renewals'!$A:$A,$D$1+ROW()-ROW($B$14))<>$C$1,"",INDEX('January 2026 Renewals'!$H:$H,$D$1+ROW()-ROW($B$14)))) | C19: =IF($D$1="","",IF(INDEX('January 2026 Renewals'!$A:$A,$D$1+ROW()-ROW($B$14))<>$C$1,"",INDEX('January 2026 Renewals'!$C:$C,$D$1+ROW()-ROW($B$14)))) | D19: =IF($D$1="","",IF(INDEX('January 2026 Renewals'!$A:$A,$D$1+ROW()-ROW($B$14))<>$C$1,"",INDEX('January 2026 Renewals'!$E:$E,$D$1+ROW()-ROW($B$14)))) | E19: =IF($D$1="","",IF(INDEX('January 2026 Renewals'!$A:$A,$D$1+ROW()-ROW($B$14))<>$C$1,"",INDEX('January 2026 Renewals'!$G:$G,$D$1+ROW()-ROW($B$14)))) | F19: =IF($D$1="","",IF(INDEX('January 2026 Renewals'!$A:$A,$D$1+ROW()-ROW($B$14))<>$C$1,"",INDEX('January 2026 Renewals'!$I:$I,$D$1+ROW()-ROW($B$14)))) | G19: =IF($D$1="","",IF(INDEX('January 2026 Renewals'!$A:$A,$D$1+ROW()-ROW($B$14))<>$C$1,"",INDEX('January 2026 Renewals'!$Q:$Q,$D$1+ROW()-ROW($B$14)))) | H19: =IF($D$1="","",IF(INDEX('January 2026 Renewals'!$A:$A,$D$1+ROW()-ROW($B$14))<>$C$1,"",INDEX('January 2026 Renewals'!$R:$R,$D$1+ROW()-ROW($B$14)))) | I19: =IF($D$1="","",IF(INDEX('January 2026 Renewals'!$A:$A,$D$1+ROW()-ROW($B$14))<>$C$1,"",INDEX('January 2026 Renewals'!$W:$W,$D$1+ROW()-ROW($B$14)))) | J19: =IF($D$1="","",IF(INDEX('January 2026 Renewals'!$A:$A,$D$1+ROW()-ROW($B$14))<>$C$1,"",INDEX('January 2026 Renewals'!$AC:$AC,$D$1+ROW()-ROW($B$14)))) | K19: =IF($D$1="","",IF(INDEX('January 2026 Renewals'!$A:$A,$D$1+ROW()-ROW($B$14))<>$C$1,"",INDEX('January 2026 Renewals'!$AM:$AM,$D$1+ROW()-ROW($B$14))))
B20: =IF($D$1="","",IF(INDEX('January 2026 Renewals'!$A:$A,$D$1+ROW()-ROW($B$14))<>$C$1,"",INDEX('January 2026 Renewals'!$H:$H,$D$1+ROW()-ROW($B$14)))) | C20: =IF($D$1="","",IF(INDEX('January 2026 Renewals'!$A:$A,$D$1+ROW()-ROW($B$14))<>$C$1,"",INDEX('January 2026 Renewals'!$C:$C,$D$1+ROW()-ROW($B$14)))) | D20: =IF($D$1="","",IF(INDEX('January 2026 Renewals'!$A:$A,$D$1+ROW()-ROW($B$14))<>$C$1,"",INDEX('January 2026 Renewals'!$E:$E,$D$1+ROW()-ROW($B$14)))) | E20: =IF($D$1="","",IF(INDEX('January 2026 Renewals'!$A:$A,$D$1+ROW()-ROW($B$14))<>$C$1,"",INDEX('January 2026 Renewals'!$G:$G,$D$1+ROW()-ROW($B$14)))) | F20: =IF($D$1="","",IF(INDEX('January 2026 Renewals'!$A:$A,$D$1+ROW()-ROW($B$14))<>$C$1,"",INDEX('January 2026 Renewals'!$I:$I,$D$1+ROW()-ROW($B$14)))) | G20: =IF($D$1="","",IF(INDEX('January 2026 Renewals'!$A:$A,$D$1+ROW()-ROW($B$14))<>$C$1,"",INDEX('January 2026 Renewals'!$Q:$Q,$D$1+ROW()-ROW($B$14)))) | H20: =IF($D$1="","",IF(INDEX('January 2026 Renewals'!$A:$A,$D$1+ROW()-ROW($B$14))<>$C$1,"",INDEX('January 2026 Renewals'!$R:$R,$D$1+ROW()-ROW($B$14)))) | I20: =IF($D$1="","",IF(INDEX('January 2026 Renewals'!$A:$A,$D$1+ROW()-ROW($B$14))<>$C$1,"",INDEX('January 2026 Renewals'!$W:$W,$D$1+ROW()-ROW($B$14)))) | J20: =IF($D$1="","",IF(INDEX('January 2026 Renewals'!$A:$A,$D$1+ROW()-ROW($B$14))<>$C$1,"",INDEX('January 2026 Renewals'!$AC:$AC,$D$1+ROW()-ROW($B$14)))) | K20: =IF($D$1="","",IF(INDEX('January 2026 Renewals'!$A:$A,$D$1+ROW()-ROW($B$14))<>$C$1,"",INDEX('January 2026 Renewals'!$AM:$AM,$D$1+ROW()-ROW($B$14))))
B21: Total | E21: =SUM(E14:E20) -> 5000
A22: Current Availibilities
A23: *can also include prospects that have turned down the site and why
B24: Tenant | C24: Building | D24: Suite | E24: SF | F24: Date Suite Taken Back | G24: Days on Market | H24: Market Effective Rent | I24: On Lock Box | J24: Lease Ready | K24: Comments | R24: CPI Comments
B25: Deal Pending | C25: =IF($F$1="","",INDEX('Working - CPI'!$B:$B,$F$1+ROW()-ROW($B$25))) -> 819 W 22nd | D25: =IF($F$1="","",INDEX('Working - CPI'!$C:$C,$F$1+ROW()-ROW($B$25))) -> 104 | E25: =IF($F$1="","",INDEX('Working - CPI'!$D:$D,$F$1+ROW()-ROW($B$25))) -> 2500 | F25: =IF($F$1="","",INDEX('Working - CPI'!$E:$E,$F$1+ROW()-ROW($B$25))) -> 45716 | G25: =IF($F$1="","",INDEX('Working - CPI'!$F:$F,$F$1+ROW()-ROW($B$25))) -> 293.52767 | H25: =IF($F$1="","",INDEX('Working - CPI'!$G:$G,$F$1+ROW()-ROW($B$25))) -> 1.3 | I25: =IF($F$1="","",INDEX('Working - CPI'!$H:$H,$F$1+ROW()-ROW($B$25))) -> Yes | J25: =IF($F$1="","",INDEX('Working - CPI'!$I:$I,$F$1+ROW()-ROW($B$25))) -> Yes | K25: =IF($F$1="","",INDEX('Working - CPI'!$J:$J,$F$1+ROW()-ROW($B$25))) -> Lease Ready | R25: Deal Pending MCLC
B26: Deal Pending | C26: =IF($F$1="","",INDEX('Working - CPI'!$B:$B,$F$1+ROW()-ROW($B$25))) -> 819 W 22nd | D26: =IF($F$1="","",INDEX('Working - CPI'!$C:$C,$F$1+ROW()-ROW($B$25))) -> 105 | E26: =IF($F$1="","",INDEX('Working - CPI'!$D:$D,$F$1+ROW()-ROW($B$25))) -> 5000 | F26: =IF($F$1="","",INDEX('Working - CPI'!$E:$E,$F$1+ROW()-ROW($B$25))) -> 45716 | G26: =IF($F$1="","",INDEX('Working - CPI'!$F:$F,$F$1+ROW()-ROW($B$25))) -> 293.52767 | H26: =IF($F$1="","",INDEX('Working - CPI'!$G:$G,$F$1+ROW()-ROW($B$25))) -> 1.3 | I26: =IF($F$1="","",INDEX('Working - CPI'!$H:$H,$F$1+ROW()-ROW($B$25))) -> Yes | J26: =IF($F$1="","",INDEX('Working - CPI'!$I:$I,$F$1+ROW()-ROW($B$25))) -> Yes | K26: =IF($F$1="","",INDEX('Working - CPI'!$J:$J,$F$1+ROW()-ROW($B$25))) -> Lease Ready | R26: Deal Pending-MCLC
B27: Deal Pending | C27: =IF($F$1="","",INDEX('Working - CPI'!$B:$B,$F$1+ROW()-ROW($B$25))) -> 819 W 22nd | D27: =IF($F$1="","",INDEX('Working - CPI'!$C:$C,$F$1+ROW()-ROW($B$25))) -> 109 | E27: =IF($F$1="","",INDEX('Working - CPI'!$D:$D,$F$1+ROW()-ROW($B$25))) -> 2500 | F27: =IF($F$1="","",INDEX('Working - CPI'!$E:$E,$F$1+ROW()-ROW($B$25))) -> 45839 | G27: =IF($F$1="","",INDEX('Working - CPI'!$F:$F,$F$1+ROW()-ROW($B$25))) -> 170.52767 | H27: =IF($F$1="","",INDEX('Working - CPI'!$G:$G,$F$1+ROW()-ROW($B$25))) -> 1.3 | I27: =IF($F$1="","",INDEX('Working - CPI'!$H:$H,$F$1+ROW()-ROW($B$25))) -> Yes | J27: =IF($F$1="","",INDEX('Working - CPI'!$I:$I,$F$1+ROW()-ROW($B$25))) -> Yes | K27: =IF($F$1="","",INDEX('Working - CPI'!$J:$J,$F$1+ROW()-ROW($B$25))) -> Lease Ready | R27: Deal Pending- Desert Coating Expansion
B28: =IF($F$1="","",IF(INDEX('Working - CPI'!$D:$D,$F$1+ROW()-ROW($B$25))>0,"Vacant","")) -> Vacant | C28: =IF($F$1="","",INDEX('Working - CPI'!$B:$B,$F$1+ROW()-ROW($B$25))) -> 835 W 22nd St | D28: =IF($F$1="","",INDEX('Working - CPI'!$C:$C,$F$1+ROW()-ROW($B$25))) -> 110 | E28: =IF($F$1="","",INDEX('Working - CPI'!$D:$D,$F$1+ROW()-ROW($B$25))) -> 2500 | F28: =IF($F$1="","",INDEX('Working - CPI'!$E:$E,$F$1+ROW()-ROW($B$25))) -> 45931 | G28: =IF($F$1="","",INDEX('Working - CPI'!$F:$F,$F$1+ROW()-ROW($B$25))) -> 78.527668 | H28: =IF($F$1="","",INDEX('Working - CPI'!$G:$G,$F$1+ROW()-ROW($B$25))) -> 1.3 | I28: =IF($F$1="","",INDEX('Working - CPI'!$H:$H,$F$1+ROW()-ROW($B$25))) -> Yes | J28: =IF($F$1="","",INDEX('Working - CPI'!$I:$I,$F$1+ROW()-ROW($B$25))) -> Yes | K28: =IF($F$1="","",INDEX('Working - CPI'!$J:$J,$F$1+ROW()-ROW($B$25))) -> Updated- Lease ready | R28: 400 AMPS power (LARGE panel)
B40: Deal Pending | C40: =SUMIF(B22:B35,B40,E22:E35) -> 10000 | E40: =SUM(E25:E39) -> 12500 | G40: Vacant | H40: =SUMIF(B22:B35,G40,E22:E35) -> 2500
A41: Executed Leases | W41: NER Calculations
G42: RENT | I42: TERM | K42: TI | M42: Free Rent | O42: Bumps | P42: LCs | Q42: NER | R42: NER Check | W42: Subtotals | AB42: Budget / Actual | AE42: Term
B43: Tenant | C43: Building | D43: Suite | E43: SF | F43: Type | G43: New | H43: Budget | I43: New | J43: Budget | K43: New | L43: Budget | M43: New | N43: Budget | O43: Actual | P43: Actual | Q43: Actual | R43: =S6 -> 0 | S43: Execution | T43: Comments | W43: Revenue | X43: Bumps | Y43: TIs | Z43: LCs | AA43: FR | AB43: Rent | AC43: FR | AD43: TI | AE43: Years | AF43: Month | AG43: Total | AH43: Term Check | AM43: =AM5 -> Raleigh Light Industrial - Rent Bump Calculation | BD43: =BD5 -> Raleigh Light Industrial - Rent Bump Calculation (Monthly Rents)
B44: =IF($G$1="","",INDEX('Lease Report 2025'!$H:$H,$G$1+ROW()-ROW($B$44))) -> TRUE WORLD FOODS PHOENIX, LLC ( TW FOODS LLC ) | C44: =IF($G$1="","",INDEX('Lease Report 2025'!$D:$D,$G$1+ROW()-ROW($B$44))) -> 835 W 22nd | D44: =IF($G$1="","",INDEX('Lease Report 2025'!$E:$E,$G$1+ROW()-ROW($B$44))) -> 105-107 | E44: =IF($G$1="","",INDEX('Lease Report 2025'!$G:$G,$G$1+ROW()-ROW($B$44))) -> 7500 | F44: =IF($G$1="","",INDEX('Lease Report 2025'!$A:$A,$G$1+ROW()-ROW($B$44))) -> R | G44: =IF($G$1="","",INDEX('Lease Report 2025'!$L:$L,$G$1+ROW()-ROW($B$44))) -> 1.15 | I44: =IF($G$1="","",INDEX('Lease Report 2025'!$P:$P,$G$1+ROW()-ROW($B$44))) -> 5 | O44: =IF($G$1="","",INDEX('Lease Report 2025'!$N:$N,$G$1+ROW()-ROW($B$44))) -> 0.05 | S44: =IF($G$1="","",INDEX('Lease Report 2025'!$R:$R,$G$1+ROW()-ROW($B$44))) -> 45901 | T44: =IF($G$1="","",INDEX('Lease Report 2025'!$O:$O,$G$1+ROW()-ROW($B$44))) -> No TI, No Free rent, No outside agent, Base Year Gross
A50: Dead Deals
A51: *can also include prospects that have turned down the site and why
A52: Broker | B52: Tenant | C52: Building | D52: Suite | E52: SF | F52: Expiration | L52: 6

Sheet 167_RR
D2: BROADWAY INDUSTRIAL PARK
C3: As Of : 11/21/2025
E5: SQFT | H5: Annual | I5: Monthly | N5: Rent | AC5: Lease
A6: Suite | B6: Tenant Name | E6: Rentable | G6: Leased | H6: Rent | I6: Rent | K6: P.S.F | L6: Suite(s) | N6: Begin | T6: End | W6: Base Rent | X6: P.S.F | AC6: Begin | AD6: End
A7: 819-101 | B7: VINCE NGUYEN & VAN NGUYEN | E7: 2500 | G7: 2500 | H7: 43650 | I7: 3637.5 | K7: 17.46 | N7: 45627 | W7: 3637.5 | X7: 17.46 | AC7: 45627
A9: 819-102 | B9: Dew Utility LLC | E9: 2500 | G9: 2500 | H9: 37200 | I9: 3100 | K9: 14.88 | N9: 45839 | T9: 46203 | W9: 3100 | X9: 14.88 | AC9: 45108 | AD9: 06/30/2026
A11: 819-103 | B11: QUALITY SIGN COMPANY LLC | E11: 2500 | G11: 2500 | H11: 36300 | I11: 3025 | K11: 14.52 | N11: 45717 | T11: 46081 | W11: 3025 | X11: 14.52 | AC11: 45352 | AD11: 02/28/2027
N12: 46082 | T12: 46446 | W12: 3175 | X12: 15.24
A14: 819-104 | B14: Vacant | E14: 2500 | G14: 0 | K14: 0 | X14: 0
A16: 819-105 | B16: Vacant | E16: 5000 | G16: 0 | K16: 0 | X16: 0
A18: 819-107 | B18: DARKHORSE LIONHEART, LLC | E18: 732 | G18: 732 | H18: 21081.6 | I18: 1756.8 | K18: 28.8 | N18: 45474 | W18: 1756.8 | X18: 28.8 | AC18: 45474
A20: 819-108 | B20: AXISWORKS, LLC | E20: 2500 | G20: 2500 | H20: 39600 | I20: 3300 | K20: 15.84 | N20: 45627 | T20: 45991 | W20: 3300 | X20: 15.84 | AC20: 45261 | AD20: 11/30/2026
N21: 45992 | T21: 46356 | W21: 3475 | X21: 16.68
A23: 819-109 | B23: Vacant | E23: 2500 | G23: 0 | K23: 0 | X23: 0
A25: 835-101 | B25: JUST BETTER AIR CONDITIONING | E25: 2500 | G25: 2500 | H25: 63000 | I25: 5250 | K25: 12.6 | L25: 835-101, 835-102 | N25: 45839 | T25: 46142 | W25: 5250 | X25: 12.6 | AC25: 45474 | AD25: 06/30/2029
N26: 46143 | T26: 46203 | W26: 5350 | X26: 12.84
N27: 46204 | T27: 46507 | W27: 5475 | X27: 13.14
N28: 46508 | T28: 46568 | W28: 6000 | X28: 14.4
N29: 46569 | T29: 46934 | W29: 6250 | X29: 15
N30: 46935 | T30: 47299 | W30: 6500 | X30: 15.6
A32: 835-102 | B32: JUST BETTER AIR CONDITIONING | E32: 2500 | G32: 2500 | K32: 0 | L32: 835-101, 835-102 | X32: 0 | AC32: 45474 | AD32: 06/30/2029
A34: 835-103 | B34: DESERT COATING SYSTEMS, LLC | E34: 2500 | G34: 2500 | H34: 32700 | I34: 2725 | K34: 13.08 | N34: 45689 | T34: 46053 | W34: 2725 | X34: 13.08 | AC34: 44958 | AD34: 01/31/2026
A36: 835-104 | B36: US SOLAR PROGRAMS, LLC | E36: 731 | G36: 731 | H36: 11052.72 | I36: 921.06 | K36: 15.12 | N36: 45689 | T36: 46053 | W36: 921.06 | X36: 15.12 | AC36: 45323 | AD36: 01/31/2027
N37: 46054 | T37: 46418 | W37: 964.92 | X37: 15.84
A39: 835-107 | B39: TRUE WORLD FOODS PHOENIX, LLC ( TW FOODS LLC ) | E39: 7500 | G39: 7500 | H39: 103500 | I39: 8625 | K39: 13.8 | N39: 45901 | T39: 46265 | W39: 8625 | X39: 13.8 | AC39: 45901 | AD39: 08/31/2030
N40: 46266 | T40: 46630 | W40: 9000 | X40: 14.4
N41: 46631 | T41: 46996 | W41: 9375 | X41: 15
N42: 46997 | T42: 47361 | W42: 9750 | X42: 15.6
N43: 47362 | T43: 47726 | W43: 10125 | X43: 16.2
A45: 835-108 | B45: OLSSON, INC. | E45: 2500 | G45: 2500 | K45: 0 | X45: 0 | AC45: 45839
A47: 835-109 | B47: Konecranes, Inc. | E47: 2500 | G47: 2500 | H47: 39000 | I47: 3250 | K47: 15.6 | N47: 45717 | T47: 46081 | W47: 3250 | X47: 15.6 | AC47: 45352 | AD47: 02/28/2027
N48: 46082 | T48: 46446 | W48: 3380 | X48: 16.224
A50: 835-110 | B50: Vacant | E50: 2500 | G50: 0 | K50: 0 | X50: 0
J54: Report Totals :
J56: Rentable SQFT: | M56: 43963 | S56: Monthly Rent: | V56: 35590.36
S58: Annual Rent: | V58: 427084.32
J59: Leased SQFT: | M59: 31463
J62: Total Occupied | M62: 31463 | R62: % Occupancy | U62: 71.567
J63: Total Vacant | M63: 12500 | R63: % Vacant | U63: 28.433
J65: Total SQFT | M65: 43963

Sheet 336_Central Deer Valley
A1: Central Deer Valley | C1: 336 | D1: 8 | F1: =IFERROR(MATCH($C$1,'Working - CPI'!$A:$A,0),"") -> 596 | G1: =IFERROR(MATCH($C$1,'Lease Report 2025'!$B:$B,0),"") -> 14 | T1: Leasing Pipeline Report
A2: Phoenix, Arizona | C2: =IF(G2=0,"",(G2-E38)/G2) -> 0.92161339 | D2: % Occupancy | F2: SF | G2: ='Occupancy Summary Schedule'!D22 -> 52560 | U2: =TODAY() -> 46009 | AH2: SF Threshold
A3: ='Occupancy Summary Schedule'!F53 -> 0.88710744 | B3: % CPI Portfolio Occupancy | AH3: 5000
A4: Active Lease Deals | W4: NER Calculations | AJ4: # | AK4: List
G5: RENT | J5: TERM | L5: TI | N5: Free Rent | P5: Bumps (%) | Q5: LCs | R5: NER | S5: NER Check | V5: NER Check | W5: Subtotals | AB5: Budget / Actual | AE5: Term | AJ5: 0 | AK5: Good | AM5: Raleigh Light Industrial - Rent Bump Calculation | BD5: Raleigh Light Industrial - Rent Bump Calculation (Monthly Rents)
A6: Broker | B6: Tenant | C6: Building | D6: Suite | E6: SF | F6: Type | G6: Current | H6: CPI Proj | I6: Proposed | J6: Budget | K6: Proposed | L6: Budget | M6: Proposed | N6: Budget | O6: Proposed | P6: Proposed | Q6: Proposed | R6: Proposed | T6: Expiration | U6: Comments | W6: Revenue | X6: Bumps | Y6: TIs | Z6: LCs | AA6: FR | AB6: Rent | AC6: FR | AD6: TI | AE6: Years | AF6: Month | AG6: Total | AH6: Term Check | AJ6: 1 | AK6: Check Term | AL6: Month: | AM6: 12 | AN6: =AM6+12 -> 24 | AO6: =AN6+12 -> 36 | AP6: =AO6+12 -> 48 | AQ6: =AP6+12 -> 60 | AR6: =AQ6+12 -> 72 | AS6: =AR6+12 -> 84 | AT6: =AS6+12 -> 96 | AU6: =AT6+12 -> 108 | ... BB6: =BA6+12 -> 192 | BD6: =AM6 -> 12 | BE6: =AN6 -> 24 | BF6: =AO6 -> 36 | BG6: =AP6 -> 48 | BH6: =AQ6 -> 60 | BI6: =AR6 -> 72 | BJ6: =AS6 -> 84 | BK6: =AT6 -> 96 | ... BS6: =BB6 -> 192
W7: =AB7*E7*(AG7/12) -> 0 | X7: =SUMIFS($AM7:$BB7,$AM$6:$BB$6,"<="&AG7)+(INDEX($BD7:$BS7,MATCH(AG7+12,$AM$6:$BB$6))*(AG7-INDEX($AM$6:$BB$6,MATCH(AG7,$AM$6:$BB$6))))-W7 -> #N/A | Y7: =AD7*E7 -> 0 | Z7: =SUM(W7:X7)*Q7 -> #N/A | AA7: =AB7/12*E7*AC7 -> 0 | AB7: =IF(I7="",H7,I7) -> 0 | AC7: =IF(O7="",N7,O7) -> 0 | AD7: =IF(M7="",L7,M7) -> 0 | AE7: =IFERROR(LEFT(K7, FIND("-", K7) - 1),J7) -> 0 | AF7: =IFERROR(RIGHT(K7,LEN(K7)-SEARCH("-",K7)),0) -> 0 | AG7: =_xlfn.NUMBERVALUE(AE7)*12+_xlfn.NUMBERVALUE(AF7) -> 0 | AH7: =IF(E7<$AH$3,36,60) -> 36 | AJ7: 2 | AK7: Check | AM7: =AB7*$E7 -> 0 | AN7: =AM7*(1+$P7) -> 0 | AO7: =AN7*(1+$P7) -> 0 | AP7: =AO7*(1+$P7) -> 0 | AQ7: =AP7*(1+$P7) -> 0 | AR7: =AQ7*(1+$P7) -> 0 | AS7: =AR7*(1+$P7) -> 0 | AT7: =AS7*(1+$P7) -> 0 | AU7: =AT7*(1+$P7) -> 0 | ... BB7: =BA7*(1+$P7) -> 0 | BD7: =AM7/12 -> 0 | BE7: =AN7/12 -> 0 | BF7: =AO7/12 -> 0 | BG7: =AP7/12 -> 0 | BH7: =AQ7/12 -> 0 | BI7: =AR7/12 -> 0 | BJ7: =AS7/12 -> 0 | BK7: =AT7/12 -> 0 | ... BS7: =BB7/12 -> 0
W8: =AB8*E8*(AG8/12) -> 0 | X8: =SUMIFS($AM8:$BB8,$AM$6:$BB$6,"<="&AG8)+(INDEX($BD8:$BS8,MATCH(AG8+12,$AM$6:$BB$6))*(AG8-INDEX($AM$6:$BB$6,MATCH(AG8,$AM$6:$BB$6))))-W8 -> #N/A | Y8: =AD8*E8 -> 0 | Z8: =SUM(W8:X8)*Q8 -> #N/A | AA8: =AB8/12*E8*AC8 -> 0 | AB8: =IF(I8="",H8,I8) -> 0 | AC8: =IF(O8="",N8,O8) -> 0 | AD8: =IF(M8="",L8,M8) -> 0 | AE8: =IFERROR(LEFT(K8, FIND("-", K8) - 1),J8) -> 0 | AF8: =IFERROR(RIGHT(K8,LEN(K8)-SEARCH("-",K8)),0) -> 0 | AG8: =_xlfn.NUMBERVALUE(AE8)*12+_xlfn.NUMBERVALUE(AF8) -> 0 | AH8: =IF(E8<$AH$3,36,60) -> 36 | AM8: =AB8*$E8 -> 0 | AN8: =AM8*(1+$P8) -> 0 | AO8: =AN8*(1+$P8) -> 0 | AP8: =AO8*(1+$P8) -> 0 | AQ8: =AP8*(1+$P8) -> 0 | AR8: =AQ8*(1+$P8) -> 0 | AS8: =AR8*(1+$P8) -> 0 | AT8: =AS8*(1+$P8) -> 0 | AU8: =AT8*(1+$P8) -> 0 | ... BB8: =BA8*(1+$P8) -> 0 | BD8: =AM8/12 -> 0 | BE8: =AN8/12 -> 0 | BF8: =AO8/12 -> 0 | BG8: =AP8/12 -> 0 | BH8: =AQ8/12 -> 0 | BI8: =AR8/12 -> 0 | BJ8: =AS8/12 -> 0 | BK8: =AT8/12 -> 0 | ... BS8: =BB8/12 -> 0
W9: =AB9*E9*(AG9/12) -> 0 | X9: =SUMIFS($AM9:$BB9,$AM$6:$BB$6,"<="&AG9)+(INDEX($BD9:$BS9,MATCH(AG9+12,$AM$6:$BB$6))*(AG9-INDEX($AM$6:$BB$6,MATCH(AG9,$AM$6:$BB$6))))-W9 -> #N/A | Y9: =AD9*E9 -> 0 | Z9: =SUM(W9:X9)*Q9 -> #N/A | AA9: =AB9/12*E9*AC9 -> 0 | AB9: =IF(I9="",H9,I9) -> 0 | AC9: =IF(O9="",N9,O9) -> 0 | AD9: =IF(M9="",L9,M9) -> 0 | AE9: =IFERROR(LEFT(K9, FIND("-", K9) - 1),J9) -> 0 | AF9: =IFERROR(RIGHT(K9,LEN(K9)-SEARCH("-",K9)),0) -> 0 | AG9: =_xlfn.NUMBERVALUE(AE9)*12+_xlfn.NUMBERVALUE(AF9) -> 0 | AH9: =IF(E9<$AH$3,36,60) -> 36 | AM9: =AB9*$E9 -> 0 | AN9: =AM9*(1+$P9) -> 0 | AO9: =AN9*(1+$P9) -> 0 | AP9: =AO9*(1+$P9) -> 0 | AQ9: =AP9*(1+$P9) -> 0 | AR9: =AQ9*(1+$P9) -> 0 | AS9: =AR9*(1+$P9) -> 0 | AT9: =AS9*(1+$P9) -> 0 | AU9: =AT9*(1+$P9) -> 0 | ... BB9: =BA9*(1+$P9) -> 0 | BD9: =AM9/12 -> 0 | BE9: =AN9/12 -> 0 | BF9: =AO9/12 -> 0 | BG9: =AP9/12 -> 0 | BH9: =AQ9/12 -> 0 | BI9: =AR9/12 -> 0 | BJ9: =AS9/12 -> 0 | BK9: =AT9/12 -> 0 | ... BS9: =BB9/12 -> 0
A10: Tenants Expiring - Next 6 months
A12: Broker | B12: Tenant | C12: Building | D12: Suite | E12: SF | F12: Expires | G12: Current | H12: Budget | I12: Proposed 3 Year | J12: Proposed 5 Year | K12: Notes | W12: Revenue | X12: Bumps | Y12: TIs | Z12: LCs | AA12: FR | AB12: Rent | AC12: FR | AD12: TI | AE12: Years | AF12: Month | AG12: Total | AH12: Term Check | AJ12: 1 | AK12: Check Term | AL12: Month: | AM12: 12 | AN12: =AM12+12 -> 24 | AO12: =AN12+12 -> 36 | AP12: =AO12+12 -> 48 | AQ12: =AP12+12 -> 60 | AR12: =AQ12+12 -> 72 | AS12: =AR12+12 -> 84 | AT12: =AS12+12 -> 96 | AU12: =AT12+12 -> 108 | ... BB12: =BA12+12 -> 192 | BD12: =AM12 -> 12 | BE12: =AN12 -> 24 | BF12: =AO12 -> 36 | BG12: =AP12 -> 48 | BH12: =AQ12 -> 60 | BI12: =AR12 -> 72 | BJ12: =AS12 -> 84 | BK12: =AT12 -> 96 | ... BS12: =BB12 -> 192
B13: =IF($D$1="","",IF(INDEX('January 2026 Renewals'!$A:$A,$D$1+ROW()-ROW($B$13))<>$C$1,"",INDEX('January 2026 Renewals'!$H:$H,$D$1+ROW()-ROW($B$13)))) -> MANNINO CUSTOM FURNITURE & AMERICAN CLASSIC FLOORING | C13: =IF($D$1="","",IF(INDEX('January 2026 Renewals'!$A:$A,$D$1+ROW()-ROW($B$13))<>$C$1,"",INDEX('January 2026 Renewals'!$C:$C,$D$1+ROW()-ROW($B$13)))) -> 616-01/616-02/616-10 | D13: =IF($D$1="","",IF(INDEX('January 2026 Renewals'!$A:$A,$D$1+ROW()-ROW($B$13))<>$C$1,"",INDEX('January 2026 Renewals'!$E:$E,$D$1+ROW()-ROW($B$13)))) -> Base | E13: =IF($D$1="","",IF(INDEX('January 2026 Renewals'!$A:$A,$D$1+ROW()-ROW($B$13))<>$C$1,"",INDEX('January 2026 Renewals'!$G:$G,$D$1+ROW()-ROW($B$13)))) -> 3675 | F13: =IF($D$1="","",IF(INDEX('January 2026 Renewals'!$A:$A,$D$1+ROW()-ROW($B$13))<>$C$1,"",INDEX('January 2026 Renewals'!$I:$I,$D$1+ROW()-ROW($B$13)))) -> 46112 | G13: =IF($D$1="","",IF(INDEX('January 2026 Renewals'!$A:$A,$D$1+ROW()-ROW($B$13))<>$C$1,"",INDEX('January 2026 Renewals'!$Q:$Q,$D$1+ROW()-ROW($B$13)))) -> 1.45 | H13: =IF($D$1="","",IF(INDEX('January 2026 Renewals'!$A:$A,$D$1+ROW()-ROW($B$13))<>$C$1,"",INDEX('January 2026 Renewals'!$R:$R,$D$1+ROW()-ROW($B$13)))) -> 0 | I13: =IF($D$1="","",IF(INDEX('January 2026 Renewals'!$A:$A,$D$1+ROW()-ROW($B$13))<>$C$1,"",INDEX('January 2026 Renewals'!$W:$W,$D$1+ROW()-ROW($B$13)))) -> 1.52 | J13: =IF($D$1="","",IF(INDEX('January 2026 Renewals'!$A:$A,$D$1+ROW()-ROW($B$13))<>$C$1,"",INDEX('January 2026 Renewals'!$AC:$AC,$D$1+ROW()-ROW($B$13)))) -> 1.52 | K13: =IF($D$1="","",IF(INDEX('January 2026 Renewals'!$A:$A,$D$1+ROW()-ROW($B$13))<>$C$1,"",INDEX('January 2026 Renewals'!$AM:$AM,$D$1+ROW()-ROW($B$13)))) -> 0
B14: =IF($D$1="","",IF(INDEX('January 2026 Renewals'!$A:$A,$D$1+ROW()-ROW($B$13))<>$C$1,"",INDEX('January 2026 Renewals'!$H:$H,$D$1+ROW()-ROW($B$13)))) | C14: =IF($D$1="","",IF(INDEX('January 2026 Renewals'!$A:$A,$D$1+ROW()-ROW($B$13))<>$C$1,"",INDEX('January 2026 Renewals'!$C:$C,$D$1+ROW()-ROW($B$13)))) | D14: =IF($D$1="","",IF(INDEX('January 2026 Renewals'!$A:$A,$D$1+ROW()-ROW($B$13))<>$C$1,"",INDEX('January 2026 Renewals'!$E:$E,$D$1+ROW()-ROW($B$13)))) | E14: =IF($D$1="","",IF(INDEX('January 2026 Renewals'!$A:$A,$D$1+ROW()-ROW($B$13))<>$C$1,"",INDEX('January 2026 Renewals'!$G:$G,$D$1+ROW()-ROW($B$13)))) | F14: =IF($D$1="","",IF(INDEX('January 2026 Renewals'!$A:$A,$D$1+ROW()-ROW($B$13))<>$C$1,"",INDEX('January 2026 Renewals'!$I:$I,$D$1+ROW()-ROW($B$13)))) | G14: =IF($D$1="","",IF(INDEX('January 2026 Renewals'!$A:$A,$D$1+ROW()-ROW($B$13))<>$C$1,"",INDEX('January 2026 Renewals'!$Q:$Q,$D$1+ROW()-ROW($B$13)))) | H14: =IF($D$1="","",IF(INDEX('January 2026 Renewals'!$A:$A,$D$1+ROW()-ROW($B$13))<>$C$1,"",INDEX('January 2026 Renewals'!$R:$R,$D$1+ROW()-ROW($B$13)))) | I14: =IF($D$1="","",IF(INDEX('January 2026 Renewals'!$A:$A,$D$1+ROW()-ROW($B$13))<>$C$1,"",INDEX('January 2026 Renewals'!$W:$W,$D$1+ROW()-ROW($B$13)))) | J14: =IF($D$1="","",IF(INDEX('January 2026 Renewals'!$A:$A,$D$1+ROW()-ROW($B$13))<>$C$1,"",INDEX('January 2026 Renewals'!$AC:$AC,$D$1+ROW()-ROW($B$13)))) | K14: =IF($D$1="","",IF(INDEX('January 2026 Renewals'!$A:$A,$D$1+ROW()-ROW($B$13))<>$C$1,"",INDEX('January 2026 Renewals'!$AM:$AM,$D$1+ROW()-ROW($B$13))))
B15: =IF($D$1="","",IF(INDEX('January 2026 Renewals'!$A:$A,$D$1+ROW()-ROW($B$13))<>$C$1,"",INDEX('January 2026 Renewals'!$H:$H,$D$1+ROW()-ROW($B$13)))) | C15: =IF($D$1="","",IF(INDEX('January 2026 Renewals'!$A:$A,$D$1+ROW()-ROW($B$13))<>$C$1,"",INDEX('January 2026 Renewals'!$C:$C,$D$1+ROW()-ROW($B$13)))) | D15: =IF($D$1="","",IF(INDEX('January 2026 Renewals'!$A:$A,$D$1+ROW()-ROW($B$13))<>$C$1,"",INDEX('January 2026 Renewals'!$E:$E,$D$1+ROW()-ROW($B$13)))) | E15: =IF($D$1="","",IF(INDEX('January 2026 Renewals'!$A:$A,$D$1+ROW()-ROW($B$13))<>$C$1,"",INDEX('January 2026 Renewals'!$G:$G,$D$1+ROW()-ROW($B$13)))) | F15: =IF($D$1="","",IF(INDEX('January 2026 Renewals'!$A:$A,$D$1+ROW()-ROW($B$13))<>$C$1,"",INDEX('January 2026 Renewals'!$I:$I,$D$1+ROW()-ROW($B$13)))) | G15: =IF($D$1="","",IF(INDEX('January 2026 Renewals'!$A:$A,$D$1+ROW()-ROW($B$13))<>$C$1,"",INDEX('January 2026 Renewals'!$Q:$Q,$D$1+ROW()-ROW($B$13)))) | H15: =IF($D$1="","",IF(INDEX('January 2026 Renewals'!$A:$A,$D$1+ROW()-ROW($B$13))<>$C$1,"",INDEX('January 2026 Renewals'!$R:$R,$D$1+ROW()-ROW($B$13)))) | I15: =IF($D$1="","",IF(INDEX('January 2026 Renewals'!$A:$A,$D$1+ROW()-ROW($B$13))<>$C$1,"",INDEX('January 2026 Renewals'!$W:$W,$D$1+ROW()-ROW($B$13)))) | J15: =IF($D$1="","",IF(INDEX('January 2026 Renewals'!$A:$A,$D$1+ROW()-ROW($B$13))<>$C$1,"",INDEX('January 2026 Renewals'!$AC:$AC,$D$1+ROW()-ROW($B$13)))) | K15: =IF($D$1="","",IF(INDEX('January 2026 Renewals'!$A:$A,$D$1+ROW()-ROW($B$13))<>$C$1,"",INDEX('January 2026 Renewals'!$AM:$AM,$D$1+ROW()-ROW($B$13))))
B16: =IF($D$1="","",IF(INDEX('January 2026 Renewals'!$A:$A,$D$1+ROW()-ROW($B$13))<>$C$1,"",INDEX('January 2026 Renewals'!$H:$H,$D$1+ROW()-ROW($B$13)))) | C16: =IF($D$1="","",IF(INDEX('January 2026 Renewals'!$A:$A,$D$1+ROW()-ROW($B$13))<>$C$1,"",INDEX('January 2026 Renewals'!$C:$C,$D$1+ROW()-ROW($B$13)))) | D16: =IF($D$1="","",IF(INDEX('January 2026 Renewals'!$A:$A,$D$1+ROW()-ROW($B$13))<>$C$1,"",INDEX('January 2026 Renewals'!$E:$E,$D$1+ROW()-ROW($B$13)))) | E16: =IF($D$1="","",IF(INDEX('January 2026 Renewals'!$A:$A,$D$1+ROW()-ROW($B$13))<>$C$1,"",INDEX('January 2026 Renewals'!$G:$G,$D$1+ROW()-ROW($B$13)))) | F16: =IF($D$1="","",IF(INDEX('January 2026 Renewals'!$A:$A,$D$1+ROW()-ROW($B$13))<>$C$1,"",INDEX('January 2026 Renewals'!$I:$I,$D$1+ROW()-ROW($B$13)))) | G16: =IF($D$1="","",IF(INDEX('January 2026 Renewals'!$A:$A,$D$1+ROW()-ROW($B$13))<>$C$1,"",INDEX('January 2026 Renewals'!$Q:$Q,$D$1+ROW()-ROW($B$13)))) | H16: =IF($D$1="","",IF(INDEX('January 2026 Renewals'!$A:$A,$D$1+ROW()-ROW($B$13))<>$C$1,"",INDEX('January 2026 Renewals'!$R:$R,$D$1+ROW()-ROW($B$13)))) | I16: =IF($D$1="","",IF(INDEX('January 2026 Renewals'!$A:$A,$D$1+ROW()-ROW($B$13))<>$C$1,"",INDEX('January 2026 Renewals'!$W:$W,$D$1+ROW()-ROW($B$13)))) | J16: =IF($D$1="","",IF(INDEX('January 2026 Renewals'!$A:$A,$D$1+ROW()-ROW($B$13))<>$C$1,"",INDEX('January 2026 Renewals'!$AC:$AC,$D$1+ROW()-ROW($B$13)))) | K16: =IF($D$1="","",IF(INDEX('January 2026 Renewals'!$A:$A,$D$1+ROW()-ROW($B$13))<>$C$1,"",INDEX('January 2026 Renewals'!$AM:$AM,$D$1+ROW()-ROW($B$13))))
B17: =IF($D$1="","",IF(INDEX('January 2026 Renewals'!$A:$A,$D$1+ROW()-ROW($B$13))<>$C$1,"",INDEX('January 2026 Renewals'!$H:$H,$D$1+ROW()-ROW($B$13)))) | C17: =IF($D$1="","",IF(INDEX('January 2026 Renewals'!$A:$A,$D$1+ROW()-ROW($B$13))<>$C$1,"",INDEX('January 2026 Renewals'!$C:$C,$D$1+ROW()-ROW($B$13)))) | D17: =IF($D$1="","",IF(INDEX('January 2026 Renewals'!$A:$A,$D$1+ROW()-ROW($B$13))<>$C$1,"",INDEX('January 2026 Renewals'!$E:$E,$D$1+ROW()-ROW($B$13)))) | E17: =IF($D$1="","",IF(INDEX('January 2026 Renewals'!$A:$A,$D$1+ROW()-ROW($B$13))<>$C$1,"",INDEX('January 2026 Renewals'!$G:$G,$D$1+ROW()-ROW($B$13)))) | F17: =IF($D$1="","",IF(INDEX('January 2026 Renewals'!$A:$A,$D$1+ROW()-ROW($B$13))<>$C$1,"",INDEX('January 2026 Renewals'!$I:$I,$D$1+ROW()-ROW($B$13)))) | G17: =IF($D$1="","",IF(INDEX('January 2026 Renewals'!$A:$A,$D$1+ROW()-ROW($B$13))<>$C$1,"",INDEX('January 2026 Renewals'!$Q:$Q,$D$1+ROW()-ROW($B$13)))) | H17: =IF($D$1="","",IF(INDEX('January 2026 Renewals'!$A:$A,$D$1+ROW()-ROW($B$13))<>$C$1,"",INDEX('January 2026 Renewals'!$R:$R,$D$1+ROW()-ROW($B$13)))) | I17: =IF($D$1="","",IF(INDEX('January 2026 Renewals'!$A:$A,$D$1+ROW()-ROW($B$13))<>$C$1,"",INDEX('January 2026 Renewals'!$W:$W,$D$1+ROW()-ROW($B$13)))) | J17: =IF($D$1="","",IF(INDEX('January 2026 Renewals'!$A:$A,$D$1+ROW()-ROW($B$13))<>$C$1,"",INDEX('January 2026 Renewals'!$AC:$AC,$D$1+ROW()-ROW($B$13)))) | K17: =IF($D$1="","",IF(INDEX('January 2026 Renewals'!$A:$A,$D$1+ROW()-ROW($B$13))<>$C$1,"",INDEX('January 2026 Renewals'!$AM:$AM,$D$1+ROW()-ROW($B$13))))
B18: =IF($D$1="","",IF(INDEX('January 2026 Renewals'!$A:$A,$D$1+ROW()-ROW($B$13))<>$C$1,"",INDEX('January 2026 Renewals'!$H:$H,$D$1+ROW()-ROW($B$13)))) | C18: =IF($D$1="","",IF(INDEX('January 2026 Renewals'!$A:$A,$D$1+ROW()-ROW($B$13))<>$C$1,"",INDEX('January 2026 Renewals'!$C:$C,$D$1+ROW()-ROW($B$13)))) | D18: =IF($D$1="","",IF(INDEX('January 2026 Renewals'!$A:$A,$D$1+ROW()-ROW($B$13))<>$C$1,"",INDEX('January 2026 Renewals'!$E:$E,$D$1+ROW()-ROW($B$13)))) | E18: =IF($D$1="","",IF(INDEX('January 2026 Renewals'!$A:$A,$D$1+ROW()-ROW($B$13))<>$C$1,"",INDEX('January 2026 Renewals'!$G:$G,$D$1+ROW()-ROW($B$13)))) | F18: =IF($D$1="","",IF(INDEX('January 2026 Renewals'!$A:$A,$D$1+ROW()-ROW($B$13))<>$C$1,"",INDEX('January 2026 Renewals'!$I:$I,$D$1+ROW()-ROW($B$13)))) | G18: =IF($D$1="","",IF(INDEX('January 2026 Renewals'!$A:$A,$D$1+ROW()-ROW($B$13))<>$C$1,"",INDEX('January 2026 Renewals'!$Q:$Q,$D$1+ROW()-ROW($B$13)))) | H18: =IF($D$1="","",IF(INDEX('January 2026 Renewals'!$A:$A,$D$1+ROW()-ROW($B$13))<>$C$1,"",INDEX('January 2026 Renewals'!$R:$R,$D$1+ROW()-ROW($B$13)))) | I18: =IF($D$1="","",IF(INDEX('January 2026 Renewals'!$A:$A,$D$1+ROW()-ROW($B$13))<>$C$1,"",INDEX('January 2026 Renewals'!$W:$W,$D$1+ROW()-ROW($B$13)))) | J18: =IF($D$1="","",IF(INDEX('January 2026 Renewals'!$A:$A,$D$1+ROW()-ROW($B$13))<>$C$1,"",INDEX('January 2026 Renewals'!$AC:$AC,$D$1+ROW()-ROW($B$13)))) | K18: =IF($D$1="","",IF(INDEX('January 2026 Renewals'!$A:$A,$D$1+ROW()-ROW($B$13))<>$C$1,"",INDEX('January 2026 Renewals'!$AM:$AM,$D$1+ROW()-ROW($B$13))))
B19: =IF($D$1="","",IF(INDEX('January 2026 Renewals'!$A:$A,$D$1+ROW()-ROW($B$13))<>$C$1,"",INDEX('January 2026 Renewals'!$H:$H,$D$1+ROW()-ROW($B$13)))) | C19: =IF($D$1="","",IF(INDEX('January 2026 Renewals'!$A:$A,$D$1+ROW()-ROW($B$13))<>$C$1,"",INDEX('January 2026 Renewals'!$C:$C,$D$1+ROW()-ROW($B$13)))) | D19: =IF($D$1="","",IF(INDEX('January 2026 Renewals'!$A:$A,$D$1+ROW()-ROW($B$13))<>$C$1,"",INDEX('January 2026 Renewals'!$E:$E,$D$1+ROW()-ROW($B$13)))) | E19: =IF($D$1="","",IF(INDEX('January 2026 Renewals'!$A:$A,$D$1+ROW()-ROW($B$13))<>$C$1,"",INDEX('January 2026 Renewals'!$G:$G,$D$1+ROW()-ROW($B$13)))) | F19: =IF($D$1="","",IF(INDEX('January 2026 Renewals'!$A:$A,$D$1+ROW()-ROW($B$13))<>$C$1,"",INDEX('January 2026 Renewals'!$I:$I,$D$1+ROW()-ROW($B$13)))) | G19: =IF($D$1="","",IF(INDEX('January 2026 Renewals'!$A:$A,$D$1+ROW()-ROW($B$13))<>$C$1,"",INDEX('January 2026 Renewals'!$Q:$Q,$D$1+ROW()-ROW($B$13)))) | H19: =IF($D$1="","",IF(INDEX('January 2026 Renewals'!$A:$A,$D$1+ROW()-ROW($B$13))<>$C$1,"",INDEX('January 2026 Renewals'!$R:$R,$D$1+ROW()-ROW($B$13)))) | I19: =IF($D$1="","",IF(INDEX('January 2026 Renewals'!$A:$A,$D$1+ROW()-ROW($B$13))<>$C$1,"",INDEX('January 2026 Renewals'!$W:$W,$D$1+ROW()-ROW($B$13)))) | J19: =IF($D$1="","",IF(INDEX('January 2026 Renewals'!$A:$A,$D$1+ROW()-ROW($B$13))<>$C$1,"",INDEX('January 2026 Renewals'!$AC:$AC,$D$1+ROW()-ROW($B$13)))) | K19: =IF($D$1="","",IF(INDEX('January 2026 Renewals'!$A:$A,$D$1+ROW()-ROW($B$13))<>$C$1,"",INDEX('January 2026 Renewals'!$AM:$AM,$D$1+ROW()-ROW($B$13))))
B20: Total | E20: =SUM(E13:E19) -> 3675
A21: Current Availibilities
A22: *can also include prospects that have turned down the site and why
B23: Tenant | C23: Building | D23: Suite | E23: SF | F23: Date Suite Taken Back | G23: Days on Market | H23: Market Effective Rent | I23: On Lock Box | J23: Lease Ready | K23: Comments | R23: CPI Comments
B24: Leased | C24: =IF($F$1="","",INDEX('Working - CPI'!$B:$B,$F$1+ROW()-ROW($B$24))) -> 21602 N Central | D24: =IF($F$1="","",INDEX('Working - CPI'!$C:$C,$F$1+ROW()-ROW($B$24))) -> 3 | E24: =IF($F$1="","",INDEX('Working - CPI'!$D:$D,$F$1+ROW()-ROW($B$24))) -> 2060 | F24: =IF($F$1="","",INDEX('Working - CPI'!$E:$E,$F$1+ROW()-ROW($B$24))) -> 45748 | G24: =IF($F$1="","",INDEX('Working - CPI'!$F:$F,$F$1+ROW()-ROW($B$24))) -> 261.52767 | H24: =IF($F$1="","",INDEX('Working - CPI'!$G:$G,$F$1+ROW()-ROW($B$24))) -> 1.5 | I24: =IF($F$1="","",INDEX('Working - CPI'!$H:$H,$F$1+ROW()-ROW($B$24))) -> Yes | J24: =IF($F$1="","",INDEX('Working - CPI'!$I:$I,$F$1+ROW()-ROW($B$24))) -> Yes | K24: =IF($F$1="","",INDEX('Working - CPI'!$J:$J,$F$1+ROW()-ROW($B$24))) -> epoxy flooring space | R24: Space has leased to Robo Painting
B25: =IF($F$1="","",IF(INDEX('Working - CPI'!$D:$D,$F$1+ROW()-ROW($B$24))>0,"Vacant","")) -> Vacant | C25: =IF($F$1="","",INDEX('Working - CPI'!$B:$B,$F$1+ROW()-ROW($B$24))) -> 21602 N Central | D25: =IF($F$1="","",INDEX('Working - CPI'!$C:$C,$F$1+ROW()-ROW($B$24))) -> 4 | E25: =IF($F$1="","",INDEX('Working - CPI'!$D:$D,$F$1+ROW()-ROW($B$24))) -> 2060 | F25: =IF($F$1="","",INDEX('Working - CPI'!$E:$E,$F$1+ROW()-ROW($B$24))) -> 45748 | G25: =IF($F$1="","",INDEX('Working - CPI'!$F:$F,$F$1+ROW()-ROW($B$24))) -> 261.52767 | H25: =IF($F$1="","",INDEX('Working - CPI'!$G:$G,$F$1+ROW()-ROW($B$24))) -> 1.5 | I25: =IF($F$1="","",INDEX('Working - CPI'!$H:$H,$F$1+ROW()-ROW($B$24))) -> Yes | J25: =IF($F$1="","",INDEX('Working - CPI'!$I:$I,$F$1+ROW()-ROW($B$24))) -> Yes | K25: =IF($F$1="","",INDEX('Working - CPI'!$J:$J,$F$1+ROW()-ROW($B$24))) -> epoxy flooring space | R25: Hometown HVAC was not approved dur to financials
B38: Deal Pending | C38: =SUMIF(B20:B33,B38,E20:E33) -> 0 | E38: =SUM(E24:E37) -> 4120 | G38: Vacant | H38: =SUMIF(B20:B33,G38,E20:E33) -> 2060
A39: Executed Leases | W39: NER Calculations
G40: RENT | I40: TERM | K40: TI | M40: Free Rent | O40: Bumps | P40: LCs | Q40: NER | R40: NER Check | W40: Subtotals | AB40: Budget / Actual | AE40: Term
B41: Tenant | C41: Building | D41: Suite | E41: SF | F41: Type | G41: New | H41: Budget | I41: New | J41: Budget | K41: New | L41: Budget | M41: New | N41: Budget | O41: Actual | P41: Actual | Q41: Actual | R41: =S6 -> 0 | S41: Execution | T41: Comments | W41: Revenue | X41: Bumps | Y41: TIs | Z41: LCs | AA41: FR | AB41: Rent | AC41: FR | AD41: TI | AE41: Years | AF41: Month | AG41: Total | AH41: Term Check | AM41: =AM5 -> Raleigh Light Industrial - Rent Bump Calculation | BD41: =BD5 -> Raleigh Light Industrial - Rent Bump Calculation (Monthly Rents)
B42: =IF($G$1="","",INDEX('Lease Report 2025'!$H:$H,$G$1+ROW()-ROW($B$42))) -> Claude Bryant | C42: =IF($G$1="","",INDEX('Lease Report 2025'!$D:$D,$G$1+ROW()-ROW($B$42))) -> 21616 N Central Ave | D42: =IF($G$1="","",INDEX('Lease Report 2025'!$E:$E,$G$1+ROW()-ROW($B$42))) -> 0 | E42: =IF($G$1="","",INDEX('Lease Report 2025'!$G:$G,$G$1+ROW()-ROW($B$42))) -> 1225 | F42: =IF($G$1="","",INDEX('Lease Report 2025'!$A:$A,$G$1+ROW()-ROW($B$42))) -> R | G42: =IF($G$1="","",INDEX('Lease Report 2025'!$L:$L,$G$1+ROW()-ROW($B$42))) -> 1.4 | I42: =IF($G$1="","",INDEX('Lease Report 2025'!$P:$P,$G$1+ROW()-ROW($B$42))) -> 3 | O42: =IF($G$1="","",INDEX('Lease Report 2025'!$N:$N,$G$1+ROW()-ROW($B$42))) -> 0.06 | S42: =IF($G$1="","",INDEX('Lease Report 2025'!$R:$R,$G$1+ROW()-ROW($B$42))) -> 45689 | T42: =IF($G$1="","",INDEX('Lease Report 2025'!$O:$O,$G$1+ROW()-ROW($B$42))) -> Tenant signed 3 year renewal
B43: =IF($G$1="","",INDEX('Lease Report 2025'!$H:$H,$G$1+ROW()-ROW($B$42))) -> James Cartwright a/b/a Vision Scape | C43: =IF($G$1="","",INDEX('Lease Report 2025'!$D:$D,$G$1+ROW()-ROW($B$42))) -> 21616 N Centerl | D43: =IF($G$1="","",INDEX('Lease Report 2025'!$E:$E,$G$1+ROW()-ROW($B$42))) -> 16 | E43: =IF($G$1="","",INDEX('Lease Report 2025'!$G:$G,$G$1+ROW()-ROW($B$42))) -> 1225 | F43: =IF($G$1="","",INDEX('Lease Report 2025'!$A:$A,$G$1+ROW()-ROW($B$42))) -> New | G43: =IF($G$1="","",INDEX('Lease Report 2025'!$L:$L,$G$1+ROW()-ROW($B$42))) -> 1.47 | I43: =IF($G$1="","",INDEX('Lease Report 2025'!$P:$P,$G$1+ROW()-ROW($B$42))) -> 5 | O43: =IF($G$1="","",INDEX('Lease Report 2025'!$N:$N,$G$1+ROW()-ROW($B$42))) -> 0.05 | S43: =IF($G$1="","",INDEX('Lease Report 2025'!$R:$R,$G$1+ROW()-ROW($B$42))) -> 45748 | T43: =IF($G$1="","",INDEX('Lease Report 2025'!$O:$O,$G$1+ROW()-ROW($B$42))) -> 2
B44: =IF($G$1="","",INDEX('Lease Report 2025'!$H:$H,$G$1+ROW()-ROW($B$42))) -> Quiiriego Restaurant, LLC | C44: =IF($G$1="","",INDEX('Lease Report 2025'!$D:$D,$G$1+ROW()-ROW($B$42))) -> 21628 N Central | D44: =IF($G$1="","",INDEX('Lease Report 2025'!$E:$E,$G$1+ROW()-ROW($B$42))) -> 8 | E44: =IF($G$1="","",INDEX('Lease Report 2025'!$G:$G,$G$1+ROW()-ROW($B$42))) -> 2060 | F44: =IF($G$1="","",INDEX('Lease Report 2025'!$A:$A,$G$1+ROW()-ROW($B$42))) -> New | G44: =IF($G$1="","",INDEX('Lease Report 2025'!$L:$L,$G$1+ROW()-ROW($B$42))) -> 1.42 | I44: =IF($G$1="","",INDEX('Lease Report 2025'!$P:$P,$G$1+ROW()-ROW($B$42))) -> 3 | O44: =IF($G$1="","",INDEX('Lease Report 2025'!$N:$N,$G$1+ROW()-ROW($B$42))) -> 0.085 | S44: =IF($G$1="","",INDEX('Lease Report 2025'!$R:$R,$G$1+ROW()-ROW($B$42))) -> 45748 | T44: =IF($G$1="","",INDEX('Lease Report 2025'!$O:$O,$G$1+ROW()-ROW($B$42))) -> 1
B45: =IF($G$1="","",INDEX('Lease Report 2025'!$H:$H,$G$1+ROW()-ROW($B$42))) -> Pool Barrier of AZ | C45: =IF($G$1="","",INDEX('Lease Report 2025'!$D:$D,$G$1+ROW()-ROW($B$42))) -> 21616 N Central Ave | D45: =IF($G$1="","",INDEX('Lease Report 2025'!$E:$E,$G$1+ROW()-ROW($B$42))) -> 15 | E45: =IF($G$1="","",INDEX('Lease Report 2025'!$G:$G,$G$1+ROW()-ROW($B$42))) -> 1225 | F45: =IF($G$1="","",INDEX('Lease Report 2025'!$A:$A,$G$1+ROW()-ROW($B$42))) -> R | G45: =IF($G$1="","",INDEX('Lease Report 2025'!$L:$L,$G$1+ROW()-ROW($B$42))) -> 1.4 | I45: =IF($G$1="","",INDEX('Lease Report 2025'!$P:$P,$G$1+ROW()-ROW($B$42))) -> 3 | O45: =IF($G$1="","",INDEX('Lease Report 2025'!$N:$N,$G$1+ROW()-ROW($B$42))) -> 0.06 | S45: =IF($G$1="","",INDEX('Lease Report 2025'!$R:$R,$G$1+ROW()-ROW($B$42))) -> 45748 | T45: =IF($G$1="","",INDEX('Lease Report 2025'!$O:$O,$G$1+ROW()-ROW($B$42))) -> Tenant agreed to a 3 year MG renewal
B46: =IF($G$1="","",INDEX('Lease Report 2025'!$H:$H,$G$1+ROW()-ROW($B$42))) -> Rich Interiors | C46: =IF($G$1="","",INDEX('Lease Report 2025'!$D:$D,$G$1+ROW()-ROW($B$42))) -> 21616 N Central Ave | D46: =IF($G$1="","",INDEX('Lease Report 2025'!$E:$E,$G$1+ROW()-ROW($B$42))) -> 5, 11, 12, 13 | E46: =IF($G$1="","",INDEX('Lease Report 2025'!$G:$G,$G$1+ROW()-ROW($B$42))) -> 4900 | F46: =IF($G$1="","",INDEX('Lease Report 2025'!$A:$A,$G$1+ROW()-ROW($B$42))) -> R | G46: =IF($G$1="","",INDEX('Lease Report 2025'!$L:$L,$G$1+ROW()-ROW($B$42))) -> 1.35 | I46: =IF($G$1="","",INDEX('Lease Report 2025'!$P:$P,$G$1+ROW()-ROW($B$42))) -> 3 | O46: =IF($G$1="","",INDEX('Lease Report 2025'!$N:$N,$G$1+ROW()-ROW($B$42))) -> 0.06 | S46: =IF($G$1="","",INDEX('Lease Report 2025'!$R:$R,$G$1+ROW()-ROW($B$42))) -> 45748 | T46: =IF($G$1="","",INDEX('Lease Report 2025'!$O:$O,$G$1+ROW()-ROW($B$42))) -> Tenant agreed to a 3 year renewal - MG lease
B47: =IF($G$1="","",INDEX('Lease Report 2025'!$H:$H,$G$1+ROW()-ROW($B$42))) -> Scudo Divers, LLC | C47: =IF($G$1="","",INDEX('Lease Report 2025'!$D:$D,$G$1+ROW()-ROW($B$42))) -> 21602 N Central Ave | D47: =IF($G$1="","",INDEX('Lease Report 2025'!$E:$E,$G$1+ROW()-ROW($B$42))) -> 7 | E47: =IF($G$1="","",INDEX('Lease Report 2025'!$G:$G,$G$1+ROW()-ROW($B$42))) -> 4120 | F47: =IF($G$1="","",INDEX('Lease Report 2025'!$A:$A,$G$1+ROW()-ROW($B$42))) -> R | G47: =IF($G$1="","",INDEX('Lease Report 2025'!$L:$L,$G$1+ROW()-ROW($B$42))) -> 1.35 | I47: =IF($G$1="","",INDEX('Lease Report 2025'!$P:$P,$G$1+ROW()-ROW($B$42))) -> 3 | O47: =IF($G$1="","",INDEX('Lease Report 2025'!$N:$N,$G$1+ROW()-ROW($B$42))) -> 0.06 | S47: =IF($G$1="","",INDEX('Lease Report 2025'!$R:$R,$G$1+ROW()-ROW($B$42))) -> 45778 | T47: =IF($G$1="","",INDEX('Lease Report 2025'!$O:$O,$G$1+ROW()-ROW($B$42))) -> No TI, No Free rent, No outside agent, Base Year Gross
B48: =IF($G$1="","",INDEX('Lease Report 2025'!$H:$H,$G$1+ROW()-ROW($B$42))) -> AZ Gun Works | C48: =IF($G$1="","",INDEX('Lease Report 2025'!$D:$D,$G$1+ROW()-ROW($B$42))) -> 21628 N Central Ave | D48: =IF($G$1="","",INDEX('Lease Report 2025'!$E:$E,$G$1+ROW()-ROW($B$42))) -> 3 | E48: =IF($G$1="","",INDEX('Lease Report 2025'!$G:$G,$G$1+ROW()-ROW($B$42))) -> 2060 | F48: =IF($G$1="","",INDEX('Lease Report 2025'!$A:$A,$G$1+ROW()-ROW($B$42))) -> R | G48: =IF($G$1="","",INDEX('Lease Report 2025'!$L:$L,$G$1+ROW()-ROW($B$42))) -> 1.3 | I48: =IF($G$1="","",INDEX('Lease Report 2025'!$P:$P,$G$1+ROW()-ROW($B$42))) -> 5 | O48: =IF($G$1="","",INDEX('Lease Report 2025'!$N:$N,$G$1+ROW()-ROW($B$42))) -> 0.05 | S48: =IF($G$1="","",INDEX('Lease Report 2025'!$R:$R,$G$1+ROW()-ROW($B$42))) -> 45839 | T48: =IF($G$1="","",INDEX('Lease Report 2025'!$O:$O,$G$1+ROW()-ROW($B$42))) -> Tenant has agreed to a 5 year MG Renewal
B49: =IF($G$1="","",INDEX('Lease Report 2025'!$H:$H,$G$1+ROW()-ROW($B$42))) -> Bruno's Shooting Supply | C49: =IF($G$1="","",INDEX('Lease Report 2025'!$D:$D,$G$1+ROW()-ROW($B$42))) -> 21628 N Central Ave | D49: =IF($G$1="","",INDEX('Lease Report 2025'!$E:$E,$G$1+ROW()-ROW($B$42))) -> 4 & 5 | E49: =IF($G$1="","",INDEX('Lease Report 2025'!$G:$G,$G$1+ROW()-ROW($B$42))) -> 4120 | F49: =IF($G$1="","",INDEX('Lease Report 2025'!$A:$A,$G$1+ROW()-ROW($B$42))) -> R | G49: =IF($G$1="","",INDEX('Lease Report 2025'!$L:$L,$G$1+ROW()-ROW($B$42))) -> 1.3 | I49: =IF($G$1="","",INDEX('Lease Report 2025'!$P:$P,$G$1+ROW()-ROW($B$42))) -> 5 | O49: =IF($G$1="","",INDEX('Lease Report 2025'!$N:$N,$G$1+ROW()-ROW($B$42))) -> 0.05 | S49: =IF($G$1="","",INDEX('Lease Report 2025'!$R:$R,$G$1+ROW()-ROW($B$42))) -> 45839 | T49: =IF($G$1="","",INDEX('Lease Report 2025'!$O:$O,$G$1+ROW()-ROW($B$42))) -> Tenant has agreed to a 5 year MG Renewal
B50: =IF($G$1="","",INDEX('Lease Report 2025'!$H:$H,$G$1+ROW()-ROW($B$42))) -> Moto Garage | C50: =IF($G$1="","",INDEX('Lease Report 2025'!$D:$D,$G$1+ROW()-ROW($B$42))) -> 21628 N Central Ave | D50: =IF($G$1="","",INDEX('Lease Report 2025'!$E:$E,$G$1+ROW()-ROW($B$42))) -> 1 & 2 | E50: =IF($G$1="","",INDEX('Lease Report 2025'!$G:$G,$G$1+ROW()-ROW($B$42))) -> 4120 | F50: =IF($G$1="","",INDEX('Lease Report 2025'!$A:$A,$G$1+ROW()-ROW($B$42))) -> R | G50: =IF($G$1="","",INDEX('Lease Report 2025'!$L:$L,$G$1+ROW()-ROW($B$42))) -> 1.4 | I50: =IF($G$1="","",INDEX('Lease Report 2025'!$P:$P,$G$1+ROW()-ROW($B$42))) -> 3 | O50: =IF($G$1="","",INDEX('Lease Report 2025'!$N:$N,$G$1+ROW()-ROW($B$42))) -> 0.06 | S50: =IF($G$1="","",INDEX('Lease Report 2025'!$R:$R,$G$1+ROW()-ROW($B$42))) -> 45839 | T50: =IF($G$1="","",INDEX('Lease Report 2025'!$O:$O,$G$1+ROW()-ROW($B$42))) -> Tenant has agreed to a 3 year MG Renewal
B51: =IF($G$1="","",INDEX('Lease Report 2025'!$H:$H,$G$1+ROW()-ROW($B$42))) -> Gecko Garage Doors Inc Doors | C51: =IF($G$1="","",INDEX('Lease Report 2025'!$D:$D,$G$1+ROW()-ROW($B$42))) -> 21606 N Central | D51: =IF($G$1="","",INDEX('Lease Report 2025'!$E:$E,$G$1+ROW()-ROW($B$42))) -> 14 | E51: =IF($G$1="","",INDEX('Lease Report 2025'!$G:$G,$G$1+ROW()-ROW($B$42))) -> 1225 | F51: =IF($G$1="","",INDEX('Lease Report 2025'!$A:$A,$G$1+ROW()-ROW($B$42))) -> New | G51: =IF($G$1="","",INDEX('Lease Report 2025'!$L:$L,$G$1+ROW()-ROW($B$42))) -> 1.47 | I51: =IF($G$1="","",INDEX('Lease Report 2025'!$P:$P,$G$1+ROW()-ROW($B$42))) -> 3 | O51: =IF($G$1="","",INDEX('Lease Report 2025'!$N:$N,$G$1+ROW()-ROW($B$42))) -> 0.06 | S51: =IF($G$1="","",INDEX('Lease Report 2025'!$R:$R,$G$1+ROW()-ROW($B$42))) -> 45870 | T51: =IF($G$1="","",INDEX('Lease Report 2025'!$O:$O,$G$1+ROW()-ROW($B$42))) -> 1
B52: =IF($G$1="","",INDEX('Lease Report 2025'!$H:$H,$G$1+ROW()-ROW($B$42))) -> Import Care Center/Benz | C52: =IF($G$1="","",INDEX('Lease Report 2025'!$D:$D,$G$1+ROW()-ROW($B$42))) -> 21602 N Central Ave | D52: =IF($G$1="","",INDEX('Lease Report 2025'!$E:$E,$G$1+ROW()-ROW($B$42))) -> 1 | E52: =IF($G$1="","",INDEX('Lease Report 2025'!$G:$G,$G$1+ROW()-ROW($B$42))) -> 2060 | F52: =IF($G$1="","",INDEX('Lease Report 2025'!$A:$A,$G$1+ROW()-ROW($B$42))) -> R | G52: =IF($G$1="","",INDEX('Lease Report 2025'!$L:$L,$G$1+ROW()-ROW($B$42))) -> 1.4 | I52: =IF($G$1="","",INDEX('Lease Report 2025'!$P:$P,$G$1+ROW()-ROW($B$42))) -> 3 | O52: =IF($G$1="","",INDEX('Lease Report 2025'!$N:$N,$G$1+ROW()-ROW($B$42))) -> 0.06 | S52: =IF($G$1="","",INDEX('Lease Report 2025'!$R:$R,$G$1+ROW()-ROW($B$42))) -> 45870 | T52: =IF($G$1="","",INDEX('Lease Report 2025'!$O:$O,$G$1+ROW()-ROW($B$42))) -> Tenant signed a new 3 year MG renewal
B53: =IF($G$1="","",INDEX('Lease Report 2025'!$H:$H,$G$1+ROW()-ROW($B$42))) -> D&A Partners LLC | C53: =IF($G$1="","",INDEX('Lease Report 2025'!$D:$D,$G$1+ROW()-ROW($B$42))) -> 21602 N Central | D53: =IF($G$1="","",INDEX('Lease Report 2025'!$E:$E,$G$1+ROW()-ROW($B$42))) -> 5,6 | E53: =IF($G$1="","",INDEX('Lease Report 2025'!$G:$G,$G$1+ROW()-ROW($B$42))) -> 4120 | F53: =IF($G$1="","",INDEX('Lease Report 2025'!$A:$A,$G$1+ROW()-ROW($B$42))) -> New | G53: =IF($G$1="","",INDEX('Lease Report 2025'!$L:$L,$G$1+ROW()-ROW($B$42))) -> 1.4 | I53: =IF($G$1="","",INDEX('Lease Report 2025'!$P:$P,$G$1+ROW()-ROW($B$42))) -> 3 | O53: =IF($G$1="","",INDEX('Lease Report 2025'!$N:$N,$G$1+ROW()-ROW($B$42))) -> 0.05 | S53: =IF($G$1="","",INDEX('Lease Report 2025'!$R:$R,$G$1+ROW()-ROW($B$42))) -> 45931 | T53: =IF($G$1="","",INDEX('Lease Report 2025'!$O:$O,$G$1+ROW()-ROW($B$42))) -> 0
B54: =IF($G$1="","",INDEX('Lease Report 2025'!$H:$H,$G$1+ROW()-ROW($B$42))) -> Two Brother's Auto Restoration | C54: =IF($G$1="","",INDEX('Lease Report 2025'!$D:$D,$G$1+ROW()-ROW($B$42))) -> 21616 &21628 N Central Av3 | D54: =IF($G$1="","",INDEX('Lease Report 2025'!$E:$E,$G$1+ROW()-ROW($B$42))) -> 3, 4, 8 | E54: =IF($G$1="","",INDEX('Lease Report 2025'!$G:$G,$G$1+ROW()-ROW($B$42))) -> 4510 | F54: =IF($G$1="","",INDEX('Lease Report 2025'!$A:$A,$G$1+ROW()-ROW($B$42))) -> RX | G54: =IF($G$1="","",INDEX('Lease Report 2025'!$L:$L,$G$1+ROW()-ROW($B$42))) -> 1.42 | I54: =IF($G$1="","",INDEX('Lease Report 2025'!$P:$P,$G$1+ROW()-ROW($B$42))) -> 3 | O54: =IF($G$1="","",INDEX('Lease Report 2025'!$N:$N,$G$1+ROW()-ROW($B$42))) -> 0.06 | S54: =IF($G$1="","",INDEX('Lease Report 2025'!$R:$R,$G$1+ROW()-ROW($B$42))) -> 45992 | T54: =IF($G$1="","",INDEX('Lease Report 2025'!$O:$O,$G$1+ROW()-ROW($B$42))) -> Tenant is increasing 835 sf and signing a 3 year MG renewal
B55: Robo Painting | C55: 21602 N Central Ave | D55: 3 | E55: 2060 | F55: New | G55: 1.5 | I55: 5 | O55: 0.05 | S55: 45992 | T55: Tenant signed a 5 year lease MG lease
A56: Dead Deals
A57: *can also include prospects that have turned down the site and why
A58: Broker | B58: Tenant | C58: Building | D58: Suite | E58: SF | F58: Expiration | L58: 8

Sheet 336_RR
D2: CENTRAL DEER VALLEY
C3: As Of : 11/21/2025
E5: SQFT | H5: Annual | I5: Monthly | N5: Rent | AC5: Lease
A6: Suite | B6: Tenant Name | E6: Rentable | G6: Leased | H6: Rent | I6: Rent | K6: P.S.F | L6: Suite(s) | N6: Begin | T6: End | W6: Base Rent | X6: P.S.F | AC6: Begin | AD6: End
A7: 602-01 | B7: ECU SYSTEMS, LLC | E7: 2060 | G7: 2060 | H7: 34608 | I7: 2884 | K7: 16.8 | N7: 45870 | T7: 46234 | W7: 2884 | X7: 16.8 | AC7: 45870 | AD7: 07/31/2028
N8: 46235 | T8: 46599 | W8: 3007.6 | X8: 17.52
N9: 46600 | T9: 46965 | W9: 3131.2 | X9: 18.24
A11: 602-02 | B11: LK TECHNICA SERVICES, LLC | E11: 2060 | G11: 2060 | H11: 37327.2 | I11: 3110.6 | K11: 18.12 | N11: 45778 | T11: 46142 | W11: 3110.6 | X11: 18.12 | AC11: 45413 | AD11: 04/30/2027
N12: 46143 | T12: 46507 | W12: 3234.2 | X12: 18.84
A14: 602-03 | B14: Vacant | E14: 2060 | G14: 0 | K14: 0 | X14: 0
A16: 602-04 | B16: Vacant | E16: 2060 | G16: 0 | K16: 0 | X16: 0
A18: 602-05 | B18: D&A PARTNERS LLC | E18: 2060 | G18: 2060 | H18: 69216 | I18: 5768 | K18: 16.8 | L18: 602-05, 602-06 | N18: 45931 | T18: 46295 | W18: 5768 | X18: 16.8 | AC18: 45931 | AD18: 09/30/2028
N19: 46296 | T19: 46660 | W19: 5974 | X19: 17.4
N20: 46661 | T20: 47026 | W20: 6180 | X20: 18
A22: 602-06 | B22: D&A PARTNERS LLC | E22: 2060 | G22: 2060 | K22: 0 | L22: 602-05, 602-06 | X22: 0 | AC22: 45931 | AD22: 09/30/2028
A24: 602-07 | B24: SCUDO DRIVERS LLC | E24: 2060 | G24: 2060 | H24: 66744 | I24: 5562 | K24: 16.2 | L24: 602-07, 602-08 | N24: 45778 | T24: 46142 | W24: 5562 | X24: 16.2 | AC24: 45778 | AD24: 04/30/2028
N25: 46143 | T25: 46507 | W25: 5809.2 | X25: 16.92
N26: 46508 | T26: 46873 | W26: 6056.4 | X26: 17.64
A28: 602-08 | B28: SCUDO DRIVERS LLC | E28: 2060 | G28: 2060 | K28: 0 | L28: 602-07, 602-08 | X28: 0 | AC28: 45778 | AD28: 04/30/2028
A30: 616-01 | B30: MANNINO CUSTOM FURNITURE & AMERICAN CLASSIC FLOORING | E30: 1225 | G30: 1225 | H30: 63945 | I30: 5328.75 | K30: 17.4 | L30: 616-01, 616-02, 616-10 | N30: 45748 | T30: 46112 | W30: 5328.75 | X30: 17.4 | AC30: 45017 | AD30: 03/31/2026
A32: 616-02 | B32: MANNINO CUSTOM FURNITURE & AMERICAN CLASSIC FLOORING | E32: 1225 | G32: 1225 | K32: 0 | L32: 616-01, 616-02, 616-10 | X32: 0 | AC32: 45017 | AD32: 03/31/2026
A34: 616-03 | B34: TWO BROTHERS AUTO RESTORATION, LLC | E34: 1225 | G34: 1225 | H34: 55125 | I34: 4593.75 | K34: 15 | L34: 616-03, 616-04, 616-08 | N34: 45627 | T34: 45991 | W34: 4593.75 | X34: 15 | AC34: 44896 | AD34: 11/30/2025
B35: <RENEWAL> TWO BROTHERS AUTO RESTORATION, LLC | K35: 0 | L35: 616-03, 616-04, 628-06 | N35: 45992 | T35: 46356 | W35: 6404.2 | X35: 17.04 | AC35: 45992 | AD35: 11/30/2028
N36: 46357 | T36: 46721 | W36: 6674.8 | X36: 17.76
N37: 46722 | T37: 47087 | W37: 6945.4 | X37: 18.48
A39: 616-04 | B39: TWO BROTHERS AUTO RESTORATION, LLC | E39: 1225 | G39: 1225 | K39: 0 | L39: 616-03, 616-04, 616-08 | X39: 0 | AC39: 44896 | AD39: 11/30/2025
B40: <RENEWAL> TWO BROTHERS AUTO RESTORATION, LLC | L40: 616-03, 616-04, 628-06 | X40: 0 | AC40: 45992 | AD40: 11/30/2028
A42: 616-05 | B42: RICH INTERIOR | E42: 1225 | G42: 1225 | H42: 79380 | I42: 6615 | K42: 16.2 | L42: 616-05, 616-11, 616-12, 616-13 | N42: 45748 | T42: 46112 | W42: 6615 | X42: 16.2 | AC42: 45748 | AD42: 03/31/2028
N43: 46113 | T43: 46477 | W43: 6909 | X43: 16.92
N44: 46478 | T44: 46843 | W44: 7203 | X44: 17.64
A46: 616-06 | B46: SOARING EAGLE ADVENTURES ARIZONA, LLC | E46: 1225 | G46: 1225 | H46: 22050 | I46: 1837.5 | K46: 18 | N46: 45809 | T46: 46173 | W46: 1837.5 | X46: 18 | AC46: 45413 | AD46: 05/31/2027
N47: 46174 | T47: 46538 | W47: 1898.75 | X47: 18.6
A49: 616-07 | B49: CLAUDE BRYANT | E49: 1225 | G49: 1225 | H49: 20580 | I49: 1715 | K49: 16.8 | N49: 45689 | T49: 46053 | W49: 1715 | X49: 16.8 | AC49: 45689 | AD49: 01/31/2028
N50: 46054 | T50: 46418 | W50: 1788.5 | X50: 17.52
N51: 46419 | T51: 46783 | W51: 1862 | X51: 18.24
A53: 616-08 | B53: TWO BROTHERS AUTO RESTORATION, LLC | E53: 1225 | G53: 1225 | K53: 0 | L53: 616-03, 616-04, 616-08 | X53: 0 | AC53: 44896 | AD53: 11/30/2025
A55: 616-09 | B55: ENGINES DIRECT | E55: 1225 | G55: 1225 | H55: 22050 | I55: 1837.5 | K55: 18 | N55: 45689 | T55: 46053 | W55: 1837.5 | X55: 18 | AC55: 45323 | AD55: 01/31/2027
N56: 46054 | T56: 46418 | W56: 1898.75 | X56: 18.6
A58: 616-10 | B58: MANNINO CUSTOM FURNITURE & AMERICAN CLASSIC FLOORING | E58: 1225 | G58: 1225 | K58: 0 | L58: 616-01, 616-02, 616-10 | X58: 0 | AC58: 45017 | AD58: 03/31/2026
A60: 616-11 | B60: RICH INTERIOR | E60: 1225 | G60: 1225 | K60: 0 | L60: 616-05, 616-11, 616-12, 616-13 | X60: 0 | AC60: 45748 | AD60: 03/31/2028
